Workbook

Sheet Médicos
A1: FECHA | B1: INVNUM | C1: COMPROBANTE | D1: FACTURA | E1: TIPO PAGO | F1: # DOC | G1: PACIENTE | H1: DNI | I1: MEDICO | J1: INSTITUCIÓN | K1: CARTERA | L1: HISTORIA | M1: TELEFONO | N1: RAZON SOCIAL | O1: PREFACTURA | P1: DESCRIPCION | Q1: CANTIDAD | R1: DESCRIP PLAN | S1: CONTRATANTE | T1: ASEGURADORA | U1: SEDEXX | V1: FACTURADOR | W1: FAC TOTAL | X1: CENTRO_COSTO | Y1: CONVENIO | Z1: SEDE | AA1: CELULAR | AB1: CUENTA BANCARIA
A2: 46174 | B2: 97734 | C2: BO | D2: 5483 | E2: CO | F2: BO-5483 | G2: MARIN DIAZ JORGE MARCIAL | H2: 06105706 | I2: ORNA ACOSTA JORGE AQUILES | J2: HOSPITAL LOAYZA | K2: CRISTINA | L2: 0069701 | M2: 990056060 | N2: MARIN DIAZ JORGE MARCIAL | O2: 85829 | P2: OCT DE MACULA | Q2: 1 | R2: PRECISA | S2: POR ASIGNAR | T2: INSTITUTO MEDICO QUIRURGICO AREQUIPA S.A | U2: L.CENTRO | V2: ACABRERA | W2: 186.44 | X2: LN. EXAMENES | Y2: CIAS. DE SEGURO | Z2: CENTRO | AA2: 999996347 | AB2: 052-7510523
A3: 46174 | B3: 97768 | C3: BO | D3: 11380 | E3: CO | F3: BO-11380 | G3: DAVILA URIBE JOSELUIS FRANKLIN | H3: 63710675 | I3: PEÑA CAMARGO CRISTOPHER OMAR | J3: HOSPITAL SERGIO BERNALES | K3: CRISTINA | L3: 0069713 | M3: 916691513 | N3: DAVILA URIBE JOSELUIS FRANKLIN | O3: 85858 | P3: OCT DE MACULA | Q3: 1 | R3: PRECISA | S3: POR ASIGNAR | T3: INSTITUTO MEDICO QUIRURGICO AREQUIPA S.A | U3: L.CENTRO | V3: LMAGAN | W3: 186.44 | X3: LN. EXAMENES | Y3: CIAS. DE SEGURO | Z3: CENTRO | AA3: 964328569 | AB3: 191-70241223029
A4: 46174 | B4: 97737 | C4: BO | D4: 5485 | E4: CO | F4: BO-5485 | G4: JIMENEZ BORCKARDT MARIA ELENA | H4: 09175695 | I4: TORRES LEAL ADOLFO LEON | J4: CLÍNICA SAN FELIPE LA MOLINA | K4: CRISTINA | L4: 0069704 | M4: 962711137 | N4: JIMENEZ BORCKARDT MARIA ELENA | O4: 85831 | P4: ECOGRAFIA OCULAR GENERAL SCAN A,B | Q4: 1 | R4: PRECISA | S4: POR ASIGNAR | T4: INSTITUTO MEDICO QUIRURGICO AREQUIPA S.A | U4: L.CENTRO | V4: ACABRERA | W4: 135.59 | X4: LN. EXAMENES | Y4: CIAS. DE SEGURO | Z4: CENTRO | AA4: 999421990
A5: 46174 | B5: 97761 | C5: BO | D5: 11378 | E5: CO | F5: BO-11378 | G5: SANDOVAL SANTAMARIA ANTERO | H5: 17562410 | I5: HUARANGA RUIZ CORNEJO JORGE ERNESTO | J5: HOSPITAL MONGRUT | K5: CRISTINA | L5: 0069712 | M5: 956259223 | N5: SANDOVAL SANTAMARIA ANTERO | O5: 85854 | P5: ECOGRAFIA OCULAR GENERAL SCAN A,B | Q5: 1 | R5: PRECISA | S5: POR ASIGNAR | T5: INSTITUTO MEDICO QUIRURGICO AREQUIPA S.A | U5: L.CENTRO | V5: LMAGAN | W5: 135.59 | X5: LN. EXAMENES | Y5: CIAS. DE SEGURO | Z5: CENTRO | AA5: 945319366 | AB5: 194-94066798065
A6: 46174 | B6: 97762 | C6: BO | D6: 3764 | E6: CO | F6: BO-3764 | G6: DIAZ DIAZ MARIA JUANA | H6: 48820433 | I6: AGRAMONTE ZEA EDILBERTO | J6: HOSPITAL DE LA SOLIDARIDAD SJL | K6: CRISTINA | L6: 0068509 | M6: 980843789 | N6: DIAZ DIAZ MARIA JUANA | O6: 85855 | P6: ECOGRAFIA OCULAR GENERAL SCAN A,B | Q6: 1 | R6: PRECISA LN | S6: POR ASIGNAR | T6: INSTITUTO MEDICO QUIRURGICO AREQUIPA S.A | U6: L.NORTE | V6: BGALLOSA | W6: 135.59 | X6: LN. EXAMENES | Y6: CIAS. DE SEGURO | Z6: NORTE | AA6: 987407712 | AB6: 0011-0190-0200333106
A7: 46174 | B7: 97751 | C7: BO | D7: 11374 | E7: CO | F7: BO-11374 | G7: HERRERA GRANDA VANNIA LUZ | H7: 77928579 | I7: PEÑA CAMARGO CRISTOPHER OMAR | J7: HOSPITAL SERGIO BERNALES | K7: CRISTINA | L7: 0067338 | M7: 953421025 | N7: HERRERA GRANDA VANNIA LUZ | O7: 85844 | P7: OCT DE NERVIO OPTICO Y CELULAS GANGLION | Q7: 1 | R7: PRECISA | S7: POR ASIGNAR | T7: INSTITUTO MEDICO QUIRURGICO AREQUIPA S.A | U7: L.CENTRO | V7: LMAGAN | W7: 186.44 | X7: LN. EXAMENES | Y7: CIAS. DE SEGURO | Z7: CENTRO | AA7: 964328569 | AB7: 191-70241223029
A8: 46175 | B8: 97877 | C8: BO | D8: 5505 | E8: CO | F8: BO-5505 | G8: REATEGUI VALLES REITER | H8: 01092510 | I8: MANSILLA JUAN JOSÉ | J8: CONSULTORIO PARTICULAR | K8: CRISTINA | L8: 0069757 | M8: 931872630 | N8: REATEGUI VALLES REITER | O8: 85945 | P8: USO DE EQUIPOS E INSUMO AVASTIN | Q8: 1 | R8: PRECISA | S8: POR ASIGNAR | T8: INSTITUTO MEDICO QUIRURGICO AREQUIPA S.A | U8: L.CENTRO | V8: ACABRERA | W8: 254.24 | X8: LN. PROCEDIMIENTO | Y8: CIAS. DE SEGURO | Z8: CENTRO
A9: 46176 | B9: 97907 | C9: BO | D9: 5506 | E9: CO | F9: BO-5506 | G9: MOTTA MARTINEZ JUSTINA OTILIA | H9: 08795262 | I9: RODRIGUEZ CECILIA | J9: POLICLÍNICO DIVINO NIÑO JESÚS | K9: CRISTINA | L9: 0054360 | M9: 901653281 | N9: MOTTA MARTINEZ JUSTINA OTILIA | O9: 85960 | P9: CAMPIMETRIA (CAMPO VISUAL) | Q9: 1 | R9: PRECISA | S9: POR ASIGNAR | T9: INSTITUTO MEDICO QUIRURGICO AREQUIPA S.A | U9: L.CENTRO | V9: ACABRERA | W9: 135.59 | X9: LN. EXAMENES | Y9: CIAS. DE SEGURO | Z9: CENTRO
A10: 46176 | B10: 97912 | C10: BO | D10: 11395 | E10: CO | F10: BO-11395 | G10: MEDINA SILVESTRE GERONIMO | H10: 06279020 | I10: GUTARRA PAUCAR JULIA KARINA | J10: CLÍNICA SAN CAMILO | K10: CRISTINA | L10: 0069754 | M10: 997332688 | N10: MEDINA SILVESTRE GERONIMO | O10: 85967 | P10: OCT DE MACULA | Q10: 1 | R10: PRECISA | S10: POR ASIGNAR | T10: INSTITUTO MEDICO QUIRURGICO AREQUIPA S.A | U10: L.CENTRO | V10: LMAGAN | W10: 186.44 | X10: LN. EXAMENES | Y10: CIAS. DE SEGURO | Z10: CENTRO | AA10: 982673362 | AB10: 0011-0353-0200308107
A11: 46176 | B11: 97912 | C11: BO | D11: 11395 | E11: CO | F11: BO-11395 | G11: MEDINA SILVESTRE GERONIMO | H11: 06279020 | I11: GUTARRA PAUCAR JULIA KARINA | J11: CLÍNICA SAN CAMILO | K11: CRISTINA | L11: 0069754 | M11: 997332688 | N11: MEDINA SILVESTRE GERONIMO | O11: 85967 | P11: OCT DE NERVIO OPTICO Y CELULAS GANGLION | Q11: 1 | R11: PRECISA | S11: POR ASIGNAR | T11: INSTITUTO MEDICO QUIRURGICO AREQUIPA S.A | U11: L.CENTRO | V11: LMAGAN | W11: 186.44 | X11: LN. EXAMENES | Y11: CIAS. DE SEGURO | Z11: CENTRO | AA11: 982673362 | AB11: 0011-0353-0200308107
A12: 46176 | B12: 97956 | C12: BO | D12: 11402 | E12: CO | F12: BO-11402 | G12: GARCIA DE SANCHEZ MATILDE | H12: 27062832 | I12: GUTARRA PAUCAR JULIA KARINA | J12: CLÍNICA SAN CAMILO | K12: CRISTINA | L12: 0069790 | M12: 917095913 | N12: GARCIA DE SANCHEZ MATILDE | O12: 86014 | P12: OCT DE MACULA | Q12: 1 | R12: PRECISA | S12: POR ASIGNAR | T12: INSTITUTO MEDICO QUIRURGICO AREQUIPA S.A | U12: L.CENTRO | V12: LMAGAN | W12: 186.44 | X12: LN. EXAMENES | Y12: CIAS. DE SEGURO | Z12: CENTRO | AA12: 982673362 | AB12: 0011-0353-0200308107
A13: 46176 | B13: 97956 | C13: BO | D13: 11402 | E13: CO | F13: BO-11402 | G13: GARCIA DE SANCHEZ MATILDE | H13: 27062832 | I13: GUTARRA PAUCAR JULIA KARINA | J13: CLÍNICA SAN CAMILO | K13: CRISTINA | L13: 0069790 | M13: 917095913 | N13: GARCIA DE SANCHEZ MATILDE | O13: 86014 | P13: OCT DE NERVIO OPTICO Y CELULAS GANGLION | Q13: 1 | R13: PRECISA | S13: POR ASIGNAR | T13: INSTITUTO MEDICO QUIRURGICO AREQUIPA S.A | U13: L.CENTRO | V13: LMAGAN | W13: 186.44 | X13: LN. EXAMENES | Y13: CIAS. DE SEGURO | Z13: CENTRO | AA13: 982673362 | AB13: 0011-0353-0200308107
A14: 46176 | B14: 97979 | C14: BO | D14: 11406 | E14: CO | F14: BO-11406 | G14: PEREZ SANCHEZ GIOVANNA MARIELA | H14: 25792949 | I14: BOBBIO PEREZ MILKO | J14: CONSULTORIO | K14: CRISTINA | L14: 0069797 | M14: 946068386 | N14: PEREZ SANCHEZ GIOVANNA MARIELA | O14: 86027 | P14: OCT DE MACULA | Q14: 1 | R14: PRECISA | S14: POR ASIGNAR | T14: INSTITUTO MEDICO QUIRURGICO AREQUIPA S.A | U14: L.CENTRO | V14: LMAGAN | W14: 186.44 | X14: LN. EXAMENES | Y14: CIAS. DE SEGURO | Z14: CENTRO | AA14: 981214114 | AB14: 191-98432106068
A15: 46176 | B15: 97979 | C15: BO | D15: 11406 | E15: CO | F15: BO-11406 | G15: PEREZ SANCHEZ GIOVANNA MARIELA | H15: 25792949 | I15: BOBBIO PEREZ MILKO | J15: CONSULTORIO | K15: CRISTINA | L15: 0069797 | M15: 946068386 | N15: PEREZ SANCHEZ GIOVANNA MARIELA | O15: 86027 | P15: PAQUIMETRIA | Q15: 1 | R15: PRECISA | S15: POR ASIGNAR | T15: INSTITUTO MEDICO QUIRURGICO AREQUIPA S.A | U15: L.CENTRO | V15: LMAGAN | W15: 152.54 | X15: LN. EXAMENES | Y15: CIAS. DE SEGURO | Z15: CENTRO | AA15: 981214114 | AB15: 191-98432106068
A16: 46177 | B16: 98036 | C16: BO | D16: 5516 | E16: CO | F16: BO-5516 | G16: PICO DE CRUZADO LUZ EMILIA | H16: 16550311 | I16: AGRAMONTE ZEA EDILBERTO | J16: HOSPITAL DE LA SOLIDARIDAD SJL | K16: CRISTINA | L16: 0069819 | M16: 985411444 | N16: PICO DE CRUZADO LUZ EMILIA | O16: 86087 | P16: OCT DE MACULA | Q16: 1 | R16: PRECISA | S16: POR ASIGNAR | T16: INSTITUTO MEDICO QUIRURGICO AREQUIPA S.A | U16: L.CENTRO | V16: ACABRERA | W16: 186.44 | X16: LN. EXAMENES | Y16: CIAS. DE SEGURO | Z16: CENTRO | AA16: 987407712 | AB16: 0011-0190-0200333106
A17: 46177 | B17: 98044 | C17: BO | D17: 11419 | E17: CO | F17: BO-11419 | G17: SACHA NAVARRO GERARDO JUNIOR | H17: 47180662 | I17: CACERES PINTO ALVARO DANIEL | J17: HOSPITAL INO | K17: CRISTINA | L17: 0069825 | M17: 958365826 | N17: SACHA NAVARRO GERARDO JUNIOR | O17: 86096 | P17: FOTOCLINICA EN MOSAICO | Q17: 1 | R17: PRECISA | S17: POR ASIGNAR | T17: INSTITUTO MEDICO QUIRURGICO AREQUIPA S.A | U17: L.CENTRO | V17: LMAGAN | W17: 169.49 | X17: LN. EXAMENES | Y17: CIAS. DE SEGURO | Z17: CENTRO | AA17: 966697811 | AB17: 0011-0184-0200649518
A18: 46177 | B18: 98044 | C18: BO | D18: 11419 | E18: CO | F18: BO-11419 | G18: SACHA NAVARRO GERARDO JUNIOR | H18: 47180662 | I18: CACERES PINTO ALVARO DANIEL | J18: HOSPITAL INO | K18: CRISTINA | L18: 0069825 | M18: 958365826 | N18: SACHA NAVARRO GERARDO JUNIOR | O18: 86096 | P18: OCT DE MACULA | Q18: 1 | R18: PRECISA | S18: POR ASIGNAR | T18: INSTITUTO MEDICO QUIRURGICO AREQUIPA S.A | U18: L.CENTRO | V18: LMAGAN | W18: 186.44 | X18: LN. EXAMENES | Y18: CIAS. DE SEGURO | Z18: CENTRO | AA18: 966697811 | AB18: 0011-0184-0200649518
A19: 46177 | B19: 98044 | C19: BO | D19: 11419 | E19: CO | F19: BO-11419 | G19: SACHA NAVARRO GERARDO JUNIOR | H19: 47180662 | I19: CACERES PINTO ALVARO DANIEL | J19: HOSPITAL INO | K19: CRISTINA | L19: 0069825 | M19: 958365826 | N19: SACHA NAVARRO GERARDO JUNIOR | O19: 86096 | P19: OCT DE NERVIO OPTICO Y CELULAS GANGLION | Q19: 1 | R19: PRECISA | S19: POR ASIGNAR | T19: INSTITUTO MEDICO QUIRURGICO AREQUIPA S.A | U19: L.CENTRO | V19: LMAGAN | W19: 186.44 | X19: LN. EXAMENES | Y19: CIAS. DE SEGURO | Z19: CENTRO | AA19: 966697811 | AB19: 0011-0184-0200649518
A20: 46177 | B20: 98041 | C20: FA | D20: 1025 | E20: CO | F20: FA-1025 | G20: NUÑEZ ALTIS ANTONIO SALOMON | H20: 09498424 | I20: VILLAR CURAHUA MARCELA ALEJANDRA | J20: GAMARRA SALUD | K20: CRISTINA | L20: 0069549 | M20: 928076253 | N20: GAMARRA HEALTHCARE CENTER S.A.C. | O20: 86093 | P20: BIOMETRIA IOL MASTER 700 | Q20: 1 | R20: PRECISA | S20: POR ASIGNAR | T20: INSTITUTO MEDICO QUIRURGICO AREQUIPA S.A | U20: L.CENTRO | V20: LMAGAN | W20: 152.54 | X20: LN. EXAMENES | Y20: CIAS. DE SEGURO | Z20: CENTRO | AA20: 950133748 | AB20: 191-9953047026
A21: 46177 | B21: 98041 | C21: FA | D21: 1025 | E21: CO | F21: FA-1025 | G21: NUÑEZ ALTIS ANTONIO SALOMON | H21: 09498424 | I21: VILLAR CURAHUA MARCELA ALEJANDRA | J21: GAMARRA SALUD | K21: CRISTINA | L21: 0069549 | M21: 928076253 | N21: GAMARRA HEALTHCARE CENTER S.A.C. | O21: 86093 | P21: MICROSCOPIA ESPECULAR | Q21: 1 | R21: PRECISA | S21: POR ASIGNAR | T21: INSTITUTO MEDICO QUIRURGICO AREQUIPA S.A | U21: L.CENTRO | V21: LMAGAN | W21: 135.59 | X21: LN. EXAMENES | Y21: CIAS. DE SEGURO | Z21: CENTRO | AA21: 950133748 | AB21: 191-9953047026
... A31: 46178 | B31: 2353 | C31: BO | D31: 5527 | E31: CR | F31: BO-5527 | G31: BRAVO QUISPE VDA DE ANDIA ANGELICA RITA | H31: 07412423 | I31: FERNANDEZ GUTIERREZ OLGA PATRICIA | J31: CONSULTORIO PARTICULAR | K31: CR | L31: 0069850 | M31: 979750580 | N31: BRAVO QUISPE VDA DE ANDIA ANGELICA RITA | O31: 86154 | P31: USO DE EQUIPOS E INSUMO IRIDOTOMIA | Q31: 2 | R31: PRECISA | S31: POR ASIGNAR | T31: INSTITUTO MEDICO QUIRURGICO AREQUIPA S.A | U31: L.CENTRO | V31: ACABRERA | W31: 203.39 | X31: LN. PROCEDIMIENTO | Y31: CIAS. DE SEGURO | Z31: CENTRO | AA31: 982536223 | AB31: 107-3174605363
A32: 46178 | B32: 98108 | C32: FA | D32: 526 | E32: CO | F32: FA-526 | G32: ABAD OVALLE ARLINE MERCEDES | H32: 25532349 | K32: CRISTINA | L32: 0069694 | M32: 999999452 | N32: VEFER OFTALMOLOGOS S.A.C. | O32: 86152 | P32: USO DE EQUIPOS E INSUMO IRIDOTOMIA | Q32: 2 | R32: PRECISA | S32: POR ASIGNAR | T32: INSTITUTO MEDICO QUIRURGICO AREQUIPA S.A | U32: L.CENTRO | V32: ACABRERA | W32: 203.39 | X32: LN. PROCEDIMIENTO | Y32: CIAS. DE SEGURO | Z32: CENTRO
A33: 46179 | B33: 98152 | C33: BO | D33: 4244 | E33: CO | F33: BO-4244 | G33: OLIVO CASTRO JULIA GLADYS | H33: 15292242 | I33: RUIZ ROJAS PAUBLO ENRIQUE | J33: CONSULTORIO CUBANO COMAS | K33: CRISTINA | L33: 0069884 | M33: 952190646 | N33: OLIVO CASTRO JULIA GLADYS | O33: 86190 | P33: OCT DE MACULA | Q33: 1 | R33: PRECISA LN | S33: POR ASIGNAR | T33: INSTITUTO MEDICO QUIRURGICO AREQUIPA S.A | U33: L.NORTE | V33: AALARCON | W33: 186.44 | X33: LN. EXAMENES | Y33: CIAS. DE SEGURO | Z33: NORTE | AA33: 992903716 | AB33: 191-91415089071
A34: 46179 | B34: 98151 | C34: BO | D34: 11423 | E34: CO | F34: BO-11423 | G34: PACACHA FLORES BLANCA VALESKA | H34: 91733805 | I34: CRISPIN MORALES NANCY JENNY | J34: HOSPITAL ALMENARA | K34: CRISTINA | L34: 0069883 | M34: 970593962 | N34: PACACHA FLORES BLANCA VALESKA | O34: 86188 | P34: TOPOGRAFIA CORNEAL | Q34: 1 | R34: PRECISA | S34: POR ASIGNAR | T34: INSTITUTO MEDICO QUIRURGICO AREQUIPA S.A | U34: L.CENTRO | V34: LMAGAN | W34: 152.54 | X34: LN. EXAMENES | Y34: CIAS. DE SEGURO | Z34: CENTRO | AA34: 978789268 | AB34: 193-90416675072
A35: 46179 | B35: 98176 | C35: BO | D35: 11428 | E35: CO | F35: BO-11428 | G35: REYES SANCHEZ OLGA EULALIA | H35: 09330262 | I35: LLERENA MORALES OSCAR ADOLFO | J35: SANNA SAN MIGUEL | K35: CRISTINA | L35: 0069894 | M35: 947513770 | N35: REYES SANCHEZ OLGA EULALIA | O35: 86218 | P35: CAMPIMETRIA (CAMPO VISUAL) | Q35: 1 | R35: PRECISA | S35: POR ASIGNAR | T35: INSTITUTO MEDICO QUIRURGICO AREQUIPA S.A | U35: L.CENTRO | V35: LMAGAN | W35: 135.59 | X35: LN. EXAMENES | Y35: CIAS. DE SEGURO | Z35: CENTRO | AA35: 987552890 | AB35: 098-7304409
A36: 46179 | B36: 98176 | C36: BO | D36: 11428 | E36: CO | F36: BO-11428 | G36: REYES SANCHEZ OLGA EULALIA | H36: 09330262 | I36: LLERENA MORALES OSCAR ADOLFO | J36: SANNA SAN MIGUEL | K36: CRISTINA | L36: 0069894 | M36: 947513770 | N36: REYES SANCHEZ OLGA EULALIA | O36: 86218 | P36: PAQUIMETRIA | Q36: 1 | R36: PRECISA | S36: POR ASIGNAR | T36: INSTITUTO MEDICO QUIRURGICO AREQUIPA S.A | U36: L.CENTRO | V36: LMAGAN | W36: 152.54 | X36: LN. EXAMENES | Y36: CIAS. DE SEGURO | Z36: CENTRO | AA36: 987552890 | AB36: 098-7304409
A37: 46179 | B37: 98176 | C37: BO | D37: 11428 | E37: CO | F37: BO-11428 | G37: REYES SANCHEZ OLGA EULALIA | H37: 09330262 | I37: LLERENA MORALES OSCAR ADOLFO | J37: SANNA SAN MIGUEL | K37: CRISTINA | L37: 0069894 | M37: 947513770 | N37: REYES SANCHEZ OLGA EULALIA | O37: 86218 | P37: OCT DE NERVIO OPTICO Y CELULAS GANGLION | Q37: 1 | R37: PRECISA | S37: POR ASIGNAR | T37: INSTITUTO MEDICO QUIRURGICO AREQUIPA S.A | U37: L.CENTRO | V37: LMAGAN | W37: 186.44 | X37: LN. EXAMENES | Y37: CIAS. DE SEGURO | Z37: CENTRO | AA37: 987552890 | AB37: 098-7304409
A38: 46179 | B38: 98167 | C38: BO | D38: 4250 | E38: CO | F38: BO-4250 | G38: RONCAL ROMERO FANNYNG EDITH | H38: 44905743 | I38: ROJAS AQUINO EVELING KARINA | J38: POLICLÍNICO ESPÍRITU SANTO | K38: CRISTINA | L38: 0069844 | M38: 984441413 | N38: RONCAL ROMERO FANNYNG EDITH | O38: 86210 | P38: OCT DE NERVIO OPTICO Y CELULAS GANGLION | Q38: 1 | R38: PRECISA LN | S38: POR ASIGNAR | T38: INSTITUTO MEDICO QUIRURGICO AREQUIPA S.A | U38: L.NORTE | V38: AALARCON | W38: 186.44 | X38: LN. EXAMENES | Y38: CIAS. DE SEGURO | Z38: NORTE | AA38: 955356636 | AB38: 009-3226956615
A39: 46182 | B39: 98452 | C39: FA | D39: 532 | E39: CO | F39: FA-532 | G39: BENITES RAMOS ANTENOR HERMAN | H39: 07187063 | I39: VILLAR CURAHUA MARCELA ALEJANDRA | J39: GAMARRA SALUD | K39: CRISTINA | L39: 0069415 | M39: 943410784 | N39: GAMARRA HEALTHCARE CENTER S.A.C. | O39: 86345 | P39: CIRUGIA DE DIA | Q39: 1 | R39: PRECISA | S39: POR ASIGNAR | T39: INSTITUTO MEDICO QUIRURGICO AREQUIPA S.A | U39: L.CENTRO | V39: ACABRERA | W39: 0 | X39: LN. CIRUGIA | Y39: CIAS. DE SEGURO | Z39: CENTRO | AA39: 950133748 | AB39: 191-9953047026
A40: 46182 | B40: 98452 | C40: FA | D40: 532 | E40: CO | F40: FA-532 | G40: BENITES RAMOS ANTENOR HERMAN | H40: 07187063 | I40: VILLAR CURAHUA MARCELA ALEJANDRA | J40: GAMARRA SALUD | K40: CRISTINA | L40: 0069415 | M40: 943410784 | N40: GAMARRA HEALTHCARE CENTER S.A.C. | O40: 86345 | P40: FACOEMULSIFICACION PRIMIUM | Q40: 1 | R40: PRECISA | S40: POR ASIGNAR | T40: INSTITUTO MEDICO QUIRURGICO AREQUIPA S.A | U40: L.CENTRO | V40: ACABRERA | W40: 1050.85 | X40: LN. CIRUGIA | Y40: CIAS. DE SEGURO | Z40: CENTRO | AA40: 950133748 | AB40: 191-9953047026
A41: 46182 | B41: 98463 | C41: FA | D41: 533 | E41: CO | F41: FA-533 | G41: MAMANI SONCCO JUAN GREGORIO | H41: 07314057 | I41: VILLAR CURAHUA MARCELA ALEJANDRA | J41: GAMARRA SALUD | K41: CRISTINA | L41: 0069158 | M41: 987411587 | N41: GAMARRA HEALTHCARE CENTER S.A.C. | O41: 86342 | P41: CIRUGIA DE DIA | Q41: 1 | R41: PRECISA | S41: POR ASIGNAR | T41: INSTITUTO MEDICO QUIRURGICO AREQUIPA S.A | U41: L.CENTRO | V41: ACABRERA | W41: 0 | X41: LN. CIRUGIA | Y41: CIAS. DE SEGURO | Z41: CENTRO | AA41: 950133748 | AB41: 191-9953047026
A42: 46182 | B42: 98463 | C42: FA | D42: 533 | E42: CO | F42: FA-533 | G42: MAMANI SONCCO JUAN GREGORIO | H42: 07314057 | I42: VILLAR CURAHUA MARCELA ALEJANDRA | J42: GAMARRA SALUD | K42: CRISTINA | L42: 0069158 | M42: 987411587 | N42: GAMARRA HEALTHCARE CENTER S.A.C. | O42: 86342 | P42: FACOEMULSIFICACION PRIMIUM | Q42: 1 | R42: PRECISA | S42: POR ASIGNAR | T42: INSTITUTO MEDICO QUIRURGICO AREQUIPA S.A | U42: L.CENTRO | V42: ACABRERA | W42: 1050.85 | X42: LN. CIRUGIA | Y42: CIAS. DE SEGURO | Z42: CENTRO | AA42: 950133748 | AB42: 191-9953047026
A43: 46182 | B43: 98440 | C43: FA | D43: 1028 | E43: CO | F43: FA-1028 | G43: MATEO EYZAGUIRRE MARCO IVART | H43: 74312316 | I43: ACOSTA VIERA ALVARO | J43: CONSULTORIO PARTICULAR | K43: CRISTINA | L43: 0069588 | M43: 921508096 | N43: CENTRO CONTRA LA CEGUERA E.I.R.L. | O43: 86415 | P43: USO DE EQUIPOS E INSUMO BLEFAROPLASTIA | Q43: 1 | R43: PRECISA | S43: POR ASIGNAR | T43: INSTITUTO MEDICO QUIRURGICO AREQUIPA S.A | U43: L.CENTRO | V43: LMAGAN | W43: 169.49 | X43: LN. PROCEDIMIENTO | Y43: CIAS. DE SEGURO | Z43: CENTRO | AA43: 969791876 | AB43: 0011-0814-0256063048
A44: 46182 | B44: 98393 | C44: BO | D44: 5552 | E44: CO | F44: BO-5552 | G44: LAZARO CACHA JUAN CRISOSTOMO | H44: 31633639 | I44: FIERRO LEANDRO | J44: POLICLÍNICO DIVINO NIÑO JESÚS | K44: CRISTINA | L44: 0069870 | M44: 928408508 | N44: LAZARO CACHA JUAN CRISOSTOMO | O44: 86371 | P44: PQ BIOMETRIA MICROSCOPIA | Q44: 1 | R44: PRECISA | S44: POR ASIGNAR | T44: INSTITUTO MEDICO QUIRURGICO AREQUIPA S.A | U44: L.CENTRO | V44: ACABRERA | W44: 84.75 | X44: LN. EXAMENES | Y44: CIAS. DE SEGURO | Z44: CENTRO
A45: 46182 | B45: 98395 | C45: BO | D45: 11467 | E45: CO | F45: BO-11467 | G45: MENDOZA REYES BRIGIDA | H45: 08831402 | I45: FIERRO LEANDRO | J45: POLICLÍNICO DIVINO NIÑO JESÚS | K45: CRISTINA | L45: 0069872 | M45: 941194643 | N45: MENDOZA REYES BRIGIDA | O45: 86373 | P45: PQ BIOMETRIA MICROSCOPIA | Q45: 1 | R45: PRECISA | S45: POR ASIGNAR | T45: INSTITUTO MEDICO QUIRURGICO AREQUIPA S.A | U45: L.CENTRO | V45: LMAGAN | W45: 84.75 | X45: LN. EXAMENES | Y45: CIAS. DE SEGURO | Z45: CENTRO
A46: 46182 | B46: 98399 | C46: BO | D46: 5555 | E46: CO | F46: BO-5555 | G46: TINOCO OBREGON LUIS ALBERTO | H46: 15859654 | I46: FIERRO LEANDRO | J46: POLICLÍNICO DIVINO NIÑO JESÚS | K46: CRISTINA | L46: 0069871 | M46: 997639449 | N46: TINOCO OBREGON LUIS ALBERTO | O46: 86378 | P46: PQ BIOMETRIA MICROSCOPIA | Q46: 1 | R46: PRECISA | S46: POR ASIGNAR | T46: INSTITUTO MEDICO QUIRURGICO AREQUIPA S.A | U46: L.CENTRO | V46: ACABRERA | W46: 84.75 | X46: LN. EXAMENES | Y46: CIAS. DE SEGURO | Z46: CENTRO
A47: 46182 | B47: 98449 | C47: FA | D47: 530 | E47: CO | F47: FA-530 | G47: LAZARO CACHA JUAN CRISOSTOMO | H47: 31633639 | I47: FIERRO LEANDRO | J47: POLICLÍNICO DIVINO NIÑO JESÚS | K47: CRISTINA | L47: 0069870 | M47: 928408508 | N47: GRUPO MEDICO INTEGRAL SOCIEDAD ANONIMA CERRADA | O47: 86384 | P47: CIRUGIA DE DIA | Q47: 1 | R47: PRECISA | S47: POR ASIGNAR | T47: INSTITUTO MEDICO QUIRURGICO AREQUIPA S.A | U47: L.CENTRO | V47: ACABRERA | W47: 0 | X47: LN. CIRUGIA | Y47: CIAS. DE SEGURO | Z47: CENTRO
A48: 46182 | B48: 98449 | C48: FA | D48: 530 | E48: CO | F48: FA-530 | G48: LAZARO CACHA JUAN CRISOSTOMO | H48: 31633639 | I48: FIERRO LEANDRO | J48: POLICLÍNICO DIVINO NIÑO JESÚS | K48: CRISTINA | L48: 0069870 | M48: 928408508 | N48: GRUPO MEDICO INTEGRAL SOCIEDAD ANONIMA CERRADA | O48: 86384 | P48: FACOEMULSIFICACION PRIMIUM | Q48: 1 | R48: PRECISA | S48: POR ASIGNAR | T48: INSTITUTO MEDICO QUIRURGICO AREQUIPA S.A | U48: L.CENTRO | V48: ACABRERA | W48: 1525.42 | X48: LN. CIRUGIA | Y48: CIAS. DE SEGURO | Z48: CENTRO
A49: 46182 | B49: 98450 | C49: FA | D49: 531 | E49: CO | F49: FA-531 | G49: TINOCO OBREGON LUIS ALBERTO | H49: 15859654 | I49: FIERRO LEANDRO | J49: POLICLÍNICO DIVINO NIÑO JESÚS | K49: CRISTINA | L49: 0069871 | M49: 997639449 | N49: GRUPO MEDICO INTEGRAL SOCIEDAD ANONIMA CERRADA | O49: 86385 | P49: CIRUGIA DE DIA | Q49: 1 | R49: PRECISA | S49: POR ASIGNAR | T49: INSTITUTO MEDICO QUIRURGICO AREQUIPA S.A | U49: L.CENTRO | V49: ACABRERA | W49: 0 | X49: LN. CIRUGIA | Y49: CIAS. DE SEGURO | Z49: CENTRO
A50: 46182 | B50: 98450 | C50: FA | D50: 531 | E50: CO | F50: FA-531 | G50: TINOCO OBREGON LUIS ALBERTO | H50: 15859654 | I50: FIERRO LEANDRO | J50: POLICLÍNICO DIVINO NIÑO JESÚS | K50: CRISTINA | L50: 0069871 | M50: 997639449 | N50: GRUPO MEDICO INTEGRAL SOCIEDAD ANONIMA CERRADA | O50: 86385 | P50: FACOEMULSIFICACION PRIMIUM | Q50: 1 | R50: PRECISA | S50: POR ASIGNAR | T50: INSTITUTO MEDICO QUIRURGICO AREQUIPA S.A | U50: L.CENTRO | V50: ACABRERA | W50: 1525.42 | X50: LN. CIRUGIA | Y50: CIAS. DE SEGURO | Z50: CENTRO
A51: 46182 | B51: 98476 | C51: FA | D51: 1029 | E51: CO | F51: FA-1029 | G51: MENDOZA REYES BRIGIDA | H51: 08831402 | I51: FIERRO LEANDRO | J51: POLICLÍNICO DIVINO NIÑO JESÚS | K51: CRISTINA | L51: 0069872 | M51: 941194643 | N51: GRUPO MEDICO INTEGRAL SOCIEDAD ANONIMA CERRADA | O51: 86375 | P51: CIRUGIA DE DIA | Q51: 1 | R51: PRECISA | S51: POR ASIGNAR | T51: INSTITUTO MEDICO QUIRURGICO AREQUIPA S.A | U51: L.CENTRO | V51: LMAGAN | W51: 0 | X51: LN. CIRUGIA | Y51: CIAS. DE SEGURO | Z51: CENTRO
A52: 46182 | B52: 98476 | C52: FA | D52: 1029 | E52: CO | F52: FA-1029 | G52: MENDOZA REYES BRIGIDA | H52: 08831402 | I52: FIERRO LEANDRO | J52: POLICLÍNICO DIVINO NIÑO JESÚS | K52: CRISTINA | L52: 0069872 | M52: 941194643 | N52: GRUPO MEDICO INTEGRAL SOCIEDAD ANONIMA CERRADA | O52: 86375 | P52: FACOEMULSIFICACION PRIMIUM | Q52: 1 | R52: PRECISA | S52: POR ASIGNAR | T52: INSTITUTO MEDICO QUIRURGICO AREQUIPA S.A | U52: L.CENTRO | V52: LMAGAN | W52: 762.71 | X52: LN. CIRUGIA | Y52: CIAS. DE SEGURO | Z52: CENTRO
A53: 46183 | B53: 98511 | C53: BO | D53: 3829 | E53: CO | F53: BO-3829 | G53: VILLA GALVEZ MARIA ESPERANZA | H53: 08462757 | I53: ROJAS AQUINO EVELING KARINA | J53: POLICLÍNICO ESPÍRITU SANTO | K53: CRISTINA | L53: 0070015 | M53: 955008730 | N53: VILLA GALVEZ MARIA ESPERANZA | O53: 86473 | P53: ECOGRAFIA OCULAR GENERAL SCAN A,B | Q53: 1 | R53: PRECISA LN | S53: POR ASIGNAR | T53: INSTITUTO MEDICO QUIRURGICO AREQUIPA S.A | U53: L.NORTE | V53: BGALLOSA | W53: 135.59 | X53: LN. EXAMENES | Y53: CIAS. DE SEGURO | Z53: NORTE | AA53: 955356636 | AB53: 009-3226956615
A54: 46184 | B54: 98570 | C54: BO | D54: 5573 | E54: CO | F54: BO-5573 | G54: GAMARRA CHAVARRIA JUAN PASCUAL | H54: 15447914 | I54: FIERRO LEANDRO | J54: POLICLÍNICO DIVINO NIÑO JESÚS | K54: CRISTINA | L54: 0070007 | M54: 986955058 | N54: GAMARRA CHAVARRIA JUAN PASCUAL | O54: 86517 | P54: PQ BIOMETRIA MICROSCOPIA | Q54: 1 | R54: PRECISA | S54: POR ASIGNAR | T54: INSTITUTO MEDICO QUIRURGICO AREQUIPA S.A | U54: L.CENTRO | V54: ACABRERA | W54: 84.75 | X54: LN. EXAMENES | Y54: CIAS. DE SEGURO | Z54: CENTRO
A55: 46184 | B55: 98571 | C55: BO | D55: 11481 | E55: CO | F55: BO-11481 | G55: PASCO RAMOS DE HERRERA GLORIA ELISA | H55: 07017191 | I55: FIERRO LEANDRO | J55: POLICLÍNICO DIVINO NIÑO JESÚS | K55: CRISTINA | L55: 0070001 | M55: 997369213 | N55: PASCO RAMOS DE HERRERA GLORIA ELISA | O55: 86520 | P55: PQ BIOMETRIA MICROSCOPIA | Q55: 1 | R55: PRECISA | S55: POR ASIGNAR | T55: INSTITUTO MEDICO QUIRURGICO AREQUIPA S.A | U55: L.CENTRO | V55: LMAGAN | W55: 84.75 | X55: LN. EXAMENES | Y55: CIAS. DE SEGURO | Z55: CENTRO
A56: 46184 | B56: 98572 | C56: BO | D56: 11482 | E56: CO | F56: BO-11482 | G56: PASCO RAMOS DE HERRERA GLORIA ELISA | H56: 07017191 | I56: FIERRO LEANDRO | J56: POLICLÍNICO DIVINO NIÑO JESÚS | K56: CRISTINA | L56: 0070001 | M56: 997369213 | N56: PASCO RAMOS DE HERRERA GLORIA ELISA | O56: 86519 | P56: ELECTROCARDIOGRAMA-EKG | Q56: 1 | R56: PRECISA | S56: POR ASIGNAR | T56: INSTITUTO MEDICO QUIRURGICO AREQUIPA S.A | U56: L.CENTRO | V56: LMAGAN | W56: 127.12 | X56: LN. EXAMENES | Y56: CIAS. DE SEGURO | Z56: CENTRO
A57: 46184 | B57: 98573 | C57: BO | D57: 11483 | E57: CO | F57: BO-11483 | G57: PASCO RAMOS DE HERRERA GLORIA ELISA | H57: 07017191 | I57: FIERRO LEANDRO | J57: POLICLÍNICO DIVINO NIÑO JESÚS | K57: CRISTINA | L57: 0070001 | M57: 997369213 | N57: PASCO RAMOS DE HERRERA GLORIA ELISA | O57: 86518 | P57: HEMOGRAMA COMPLETO | Q57: 1 | R57: PRECISA | S57: POR ASIGNAR | T57: INSTITUTO MEDICO QUIRURGICO AREQUIPA S.A | U57: L.CENTRO | V57: LMAGAN | W57: 12.71 | X57: LN. LABORATORIO | Y57: CIAS. DE SEGURO | Z57: CENTRO
A58: 46184 | B58: 98573 | C58: BO | D58: 11483 | E58: CO | F58: BO-11483 | G58: PASCO RAMOS DE HERRERA GLORIA ELISA | H58: 07017191 | I58: FIERRO LEANDRO | J58: POLICLÍNICO DIVINO NIÑO JESÚS | K58: CRISTINA | L58: 0070001 | M58: 997369213 | N58: PASCO RAMOS DE HERRERA GLORIA ELISA | O58: 86518 | P58: ORINA COMPLETO | Q58: 1 | R58: PRECISA | S58: POR ASIGNAR | T58: INSTITUTO MEDICO QUIRURGICO AREQUIPA S.A | U58: L.CENTRO | V58: LMAGAN | W58: 21.19 | X58: LN. LABORATORIO | Y58: CIAS. DE SEGURO | Z58: CENTRO
A59: 46184 | B59: 98573 | C59: BO | D59: 11483 | E59: CO | F59: BO-11483 | G59: PASCO RAMOS DE HERRERA GLORIA ELISA | H59: 07017191 | I59: FIERRO LEANDRO | J59: POLICLÍNICO DIVINO NIÑO JESÚS | K59: CRISTINA | L59: 0070001 | M59: 997369213 | N59: PASCO RAMOS DE HERRERA GLORIA ELISA | O59: 86518 | P59: GLUCOSA | Q59: 1 | R59: PRECISA | S59: POR ASIGNAR | T59: INSTITUTO MEDICO QUIRURGICO AREQUIPA S.A | U59: L.CENTRO | V59: LMAGAN | W59: 12.71 | X59: LN. LABORATORIO | Y59: CIAS. DE SEGURO | Z59: CENTRO
A60: 46184 | B60: 98573 | C60: BO | D60: 11483 | E60: CO | F60: BO-11483 | G60: PASCO RAMOS DE HERRERA GLORIA ELISA | H60: 07017191 | I60: FIERRO LEANDRO | J60: POLICLÍNICO DIVINO NIÑO JESÚS | K60: CRISTINA | L60: 0070001 | M60: 997369213 | N60: PASCO RAMOS DE HERRERA GLORIA ELISA | O60: 86518 | P60: TIEMPO DE COAGULACION Y SANGRIA | Q60: 1 | R60: PRECISA | S60: POR ASIGNAR | T60: INSTITUTO MEDICO QUIRURGICO AREQUIPA S.A | U60: L.CENTRO | V60: LMAGAN | W60: 12.71 | X60: LN. LABORATORIO | Y60: CIAS. DE SEGURO | Z60: CENTRO
A61: 46184 | B61: 98573 | C61: BO | D61: 11483 | E61: CO | F61: BO-11483 | G61: PASCO RAMOS DE HERRERA GLORIA ELISA | H61: 07017191 | I61: FIERRO LEANDRO | J61: POLICLÍNICO DIVINO NIÑO JESÚS | K61: CRISTINA | L61: 0070001 | M61: 997369213 | N61: PASCO RAMOS DE HERRERA GLORIA ELISA | O61: 86518 | P61: HIV 1,2 (TEST RAPIDO) | Q61: 1 | R61: PRECISA | S61: POR ASIGNAR | T61: INSTITUTO MEDICO QUIRURGICO AREQUIPA S.A | U61: L.CENTRO | V61: LMAGAN | W61: 50.85 | X61: LN. LABORATORIO | Y61: CIAS. DE SEGURO | Z61: CENTRO
A62: 46184 | B62: 98577 | C62: BO | D62: 11486 | E62: CO | F62: BO-11486 | G62: SAUÑE AGUILAR MERCEDES | H62: 31032400 | I62: FIERRO LEANDRO | J62: POLICLÍNICO DIVINO NIÑO JESÚS | K62: CRISTINA | L62: 0069675 | M62: 940106575 | N62: SAUÑE AGUILAR MERCEDES | O62: 86525 | P62: HEMOGRAMA COMPLETO | Q62: 1 | R62: PRECISA | S62: POR ASIGNAR | T62: INSTITUTO MEDICO QUIRURGICO AREQUIPA S.A | U62: L.CENTRO | V62: LMAGAN | W62: 12.71 | X62: LN. LABORATORIO | Y62: CIAS. DE SEGURO | Z62: CENTRO
A63: 46184 | B63: 98577 | C63: BO | D63: 11486 | E63: CO | F63: BO-11486 | G63: SAUÑE AGUILAR MERCEDES | H63: 31032400 | I63: FIERRO LEANDRO | J63: POLICLÍNICO DIVINO NIÑO JESÚS | K63: CRISTINA | L63: 0069675 | M63: 940106575 | N63: SAUÑE AGUILAR MERCEDES | O63: 86525 | P63: ORINA COMPLETO | Q63: 1 | R63: PRECISA | S63: POR ASIGNAR | T63: INSTITUTO MEDICO QUIRURGICO AREQUIPA S.A | U63: L.CENTRO | V63: LMAGAN | W63: 21.19 | X63: LN. LABORATORIO | Y63: CIAS. DE SEGURO | Z63: CENTRO
A64: 46184 | B64: 98577 | C64: BO | D64: 11486 | E64: CO | F64: BO-11486 | G64: SAUÑE AGUILAR MERCEDES | H64: 31032400 | I64: FIERRO LEANDRO | J64: POLICLÍNICO DIVINO NIÑO JESÚS | K64: CRISTINA | L64: 0069675 | M64: 940106575 | N64: SAUÑE AGUILAR MERCEDES | O64: 86525 | P64: GLUCOSA | Q64: 1 | R64: PRECISA | S64: POR ASIGNAR | T64: INSTITUTO MEDICO QUIRURGICO AREQUIPA S.A | U64: L.CENTRO | V64: LMAGAN | W64: 12.71 | X64: LN. LABORATORIO | Y64: CIAS. DE SEGURO | Z64: CENTRO
A65: 46184 | B65: 98577 | C65: BO | D65: 11486 | E65: CO | F65: BO-11486 | G65: SAUÑE AGUILAR MERCEDES | H65: 31032400 | I65: FIERRO LEANDRO | J65: POLICLÍNICO DIVINO NIÑO JESÚS | K65: CRISTINA | L65: 0069675 | M65: 940106575 | N65: SAUÑE AGUILAR MERCEDES | O65: 86525 | P65: TIEMPO DE COAGULACION Y SANGRIA | Q65: 1 | R65: PRECISA | S65: POR ASIGNAR | T65: INSTITUTO MEDICO QUIRURGICO AREQUIPA S.A | U65: L.CENTRO | V65: LMAGAN | W65: 12.71 | X65: LN. LABORATORIO | Y65: CIAS. DE SEGURO | Z65: CENTRO
... A69: 46184 | B69: 98589 | C69: BO | D69: 11488 | E69: CO | F69: BO-11488 | G69: SAUÑE AGUILAR MERCEDES | H69: 31032400 | I69: FIERRO LEANDRO | J69: POLICLÍNICO DIVINO NIÑO JESÚS | K69: CRISTINA | L69: 0069675 | M69: 940106575 | N69: SAUÑE AGUILAR MERCEDES | O69: 86536 | P69: PQ BIOMETRIA MICROSCOPIA | Q69: 1 | R69: PRECISA | S69: POR ASIGNAR | T69: INSTITUTO MEDICO QUIRURGICO AREQUIPA S.A | U69: L.CENTRO | V69: LMAGAN | W69: 84.75 | X69: LN. EXAMENES | Y69: CIAS. DE SEGURO | Z69: CENTRO
A70: 46184 | B70: 98616 | C70: BO | D70: 11491 | E70: CO | F70: BO-11491 | G70: MUÑOZ OCAÑO ARMANDO | H70: 20976782 | I70: SILVA | K70: CRISTINA | L70: 0070068 | M70: 928786641 | N70: MUÑOZ OCAÑO ARMANDO | O70: 86562 | P70: ECOGRAFIA OCULAR GENERAL SCAN A,B | Q70: 1 | R70: PRECISA | S70: POR ASIGNAR | T70: INSTITUTO MEDICO QUIRURGICO AREQUIPA S.A | U70: L.CENTRO | V70: LMAGAN | W70: 135.59 | X70: LN. EXAMENES | Y70: CIAS. DE SEGURO | Z70: CENTRO
A71: 46185 | B71: 98684 | C71: BO | D71: 11497 | E71: CO | F71: BO-11497 | G71: GUERRA VALLE LUZ MARGARITA | H71: 06106322 | I71: SAPAICO VICUÑA AUGUSTO RODRIGO | J71: HOSPITAL LOAYZA | K71: CRISTINA | L71: 0070101 | M71: 940296008 | N71: GUERRA VALLE LUZ MARGARITA | O71: 86622 | P71: USO DE EQUIPOS E INSUMO IRIDOTOMIA | Q71: 2 | R71: PRECISA | S71: POR ASIGNAR | T71: INSTITUTO MEDICO QUIRURGICO AREQUIPA S.A | U71: L.CENTRO | V71: LMAGAN | W71: 203.39 | X71: LN. PROCEDIMIENTO | Y71: CIAS. DE SEGURO | Z71: CENTRO | AA71: 997145685 | AB71: 0011-0189-0200496417
A72: 46185 | B72: 98697 | C72: FA | D72: 1032 | E72: CO | F72: FA-1032 | G72: SAUÑE AGUILAR MERCEDES | H72: 31032400 | I72: FIERRO LEANDRO | J72: POLICLÍNICO DIVINO NIÑO JESÚS | K72: CRISTINA | L72: 0069675 | M72: 940106575 | N72: GRUPO MEDICO INTEGRAL SOCIEDAD ANONIMA CERRADA | O72: 86543 | P72: CIRUGIA DE DIA | Q72: 1 | R72: PRECISA | S72: POR ASIGNAR | T72: INSTITUTO MEDICO QUIRURGICO AREQUIPA S.A | U72: L.CENTRO | V72: LMAGAN | W72: 0 | X72: LN. CIRUGIA | Y72: CIAS. DE SEGURO | Z72: CENTRO
A73: 46185 | B73: 98697 | C73: FA | D73: 1032 | E73: CO | F73: FA-1032 | G73: SAUÑE AGUILAR MERCEDES | H73: 31032400 | I73: FIERRO LEANDRO | J73: POLICLÍNICO DIVINO NIÑO JESÚS | K73: CRISTINA | L73: 0069675 | M73: 940106575 | N73: GRUPO MEDICO INTEGRAL SOCIEDAD ANONIMA CERRADA | O73: 86543 | P73: FACOEMULSIFICACION PRIMIUM | Q73: 1 | R73: PRECISA | S73: POR ASIGNAR | T73: INSTITUTO MEDICO QUIRURGICO AREQUIPA S.A | U73: L.CENTRO | V73: LMAGAN | W73: 762.71 | X73: LN. CIRUGIA | Y73: CIAS. DE SEGURO | Z73: CENTRO
A74: 46185 | B74: 98698 | C74: FA | D74: 1033 | E74: CO | F74: FA-1033 | G74: PASCO RAMOS DE HERRERA GLORIA ELISA | H74: 07017191 | I74: FIERRO LEANDRO | J74: POLICLÍNICO DIVINO NIÑO JESÚS | K74: CRISTINA | L74: 0070001 | M74: 997369213 | N74: GRUPO MEDICO INTEGRAL SOCIEDAD ANONIMA CERRADA | O74: 86542 | P74: CIRUGIA DE DIA | Q74: 1 | R74: PRECISA | S74: POR ASIGNAR | T74: INSTITUTO MEDICO QUIRURGICO AREQUIPA S.A | U74: L.CENTRO | V74: LMAGAN | W74: 0 | X74: LN. CIRUGIA | Y74: CIAS. DE SEGURO | Z74: CENTRO
A75: 46185 | B75: 98698 | C75: FA | D75: 1033 | E75: CO | F75: FA-1033 | G75: PASCO RAMOS DE HERRERA GLORIA ELISA | H75: 07017191 | I75: FIERRO LEANDRO | J75: POLICLÍNICO DIVINO NIÑO JESÚS | K75: CRISTINA | L75: 0070001 | M75: 997369213 | N75: GRUPO MEDICO INTEGRAL SOCIEDAD ANONIMA CERRADA | O75: 86542 | P75: FACOEMULSIFICACION PRIMIUM | Q75: 1 | R75: PRECISA | S75: POR ASIGNAR | T75: INSTITUTO MEDICO QUIRURGICO AREQUIPA S.A | U75: L.CENTRO | V75: LMAGAN | W75: 1525.42 | X75: LN. CIRUGIA | Y75: CIAS. DE SEGURO | Z75: CENTRO
A76: 46185 | B76: 98661 | C76: BO | D76: 11495 | E76: CO | F76: BO-11495 | G76: GALLEGOS BENAVIDES CRISTINA ANA | H76: 07136272 | I76: CARDENAS ORTEGA MARISA | J76: CONSULTORIO | K76: CRISTINA | L76: 0070089 | M76: 979097585 | N76: GALLEGOS BENAVIDES CRISTINA ANA | O76: 86601 | P76: OCT DE MACULA | Q76: 1 | R76: PRECISA | S76: POR ASIGNAR | T76: INSTITUTO MEDICO QUIRURGICO AREQUIPA S.A | U76: L.CENTRO | V76: LMAGAN | W76: 186.44 | X76: LN. EXAMENES | Y76: CIAS. DE SEGURO | Z76: CENTRO | AA76: 947054605 | AB76: 193-34139202041
A77: 46185 | B77: 2358 | C77: NC | D77: 11496 | E77: CR | F77: NC-11496 | G77: MONTALVO SUAREZ ESTHER ESPERANZA | H77: 08507757 | I77: HUAMAN RIOS LUIS ENRIQUE | J77: HOSPITAL SERGIO BERNALES | K77: CR | L77: 0070099 | M77: 990523847 | N77: MONTALVO SUAREZ ESTHER ESPERANZA | O77: 86611 | P77: OCT DE NERVIO OPTICO Y CELULAS GANGLION | Q77: 1 | R77: PRECISA | S77: POR ASIGNAR | T77: INSTITUTO MEDICO QUIRURGICO AREQUIPA S.A | U77: L.CENTRO | V77: LMAGAN | W77: -186.44 | X77: LN. EXAMENES | Y77: CIAS. DE SEGURO | Z77: CENTRO | AA77: 999986041 | AB77: 191-30583545068
A78: 46185 | B78: 98676 | C78: FA | D78: 1030 | E78: CO | F78: FA-1030 | G78: MONTALVO SUAREZ ESTHER ESPERANZA | H78: 08507757 | I78: HUAMAN RIOS LUIS ENRIQUE | J78: HOSPITAL SERGIO BERNALES | K78: CRISTINA | L78: 0070099 | M78: 990523847 | N78: VDAXIOM S.A.C. | O78: 86613 | P78: OCT DE NERVIO OPTICO Y CELULAS GANGLION | Q78: 1 | R78: PRECISA | S78: POR ASIGNAR | T78: INSTITUTO MEDICO QUIRURGICO AREQUIPA S.A | U78: L.CENTRO | V78: LMAGAN | W78: 186.44 | X78: LN. EXAMENES | Y78: CIAS. DE SEGURO | Z78: CENTRO | AA78: 999986041 | AB78: 191-30583545068
A79: 46185 | B79: 2358 | C79: BO | D79: 11496 | E79: CR | F79: BO-11496 | G79: MONTALVO SUAREZ ESTHER ESPERANZA | H79: 08507757 | I79: HUAMAN RIOS LUIS ENRIQUE | J79: HOSPITAL SERGIO BERNALES | K79: CR | L79: 0070099 | M79: 990523847 | N79: MONTALVO SUAREZ ESTHER ESPERANZA | O79: 86611 | P79: OCT DE NERVIO OPTICO Y CELULAS GANGLION | Q79: 1 | R79: PRECISA | S79: POR ASIGNAR | T79: INSTITUTO MEDICO QUIRURGICO AREQUIPA S.A | U79: L.CENTRO | V79: LMAGAN | W79: 186.44 | X79: LN. EXAMENES | Y79: CIAS. DE SEGURO | Z79: CENTRO | AA79: 999986041 | AB79: 191-30583545068
A80: 46185 | B80: 98645 | C80: BO | D80: 5580 | E80: CO | F80: BO-5580 | G80: CUBA HIDALGO VDA DE TOSCA JULIA JESUS | H80: 08052088 | I80: DIANA DAVALOS SORIA | J80: HOSPITAL CAYETANO HEREDIA | K80: CRISTINA | L80: 0070081 | M80: 955702271 | N80: CUBA HIDALGO VDA DE TOSCA JULIA JESUS | O80: 86587 | P80: CAMPIMETRIA (CAMPO VISUAL) | Q80: 1 | R80: PRECISA | S80: POR ASIGNAR | T80: INSTITUTO MEDICO QUIRURGICO AREQUIPA S.A | U80: L.CENTRO | V80: ACABRERA | W80: 135.59 | X80: LN. EXAMENES | Y80: CIAS. DE SEGURO | Z80: CENTRO | AB80: 191-00494902000
A81: 46185 | B81: 98694 | C81: FA | D81: 1031 | E81: CO | F81: FA-1031 | G81: CARAZAS CERRILLO DE APAZA GREGORIA | H81: 08985710 | I81: MANCHEGO LOMBARDI MICHAEL | J81: CONSULTORIO PARTICULAR | K81: CRISTINA | L81: 0070006 | M81: NO TIENE | N81: CENTRO OFTALMOLOGICO OFTALMOCARE S.R.L. | O81: 86633 | P81: USO DE EQUIPOS E INSUMO AVASTIN | Q81: 1 | R81: PRECISA | S81: POR ASIGNAR | T81: INSTITUTO MEDICO QUIRURGICO AREQUIPA S.A | U81: L.CENTRO | V81: LMAGAN | W81: 254.24 | X81: LN. PROCEDIMIENTO | Y81: CIAS. DE SEGURO | Z81: CENTRO | AA81: 970582106 | AB81: 639-3004120188
A82: 46188 | B82: 98853 | C82: BO | D82: 5605 | E82: CO | F82: BO-5605 | G82: TORRELIO GUERRERO LIDIA ZOTICA | H82: 06689006 | I82: SAPAICO VICUÑA AUGUSTO RODRIGO | J82: HOSPITAL LOAYZA | K82: CRISTINA | L82: 0070124 | M82: 999488621 | N82: TORRELIO GUERRERO LIDIA ZOTICA | O82: 86768 | P82: BIOMETRIA IOL MASTER 700 | Q82: 1 | R82: PRECISA | S82: POR ASIGNAR | T82: INSTITUTO MEDICO QUIRURGICO AREQUIPA S.A | U82: L.CENTRO | V82: ACABRERA | W82: 152.54 | X82: LN. EXAMENES | Y82: CIAS. DE SEGURO | Z82: CENTRO | AA82: 997145685 | AB82: 0011-0189-0200496417
A83: 46188 | B83: 98811 | C83: BO | D83: 11521 | E83: CO | F83: BO-11521 | G83: OCAS ROSALES RONALD JEANCARLOS | H83: 45170637 | I83: ALEMAÑY ERNESTO | J83: CLINICA LA LUZ | K83: CRISTINA | L83: 0070158 | M83: 999322893 | N83: OCAS ROSALES RONALD JEANCARLOS | O83: 86729 | P83: ANGIOGRAFIA CON FLUORESCEINA | Q83: 1 | R83: PRECISA | S83: POR ASIGNAR | T83: INSTITUTO MEDICO QUIRURGICO AREQUIPA S.A | U83: L.CENTRO | V83: LMAGAN | W83: 338.98 | X83: LN. EXAMENES | Y83: CIAS. DE SEGURO | Z83: CENTRO | AA83: 978548687 | AB83: 0011-0732-0200152751
A84: 46189 | B84: 98957 | C84: BO | D84: 11554 | E84: CO | F84: BO-11554 | G84: CANCHAYA CAYO JULIO LEONCIO | H84: 44212852 | I84: AGRAMONTE ZEA EDILBERTO | J84: HOSPITAL DE LA SOLIDARIDAD SJL | K84: CRISTINA | L84: 0070227 | M84: 964246765 | N84: CANCHAYA CAYO JULIO LEONCIO | O84: 86868 | P84: CAMPIMETRIA (CAMPO VISUAL) | Q84: 1 | R84: PRECISA | S84: INSTITUTO MEDICO QUIRURGICO AREQUIPA S.A | T84: INSTITUTO MEDICO QUIRURGICO AREQUIPA S.A | U84: L.CENTRO | V84: LMAGAN | W84: 135.59 | X84: LN. EXAMENES | Y84: CIAS. DE SEGURO | Z84: CENTRO | AA84: 987407712 | AB84: 0011-0190-0200333106
A85: 46189 | B85: 98957 | C85: BO | D85: 11554 | E85: CO | F85: BO-11554 | G85: CANCHAYA CAYO JULIO LEONCIO | H85: 44212852 | I85: AGRAMONTE ZEA EDILBERTO | J85: HOSPITAL DE LA SOLIDARIDAD SJL | K85: CRISTINA | L85: 0070227 | M85: 964246765 | N85: CANCHAYA CAYO JULIO LEONCIO | O85: 86868 | P85: OCT DE NERVIO OPTICO Y CELULAS GANGLION | Q85: 1 | R85: PRECISA | S85: INSTITUTO MEDICO QUIRURGICO AREQUIPA S.A | T85: INSTITUTO MEDICO QUIRURGICO AREQUIPA S.A | U85: L.CENTRO | V85: LMAGAN | W85: 186.44 | X85: LN. EXAMENES | Y85: CIAS. DE SEGURO | Z85: CENTRO | AA85: 987407712 | AB85: 0011-0190-0200333106
A86: 46189 | B86: 98957 | C86: BO | D86: 11554 | E86: CO | F86: BO-11554 | G86: CANCHAYA CAYO JULIO LEONCIO | H86: 44212852 | I86: AGRAMONTE ZEA EDILBERTO | J86: HOSPITAL DE LA SOLIDARIDAD SJL | K86: CRISTINA | L86: 0070227 | M86: 964246765 | N86: CANCHAYA CAYO JULIO LEONCIO | O86: 86868 | P86: PAQUIMETRIA | Q86: 1 | R86: PRECISA | S86: INSTITUTO MEDICO QUIRURGICO AREQUIPA S.A | T86: INSTITUTO MEDICO QUIRURGICO AREQUIPA S.A | U86: L.CENTRO | V86: LMAGAN | W86: 152.54 | X86: LN. EXAMENES | Y86: CIAS. DE SEGURO | Z86: CENTRO | AA86: 987407712 | AB86: 0011-0190-0200333106
A87: 46189 | B87: 98947 | C87: BO | D87: 11552 | E87: CO | F87: BO-11552 | G87: QUIPUSCO BERNAL MIGUEL WENCESLAO | H87: 06057576 | I87: CACERES PINTO ALVARO DANIEL | J87: HOSPITAL INO | K87: CRISTINA | L87: 0054107 | M87: 998759676 | N87: QUIPUSCO BERNAL MIGUEL WENCESLAO | O87: 86860 | P87: OCT DE NERVIO OPTICO Y CELULAS GANGLION | Q87: 1 | R87: PRECISA | S87: INSTITUTO MEDICO QUIRURGICO AREQUIPA S.A | T87: INSTITUTO MEDICO QUIRURGICO AREQUIPA S.A | U87: L.CENTRO | V87: LMAGAN | W87: 186.44 | X87: LN. EXAMENES | Y87: CIAS. DE SEGURO | Z87: CENTRO | AA87: 966697811 | AB87: 0011-0184-0200649518
A88: 46189 | B88: 98965 | C88: BO | D88: 11556 | E88: CO | F88: BO-11556 | G88: RODRIGUEZ VELA KATHERINE FIORELLA | H88: 76232484 | I88: FIERRO LEANDRO | J88: POLICLÍNICO DIVINO NIÑO JESÚS | K88: CRISTINA | L88: 0070028 | M88: 906 777 340 | N88: RODRIGUEZ VELA KATHERINE FIORELLA | O88: 86877 | P88: BIOMETRIA IOL MASTER 700 | Q88: 1 | R88: PRECISA | S88: INSTITUTO MEDICO QUIRURGICO AREQUIPA S.A | T88: INSTITUTO MEDICO QUIRURGICO AREQUIPA S.A | U88: L.CENTRO | V88: LMAGAN | W88: 42.37 | X88: LN. EXAMENES | Y88: CIAS. DE SEGURO | Z88: CENTRO
A89: 46189 | B89: 98965 | C89: BO | D89: 11556 | E89: CO | F89: BO-11556 | G89: RODRIGUEZ VELA KATHERINE FIORELLA | H89: 76232484 | I89: FIERRO LEANDRO | J89: POLICLÍNICO DIVINO NIÑO JESÚS | K89: CRISTINA | L89: 0070028 | M89: 906 777 340 | N89: RODRIGUEZ VELA KATHERINE FIORELLA | O89: 86877 | P89: MICROSCOPIA ESPECULAR | Q89: 1 | R89: PRECISA | S89: INSTITUTO MEDICO QUIRURGICO AREQUIPA S.A | T89: INSTITUTO MEDICO QUIRURGICO AREQUIPA S.A | U89: L.CENTRO | V89: LMAGAN | W89: 42.37 | X89: LN. EXAMENES | Y89: CIAS. DE SEGURO | Z89: CENTRO
A90: 46189 | B90: 98915 | C90: BO | D90: 11546 | E90: CO | F90: BO-11546 | G90: MANCO CESPEDES EMMA IMELDA | H90: 08826096 | I90: ESPEJO ALVA JULIO EDWIN | J90: CONSULTORIO PARTICULAR | K90: CRISTINA | L90: 0070206 | M90: 964035237 | N90: MANCO CESPEDES EMMA IMELDA | O90: 86820 | P90: OCT DE MACULA | Q90: 1 | R90: PRECISA | S90: POR ASIGNAR | T90: INSTITUTO MEDICO QUIRURGICO AREQUIPA S.A | U90: L.CENTRO | V90: LMAGAN | W90: 186.44 | X90: LN. EXAMENES | Y90: CIAS. DE SEGURO | Z90: CENTRO | AA90: 981227454 | AB90: 087-3150119440
A91: 46189 | B91: 98930 | C91: BO | D91: 5621 | E91: CO | F91: BO-5621 | G91: ESPINOZA BEDRIÑANA SUSANA | H91: 08578137 | I91: HUAMAN CUICAPUSA KELLY | K91: CRISTINA | L91: 0070218 | M91: 991432739 | N91: ESPINOZA BEDRIÑANA SUSANA | O91: 86839 | P91: CAMPIMETRIA (CAMPO VISUAL) | Q91: 1 | R91: PRECISA | S91: INSTITUTO MEDICO QUIRURGICO AREQUIPA S.A | T91: INSTITUTO MEDICO QUIRURGICO AREQUIPA S.A | U91: L.CENTRO | V91: ACABRERA | W91: 135.59 | X91: LN. EXAMENES | Y91: CIAS. DE SEGURO | Z91: CENTRO
A92: 46190 | B92: 99046 | C92: BO | D92: 11571 | E92: CO | F92: BO-11571 | G92: AURIS ZENTENO DE TELLO ZENAIDA MARINA | H92: 09212243 | I92: ORNA ACOSTA JORGE AQUILES | J92: HOSPITAL LOAYZA | K92: CRISTINA | L92: 0070254 | M92: 965361980 | N92: AURIS ZENTENO DE TELLO ZENAIDA MARINA | O92: 86936 | P92: USO DE EQUIPOS E INSUMO CAPSULOTOMIA | Q92: 1 | R92: PRECISA | S92: INSTITUTO MEDICO QUIRURGICO AREQUIPA S.A | T92: INSTITUTO MEDICO QUIRURGICO AREQUIPA S.A | U92: L.CENTRO | V92: LMAGAN | W92: 101.69 | X92: LN. PROCEDIMIENTO | Y92: CIAS. DE SEGURO | Z92: CENTRO | AA92: 999996347 | AB92: 052-7510523
A93: 46190 | B93: 99113 | C93: BO | D93: 11578 | E93: CO | F93: BO-11578 | G93: SACA TICONA NELSON | H93: 42449449 | I93: AGRAMONTE ZEA EDILBERTO | J93: HOSPITAL DE LA SOLIDARIDAD SJL | K93: CRISTINA | L93: 0070273 | M93: 945692301 | N93: SACA TICONA NELSON | O93: 86964 | P93: OCT DE NERVIO OPTICO Y CELULAS GANGLION | Q93: 1 | R93: PRECISA | S93: INSTITUTO MEDICO QUIRURGICO AREQUIPA S.A | T93: INSTITUTO MEDICO QUIRURGICO AREQUIPA S.A | U93: L.CENTRO | V93: LMAGAN | W93: 186.44 | X93: LN. EXAMENES | Y93: CIAS. DE SEGURO | Z93: CENTRO | AA93: 987407712 | AB93: 0011-0190-0200333106
A94: 46190 | B94: 98996 | C94: FA | D94: 1037 | E94: CO | F94: FA-1037 | G94: BARAHONA VERASTEGUI MEDARDO | H94: 08834924 | I94: FIERRO LEANDRO | J94: POLICLÍNICO DIVINO NIÑO JESÚS | K94: CRISTINA | L94: 0070031 | M94: 981607915 | N94: GRUPO MEDICO INTEGRAL SOCIEDAD ANONIMA CERRADA | O94: 86546 | P94: CIRUGIA DE DIA | Q94: 1 | R94: PRECISA | S94: POR ASIGNAR | T94: INSTITUTO MEDICO QUIRURGICO AREQUIPA S.A | U94: L.CENTRO | V94: LMAGAN | W94: 0 | X94: LN. CIRUGIA | Y94: CIAS. DE SEGURO | Z94: CENTRO
A95: 46190 | B95: 98996 | C95: FA | D95: 1037 | E95: CO | F95: FA-1037 | G95: BARAHONA VERASTEGUI MEDARDO | H95: 08834924 | I95: FIERRO LEANDRO | J95: POLICLÍNICO DIVINO NIÑO JESÚS | K95: CRISTINA | L95: 0070031 | M95: 981607915 | N95: GRUPO MEDICO INTEGRAL SOCIEDAD ANONIMA CERRADA | O95: 86546 | P95: FACOEMULSIFICACION PRIMIUM | Q95: 1 | R95: PRECISA | S95: POR ASIGNAR | T95: INSTITUTO MEDICO QUIRURGICO AREQUIPA S.A | U95: L.CENTRO | V95: LMAGAN | W95: 762.71 | X95: LN. CIRUGIA | Y95: CIAS. DE SEGURO | Z95: CENTRO
A96: 46190 | B96: 99003 | C96: FA | D96: 1040 | E96: CO | F96: FA-1040 | G96: RODRIGUEZ VELA KATHERINE FIORELLA | H96: 76232484 | I96: FIERRO LEANDRO | J96: POLICLÍNICO DIVINO NIÑO JESÚS | K96: CRISTINA | L96: 0070028 | M96: 906 777 340 | N96: GRUPO MEDICO INTEGRAL SOCIEDAD ANONIMA CERRADA | O96: 86827 | P96: CIRUGIA DE DIA | Q96: 1 | R96: PRECISA | S96: POR ASIGNAR | T96: INSTITUTO MEDICO QUIRURGICO AREQUIPA S.A | U96: L.CENTRO | V96: LMAGAN | W96: 0 | X96: LN. CIRUGIA | Y96: CIAS. DE SEGURO | Z96: CENTRO
A97: 46190 | B97: 99003 | C97: FA | D97: 1040 | E97: CO | F97: FA-1040 | G97: RODRIGUEZ VELA KATHERINE FIORELLA | H97: 76232484 | I97: FIERRO LEANDRO | J97: POLICLÍNICO DIVINO NIÑO JESÚS | K97: CRISTINA | L97: 0070028 | M97: 906 777 340 | N97: GRUPO MEDICO INTEGRAL SOCIEDAD ANONIMA CERRADA | O97: 86827 | P97: CIRUGIA REFRACTIVA TRANS PRK | Q97: 1 | R97: PRECISA | S97: POR ASIGNAR | T97: INSTITUTO MEDICO QUIRURGICO AREQUIPA S.A | U97: L.CENTRO | V97: LMAGAN | W97: 550.85 | X97: LN. CIRUGIA | Y97: CIAS. DE SEGURO | Z97: CENTRO
A98: 46190 | B98: 99095 | C98: BO | D98: 11575 | E98: CO | F98: BO-11575 | G98: BAUTISTA LOPEZ HERMINIA | H98: 21840481 | I98: SUAREZ ALVARADO SUSANA | J98: CLINICA INTERNACIONAL SURCO | K98: CRISTINA | L98: 0044128 | M98: 999166413 | N98: BAUTISTA LOPEZ HERMINIA | O98: 86938 | P98: CIRUGIA DE DIA | Q98: 1 | R98: PRECISA | S98: INSTITUTO MEDICO QUIRURGICO AREQUIPA S.A | T98: INSTITUTO MEDICO QUIRURGICO AREQUIPA S.A | U98: L.CENTRO | V98: LMAGAN | W98: 0 | X98: LN. CIRUGIA | Y98: CIAS. DE SEGURO | Z98: CENTRO
A99: 46190 | B99: 99095 | C99: BO | D99: 11575 | E99: CO | F99: BO-11575 | G99: BAUTISTA LOPEZ HERMINIA | H99: 21840481 | I99: SUAREZ ALVARADO SUSANA | J99: CLINICA INTERNACIONAL SURCO | K99: CRISTINA | L99: 0044128 | M99: 999166413 | N99: BAUTISTA LOPEZ HERMINIA | O99: 86938 | P99: CONJUNTIVOPLASTIA | Q99: 1 | R99: PRECISA | S99: INSTITUTO MEDICO QUIRURGICO AREQUIPA S.A | T99: INSTITUTO MEDICO QUIRURGICO AREQUIPA S.A | U99: L.CENTRO | V99: LMAGAN | W99: 139.83 | X99: LN. CIRUGIA | Y99: CIAS. DE SEGURO | Z99: CENTRO
A100: 46191 | B100: 99135 | C100: BO | D100: 5638 | E100: CO | F100: BO-5638 | G100: DIAZ ESCOBAL AUGUSTO | H100: 08560804 | I100: VILLAR CURAHUA MARCELA ALEJANDRA | J100: GAMARRA SALUD | K100: CRISTINA | L100: 0070232 | M100: 923538499 | N100: DIAZ ESCOBAL AUGUSTO | O100: 86977 | P100: BIOMETRIA IOL MASTER 700 | Q100: 1 | R100: PRECISA | S100: INSTITUTO MEDICO QUIRURGICO AREQUIPA S.A | T100: INSTITUTO MEDICO QUIRURGICO AREQUIPA S.A | U100: L.CENTRO | V100: ACABRERA | W100: 42.37 | X100: LN. EXAMENES | Y100: CIAS. DE SEGURO | Z100: CENTRO | AA100: 950133748 | AB100: 191-9953047026
A101: 46191 | B101: 99135 | C101: BO | D101: 5638 | E101: CO | F101: BO-5638 | G101: DIAZ ESCOBAL AUGUSTO | H101: 08560804 | I101: VILLAR CURAHUA MARCELA ALEJANDRA | J101: GAMARRA SALUD | K101: CRISTINA | L101: 0070232 | M101: 923538499 | N101: DIAZ ESCOBAL AUGUSTO | O101: 86977 | P101: MICROSCOPIA ESPECULAR | Q101: 1 | R101: PRECISA | S101: INSTITUTO MEDICO QUIRURGICO AREQUIPA S.A | T101: INSTITUTO MEDICO QUIRURGICO AREQUIPA S.A | U101: L.CENTRO | V101: ACABRERA | W101: 42.37 | X101: LN. EXAMENES | Y101: CIAS. DE SEGURO | Z101: CENTRO | AA101: 950133748 | AB101: 191-9953047026
A102: 46191 | B102: 99177 | C102: BO | D102: 3911 | E102: CO | F102: BO-3911 | G102: ALANIA SUAREZ DE GIL DIONICIA | H102: 07738357 | I102: RUIZ ROJAS PAUBLO ENRIQUE | J102: CONSULTORIO CUBANO COMAS | K102: CRISTINA | L102: 0070290 | M102: 991819463 | N102: ALANIA SUAREZ DE GIL DIONICIA | O102: 87014 | P102: OCT DE MACULA | Q102: 1 | R102: PRECISA LN | S102: POR ASIGNAR | T102: INSTITUTO MEDICO QUIRURGICO AREQUIPA S.A | U102: L.NORTE | V102: BGALLOSA | W102: 186.44 | X102: LN. EXAMENES | Y102: CIAS. DE SEGURO | Z102: NORTE | AA102: 992903716 | AB102: 191-91415089071
A103: 46191 | B103: 99136 | C103: BO | D103: 5639 | E103: CO | F103: BO-5639 | G103: DIAZ ESCOBAL AUGUSTO | H103: 08560804 | I103: FIERRO LEANDRO | J103: POLICLÍNICO DIVINO NIÑO JESÚS | K103: CRISTINA | L103: 0070232 | M103: 923538499 | N103: DIAZ ESCOBAL AUGUSTO | O103: 86978 | P103: HEMOGRAMA COMPLETO | Q103: 1 | R103: PRECISA | S103: INSTITUTO MEDICO QUIRURGICO AREQUIPA S.A | T103: INSTITUTO MEDICO QUIRURGICO AREQUIPA S.A | U103: L.CENTRO | V103: ACABRERA | W103: 12.71 | X103: LN. LABORATORIO | Y103: CIAS. DE SEGURO | Z103: CENTRO
A104: 46191 | B104: 99136 | C104: BO | D104: 5639 | E104: CO | F104: BO-5639 | G104: DIAZ ESCOBAL AUGUSTO | H104: 08560804 | I104: FIERRO LEANDRO | J104: POLICLÍNICO DIVINO NIÑO JESÚS | K104: CRISTINA | L104: 0070232 | M104: 923538499 | N104: DIAZ ESCOBAL AUGUSTO | O104: 86978 | P104: ORINA COMPLETO | Q104: 1 | R104: PRECISA | S104: INSTITUTO MEDICO QUIRURGICO AREQUIPA S.A | T104: INSTITUTO MEDICO QUIRURGICO AREQUIPA S.A | U104: L.CENTRO | V104: ACABRERA | W104: 21.19 | X104: LN. LABORATORIO | Y104: CIAS. DE SEGURO | Z104: CENTRO
A105: 46191 | B105: 99136 | C105: BO | D105: 5639 | E105: CO | F105: BO-5639 | G105: DIAZ ESCOBAL AUGUSTO | H105: 08560804 | I105: FIERRO LEANDRO | J105: POLICLÍNICO DIVINO NIÑO JESÚS | K105: CRISTINA | L105: 0070232 | M105: 923538499 | N105: DIAZ ESCOBAL AUGUSTO | O105: 86978 | P105: GLUCOSA | Q105: 1 | R105: PRECISA | S105: INSTITUTO MEDICO QUIRURGICO AREQUIPA S.A | T105: INSTITUTO MEDICO QUIRURGICO AREQUIPA S.A | U105: L.CENTRO | V105: ACABRERA | W105: 12.71 | X105: LN. LABORATORIO | Y105: CIAS. DE SEGURO | Z105: CENTRO
A106: 46191 | B106: 99136 | C106: BO | D106: 5639 | E106: CO | F106: BO-5639 | G106: DIAZ ESCOBAL AUGUSTO | H106: 08560804 | I106: FIERRO LEANDRO | J106: POLICLÍNICO DIVINO NIÑO JESÚS | K106: CRISTINA | L106: 0070232 | M106: 923538499 | N106: DIAZ ESCOBAL AUGUSTO | O106: 86978 | P106: TIEMPO DE COAGULACION Y SANGRIA | Q106: 1 | R106: PRECISA | S106: INSTITUTO MEDICO QUIRURGICO AREQUIPA S.A | T106: INSTITUTO MEDICO QUIRURGICO AREQUIPA S.A | U106: L.CENTRO | V106: ACABRERA | W106: 12.71 | X106: LN. LABORATORIO | Y106: CIAS. DE SEGURO | Z106: CENTRO
A107: 46191 | B107: 99136 | C107: BO | D107: 5639 | E107: CO | F107: BO-5639 | G107: DIAZ ESCOBAL AUGUSTO | H107: 08560804 | I107: FIERRO LEANDRO | J107: POLICLÍNICO DIVINO NIÑO JESÚS | K107: CRISTINA | L107: 0070232 | M107: 923538499 | N107: DIAZ ESCOBAL AUGUSTO | O107: 86978 | P107: HIV 1,2 (TEST RAPIDO) | Q107: 1 | R107: PRECISA | S107: INSTITUTO MEDICO QUIRURGICO AREQUIPA S.A | T107: INSTITUTO MEDICO QUIRURGICO AREQUIPA S.A | U107: L.CENTRO | V107: ACABRERA | W107: 50.85 | X107: LN. LABORATORIO | Y107: CIAS. DE SEGURO | Z107: CENTRO
A108: 46191 | B108: 99138 | C108: BO | D108: 5640 | E108: CO | F108: BO-5640 | G108: DIAZ ESCOBAL AUGUSTO | H108: 08560804 | I108: FIERRO LEANDRO | J108: POLICLÍNICO DIVINO NIÑO JESÚS | K108: CRISTINA | L108: 0070232 | M108: 923538499 | N108: DIAZ ESCOBAL AUGUSTO | O108: 86979 | P108: ELECTROCARDIOGRAMA-EKG | Q108: 1 | R108: PRECISA | S108: INSTITUTO MEDICO QUIRURGICO AREQUIPA S.A | T108: INSTITUTO MEDICO QUIRURGICO AREQUIPA S.A | U108: L.CENTRO | V108: ACABRERA | W108: 127.12 | X108: LN. EXAMENES | Y108: CIAS. DE SEGURO | Z108: CENTRO
A109: 46191 | B109: 99219 | C109: FA | D109: 541 | E109: CO | F109: FA-541 | G109: DIAZ ESCOBAL AUGUSTO | H109: 08560804 | I109: FIERRO LEANDRO | J109: POLICLÍNICO DIVINO NIÑO JESÚS | K109: CRISTINA | L109: 0070232 | M109: 923538499 | N109: GRUPO MEDICO INTEGRAL SOCIEDAD ANONIMA CERRADA | O109: 87029 | P109: CIRUGIA DE DIA | Q109: 1 | R109: PRECISA | S109: INSTITUTO MEDICO QUIRURGICO AREQUIPA S.A | T109: INSTITUTO MEDICO QUIRURGICO AREQUIPA S.A | U109: L.CENTRO | V109: ACABRERA | W109: 0 | X109: LN. CIRUGIA | Y109: CIAS. DE SEGURO | Z109: CENTRO
A110: 46191 | B110: 99219 | C110: FA | D110: 541 | E110: CO | F110: FA-541 | G110: DIAZ ESCOBAL AUGUSTO | H110: 08560804 | I110: FIERRO LEANDRO | J110: POLICLÍNICO DIVINO NIÑO JESÚS | K110: CRISTINA | L110: 0070232 | M110: 923538499 | N110: GRUPO MEDICO INTEGRAL SOCIEDAD ANONIMA CERRADA | O110: 87029 | P110: FACOEMULSIFICACION PRIMIUM | Q110: 1 | R110: PRECISA | S110: INSTITUTO MEDICO QUIRURGICO AREQUIPA S.A | T110: INSTITUTO MEDICO QUIRURGICO AREQUIPA S.A | U110: L.CENTRO | V110: ACABRERA | W110: 762.71 | X110: LN. CIRUGIA | Y110: CIAS. DE SEGURO | Z110: CENTRO
A111: 46191 | B111: 99133 | C111: BO | D111: 5637 | E111: CO | F111: BO-5637 | G111: SALAS CABREJO NASARIO | H111: 70358831 | I111: SOTO IDROGO CLAUDIA | J111: CLÍNICA JESÚS DEL NORTE (JM) | K111: CRISTINA | L111: 0070279 | M111: 969350781 | N111: SALAS CABREJO NASARIO | O111: 86975 | P111: CAMPIMETRIA (CAMPO VISUAL) | Q111: 1 | R111: PRECISA | S111: INSTITUTO MEDICO QUIRURGICO AREQUIPA S.A | T111: INSTITUTO MEDICO QUIRURGICO AREQUIPA S.A | U111: L.CENTRO | V111: ACABRERA | W111: 135.59 | X111: LN. EXAMENES | Y111: CIAS. DE SEGURO | Z111: CENTRO | AA111: 986089286 | AB111: 191-32083755032
A112: 46192 | B112: 99250 | C112: BO | D112: 3916 | E112: CO | F112: BO-3916 | G112: ZAVALA MARTINEZ JORGE ALFONSO | H112: 06134501 | K112: CRISTINA | L112: 0070311 | M112: 944326227 | N112: ZAVALA MARTINEZ JORGE ALFONSO | O112: 87070 | P112: CAMPIMETRIA (CAMPO VISUAL) | Q112: 1 | R112: PRECISA LN | S112: POR ASIGNAR | T112: INSTITUTO MEDICO QUIRURGICO AREQUIPA S.A | U112: L.NORTE | V112: BGALLOSA | W112: 135.59 | X112: LN. EXAMENES | Y112: CIAS. DE SEGURO | Z112: NORTE
...

Sheet Cuentas
A1: Médico | B1: Celular | C1: Banco | D1: # Cuenta | E1: # CCI | F1: Institución | G1: Columna1
A2: CASTILLO JAVE NANDY | B2: 900734202 | C2: BANCO DE LA NACIÓN | D2: 04-531049328 | E2: 018-53100453104932848 | F2: HOSPITAL LOAYZA
A3: LINO LARREA CARLOS ENRIQUE | B3: 930793497 | C3: BANCO DE LA NACIÓN | D3: 04-261072713 | E3: 018-26100426107271385 | F3: HOSPITAL INO
A4: ZEBALLOS AYQUIPA MISHELLY JOHANA | B4: 949717538 | C4: BANCO DE LA NACIÓN | D4: 04-021092202 | E4: 018-00000402109220203 | F4: HOSPITAL DE POLICIA
A5: TRINIDAD MOLINA ZOSIMO | B5: 986294682 | C5: BANCO DE LA NACIÓN | D5: 04-042865309 | E5: 018-00000404286530907 | F5: VES
A6: ENTENZA NALIA | B6: 915394967 | C6: BBVA | D6: 0011-0814-0245234827 | E6: 011-814-000245234827-15 | F6: UNIDERMA JESUS MARÍA
A7: ESPINOZA LAVALLE CESAR FRANKZ | B7: 937242809 | C7: BBVA | D7: 0011-0057-0229787021 | E7: 011-057-000229787021-70 | F7: CLINICA DIVINO NIÑO JESÚS
A8: BARRANTES RAMIREZ ELENA JESUS AMERICA | B8: 940621858 | C8: BBVA | D8: 0011-0616-0200286900 | E8: 011-616-000200286900-02 | F8: OPELUCE LINCE
A9: HUAMAN MENDEZ NATHALY VANESSA | B9: 945751945 | C9: BBVA | D9: 0011-0186-0200772531 | F9: HOSPITAL DE POLICIA
A10: CASAVERDE VILLACORTA CARLOS ALBERTO | B10: 945930825 | C10: BBVA | D10: 0011-0486-0200014689 | E10: 011-486-000200014689-80 | F10: HOSPITAL GRAU
A11: PEREZ PRADO WILSON | B11: 947591368 | C11: BBVA | D11: 0011-0814-0238585177 | E11: 011-814-000238585177-15 | F11: HOSPITAL SERGIO BERNALES
A12: GAMERO FERNANDEZ EBERTH LELYS | B12: 948878123 | C12: BBVA | D12: 0011-0057-0209443814 | E12: 011-057-000209443814-76 | F12: CONSULTORIO PARTICULAR
A13: NUÑEZ DEL PRADO CUADROS MARIELA DIANA | B13: 959068627 | C13: BBVA | D13: 0011-0180-0200473345 | E13: 011-180-000200473345-73 | F13: HOSPITAL LOAYZA
A14: RIVERA FERNANDEZ JORGE GUSTAVO | B14: 959103507 | C14: BBVA | D14: 0011-0148-0200516341 | E14: 011-148-000200516341-41 | F14: CLINICA VER
A15: MONTOYA DELGADO MANUEL JESUS | B15: 959529890 | C15: BBVA | D15: 0011-0115-0100070311 | E15: 011-115-000100070311-34 | F15: CONSULTORIO
A16: CACERES PINTO ALVARO DANIEL | B16: 966697811 | C16: BBVA | D16: 0011-0184-0200649518 | E16: 011-184-000200649518-94 | F16: HOSPITAL INO
A17: GARRO ROSAS LUCIA | B17: 976498726 | C17: BBVA | D17: 0011-0148-0200614041 | E17: 011-148-000200614041-48 | F17: HOSPITAL SABOGAL
A18: FONTENLA SERNA DAVID IVAN | B18: 976922608 | C18: BBVA | D18: 0011-0117-0200577155 | E18: 011-117-000200577155-91 | F18: HOSPITAL NAVAL
A19: ALCOCER DE LA CRUZ REGINA ROCIO | B19: 981953525 | C19: BBVA | D19: 0011-0190-0200562504 | E19: 011-190-000200562504-67 | F19: OPELUCE LINCE
A20: GUTARRA PAUCAR JULIA KARINA | B20: 982673362 | C20: BBVA | D20: 0011-0353-0200308107 | E20: 0113-5300-0200308107-08 | F20: CLÍNICA SAN CAMILO
A21: ZUÑIGA SANCHEZ MARIA DEL PILAR | B21: 983338097 | C21: BBVA | D21: 0011-0057-0233799581 | E21: 011-057-000233799581-71 | F21: HOSPITAL ALMENARA
... A42: CONTRERAS SILVA ÁNGEL ALFREDO | B42: 997171889 | C42: BBVA | D42: 0011-0118-0200430370 | E42: 011-118-000200430370-73 | F42: CONSULTORIO PARTICULAR
A43: MEDRANO GUILLERMO LISSET | B43: 989704320 | C43: BBVA | D43: 0011-0189-0200431226 | F43: HOSPITAL DE LA SOLIDARIDAD
A44: LOPEZ MARTINEZ ALEXANDRA | B44: 929966474 | C44: BBVA | D44: 0011-0153-0200750511 | E44: 011-153-000200750511-44 | F44: HOSPITAL DE POLICIA
A45: RISCO CHANG ROXANA | B45: 961025690 | C45: BBVA | D45: 0011-0122-0200631866 | E45: 011-122-000200631866-97 | F45: CLINICA SAN GABRIEL
A46: SAAVEDRA ESPINOZA DARIELA MARIEL | B46: 991056603 | C46: BBVA | D46: 0011-0320-0200072928 | E46: 011-320-000200072928-91 | F46: HOSPITAL SABOGAL
A47: SANDOVAL ERQUINEO JHOVANA LICED | B47: 939369228 | C47: BBVA | D47: 0011-0057-0219092475 | E47: 011-057-000219092475-79 | F47: HOSPITAL SERGIO BERNALES
A48: YOVERA LEYVA ELSA MARIANELA | B48: 982192071 | C48: BBVA | D48: 0011-0320-0200277139 | E48: 011-320-000200277139-98 | F48: HOSPITAL 2 DE MAYO
A49: ÑAUPARI MEZA BRENNER ALBERTO | B49: 940248463 | C49: BBVA | D49: 0011-0712-0200343264 | E49: 011-712-000200343264-74 | F49: HOSPITAL ALMENARA
A50: ALVARO TAMBRA WENDY CAROLA | B50: 972627309 | C50: BBVA | D50: 0011-0320-0200061187 | E50: 011-320-000200061187-97 | F50: POLICLÍNICO PABLO BERMUDEZ
A51: PUICAN NAVARRO GUIDO ALFREDO | B51: 999088459 | C51: BBVA | D51: 0011-0286-0200053326 | E51: 011-286-000200053326-21 | F51: CONSULTORIO PARTICULAR
A52: JANAMPA CAMPOS WILSON ALEXANDER | B52: 926323940 | C52: BCP | D52: 315-99346437032 | E52: 00231519934643703204 | F52: HOSPITAL SAN JOSE
A53: QUIROZ MONTOYA CLAUDIA MICHAEL | B53: 931781027 | C53: BCP | D53: 191-14161745092 | E53: 00219111416174509250 | F53: HOSPITAL HIPOLITO UNANUE
A54: SANTE MORALES JOEL EDMUNDO | B54: 941044046 | C54: BCP | D54: 430-32526176035 | E54: 00243013252617603579 | F54: CONSULTORIO PARTICULAR
A55: BARREDA FUENTES ANDRES DANIEL | B55: 941411075 | C55: BCP | D55: 193-36174976078 | E55: 00219313617497607000 | F55: HOSPITAL DE POLICIA
A56: GALINDO SIHUIN YOSELL RAFAEL | B56: 942457955 | C56: BCP | D56: 192-99257733034 | E56: 00219219925773303430
A57: CARDENAS ROLANDO | B57: 943196346 | C57: BCP | D57: 193-04298551069 | E57: 00219310429855106913 | F57: HOSPITAL INO
A58: HOYOS SAENZ ANGELA | B58: 945127415 | C58: BCP | D58: 245-99508929094 | E58: 00224519950892909494 | F58: HOSPITAL LOAYZA
A59: CARDENAS ORTEGA MARISA | B59: 947054605 | C59: BCP | D59: 193-34139202041 | E59: 00219313413920204000 | F59: CONSULTORIO
A60: HERNANDEZ PEÑA ARTURO GABRIEL | B60: 949900695 | C60: BCP | D60: 191-15421658031 | E60: 00219111542165803150 | F60: HOSPITAL DE POLICIA
A61: VILLAR CURAHUA MARCELA ALEJANDRA | B61: 950133748 | C61: BCP | D61: 191-9953047026 | E61: 00219100995304702651 | F61: GAMARRA SALUD
A62: MARCHENA SOSA CAROLINA VIRGINIA | B62: 954714715 | C62: BCP | D62: 191-02898958038 | E62: 00219110289895803000 | F62: HOSPITAL DEL NIÑO
A63: ESPINOZA OSTOS MEIDA ANAMITH | B63: 955787986 | C63: BCP | D63: 193-94591868039 | E63: 00219319459186803913 | F63: HOSPITAL DE LA SOLIDARIDAD CAMANA
A64: SANCHEZ ORTIZ JOANA PAMELA | B64: 962358230 | C64: BCP | D64: 193-29575027063 | E64: 00219312957502706000 | F64: HOSPITAL REBAGLEATI
A65: PEÑA CAMARGO CRISTOPHER OMAR | B65: 964328569 | C65: BCP | D65: 191-70241223029 | E65: 00219117024122302954 | F65: HOSPITAL SERGIO BERNALES
A66: MENDOZA VASQUEZ HERNAN MARCO | B66: 975712892 | C66: BCP | D66: 193-91671252022 | E66: 00219319167125202000 | F66: HOSPITAL DE POLICIA
A67: BOBBIO PEREZ MILKO | B67: 981214114 | C67: BCP | D67: 191-98432106068 | E67: 00219119843210606000 | F67: CONSULTORIO
A68: CHAFLOQUE CERVANTES AUGUSTO BERNADINO | B68: 987407109 | C68: BCP | D68: 191-18537427072 | E68: 00219111853742707254 | F68: CONSULTORIO
A69: ALBAN ZAPATA GUIDO | B69: 987407712 | C69: BCP | D69: 193-15254018098 | E69: 00219311525401809819
A70: ESPINOZA HUMAREDA IVAN | B70: 987537470 | C70: BCP | D70: 191-23580691078 | E70: 00219112358069107853 | F70: HOSPITAL DE POLICIA
A71: DULANTO REINOSO VICTOR CHRISTIAN | B71: 989688510 | C71: BCP | D71: 193-2438485060 | E71: 00219300243848506018 | F71: CLINICA DULANTO
A72: REYES CUBAS MARIA MANUELA | B72: 990246916 | C72: BCP | D72: 191-24412701093 | E72: 00219112441270109000 | F72: CONSULTORIO PARTICULAR
A73: PAREDES ARAMBURU NANCY | B73: 992482115 | C73: BCP | D73: 193-36243352045 | E73: 00219313624335204000 | F73: HOSPITAL HIPOLITO UNANUE
A74: CORNEJO ZAGA MAX JOSE | B74: 992736060 | C74: BCP | D74: 194-99321092033 | E74: 00219419932109203391 | F74: HOSPITAL CAYETANO HEREDIA
A75: RUIZ ROJAS PAUBLO ENRIQUE | B75: 992903716 | C75: BCP | D75: 191-91415089071 | E75: 00219119141508907154 | F75: CONSULTORIO CUBANO COMAS
A76: ALVA FLORES VICTOR MANUEL | B76: 993397164 | C76: BCP | D76: 193-17207029036 | E76: 00219311720702903000 | F76: HOSPITAL ALMENARA
A77: MENDOZA DIAZ NORA BEATRIZ | B77: 993540760 | C77: BCP | D77: 191-03554214014 | E77: 00219110355421401000 | F77: ESSALUD ATE
A78: GISMONDI ALEGRE JUAN ALBERTO | B78: 995175656 | C78: BCP | D78: 192-01819241015 | E78: 00219210181924101538 | F78: HOSPITAL SABOGAL
A79: ZELADA LORENZO ANGEL MIGUEL | B79: 995833213 | C79: BCP | D79: 191-14525587008 | E79: 00219111452558700000 | F79: HOSPITAL NAVAL
A80: DURAN ESPINOZA CESAR ARTURO | B80: 995868651 | C80: BCP | D80: 191-92300592019 | E80: 00219119230059201956 | F80: CONSULTORIO LA MOLINA
A81: DIAZ ZARATE ELIZA MARIELA | B81: 997581972 | C81: BCP | D81: 193-91363094051 | E81: 00219319136309405111 | F81: HOSPITAL DE POLICIA
... A98: LLACCTARIMAY SANCHEZ CALEB | B98: 949080267 | C98: BCP | D98: 191-35576688046 | E98: 00219113557668804659 | F98: HOSPITAL DE SJL
A99: LOPEZ ESPINOZA JHON | C99: BCP | D99: 191-38880905040 | E99: 00219113888090504052
A100: PALACIOS URIBE PAMELA CAROLINA | B100: 994872106 | C100: BCP | D100: 193-95965374018 | E100: 00219319596537401819 | F100: CONSULTORIO PARTICULAR
A101: PINEDA SANCHEZ MAYKOL JUNIORS | B101: 981329298 | C101: BCP | D101: 193-04276035026 | E101: 00219310427603502615 | F101: HOSPITAL B. LEGUIA
A102: POVIS JUYO STEVEN | B102: 986276525 | C102: BCP | D102: 194-37627087056 | E102: 00219413762708705694 | F102: HOSPITAL DE PUENTE PIEDRA
A103: REGALADO GUTIERREZ EVELYN JOSSY | B103: 999375924 | C103: BCP | D103: 194-92762725020 | E103: 00219419276272502095 | F103: POLICLÍNICO MUNICIPAL LOS OLIVOS
A104: RIOS DIONICIO GARY | B104: 929861879 | C104: BCP | D104: 191-98745615043 | E104: 00219119874561504000 | F104: HOSPITAL CAYETANO HEREDIA
A105: RODRIGUEZ RIVERO DARLEN | B105: 983837511 | C105: BCP | D105: 191-06277655064 | E105: 00219110627765506000 | F105: HOSPITAL CAYETANO HEREDIA
A106: ROMANI FLORES LILIA | B106: 907151482 | C106: BCP | D106: 191-74255909067 | E106: 00219117425590906000 | F106: HOSPITAL ALMENARA
A107: SOTO IDROGO CLAUDIA | B107: 986089286 | C107: BCP | D107: 191-32083755032 | E107: 00219113208375503257 | F107: CLÍNICA JESÚS DEL NORTE (JM)
A108: VERA AVELINO NILO FRANCISCO | B108: 976141343 | C108: BCP | D108: 191-35576688046 | E108: 00219319179265805000 | F108: HOSPITAL MONGRUT
A109: CRISPIN MORALES NANCY JENNY | B109: 978789268 | C109: BCP | D109: 193-90416675072 | E109: 002-19319041667507211 | F109: HOSPITAL ALMENARA
A110: MERA BARBOZA MARCO | B110: 940468354 | C110: INTERBANK | D110: 166-3412325450 | E110: 00316601341232545067 | F110: HOSPITAL INO
A111: ROLDAN CORNEJO EILEEN SONIA | B111: 948328025 | C111: INTERBANK | D111: 378-3066335363 | E111: 00337801306633536374 | F111: HOSPITAL DE POLICIA
... A127: TORRES INUMA JOSY ALEXIS | B127: 950486025 | C127: INTERBANK | D127: 898 3427810358 | E127: 00389801342781035000 | F127: CLINICA MAISON DE SANTE
A128: TORRES FELIX | C128: INTERBANK | D128: 898 3427810358 | E128: 00389801342781035842
A129: LAU CUBA LUIS ALBERTO | B129: 936892722 | C129: PICHINCHA | D129: 000-14-3049933 | E129: 035-00000014304993393 | F129: CONSULTORIO
A130: MOYA AYRE EUGENIO FRANCKLIN | B130: 975726361 | C130: SCOTIABANK | D130: 691-0437489 | E130: 009-69120691043748970 | F130: CLINICA LA LUZ
A131: POMAZONGO GOYAS MANUEL ALEJANDRO | B131: 980030101 | C131: SCOTIABANK | D131: 027-7601910 | E131: 009-21920027760191075 | F131: CONSULTORIO PARTICULAR
A132: LLERENA MORALES OSCAR ADOLFO | B132: 987552890 | C132: SCOTIABANK | D132: 098-7304409 | E132: 009-09120098730440902 | F132: SANNA SAN MIGUEL
A133: HUAMANI LEANDRO MILSSA | B133: 995247963 | C133: SCOTIABANK | D133: 833-0433142 | E133: 009-72420833043314268 | F133: HOSPITAL REBAGLEATI
A134: LATOCHE ROJAS CONRAD EDWARD | B134: 999424542 | C134: SCOTIABANK | D134: 027-7291225 | E134: 009-21920027729122573 | F134: HOSPITAL MARIA AUXILIADORA
A135: ORNA ACOSTA JORGE AQUILES | B135: 999996347 | C135: SCOTIABANK | D135: 052-7510523 | E135: 009-05520052751052354 | F135: HOSPITAL LOAYZA
A136: VILLA CABRERA LUIS ALEJANDRO | B136: 975429533 | C136: SCOTIABANK | D136: 157-0441152 | E136: 009-05720157044115215
A137: INGA CARHUAMACA | B137: 933162551
A138: NIETO ASTETE MARITZA ISABEL | B138: 941451427 | F138: HOSPITAL B. LEGUIA
A139: CERPA SILVA ARTURO | B139: 956386291
A140: ROJAS GAVILAN OSCAR EUSEBIO | B140: 959686281 | F140: HOSPITAL MILITAR
A141: MARTINEZ QUIJANDRIA JUAN CARLOS | B141: 961711087 | F141: HOSPITAL SABOGAL
A142: VALDERRAMA LOAYZA MIREYA ELIZABETH | B142: 972250960 | F142: POLICLINICO IZAGUIRRE
A143: VASQUEZ MORENO LUIS ENRIQUE | B143: 975462002 | F143: CLINICA CENTENARIO
A144: CABANILLAS PEREZ ROSAMARIE MILAGROS | B144: 981604885
A145: RONDON SANCHEZ MIGUEL ANGEL | B145: 982769481 | F145: CLÍNICA SAN VICENTE
A146: GOMEZ SANCHEZ MATEO DOMINGO | B146: 985473445 | F146: HOSPITAL 2 DE MAYO
A147: TARAZONA CHAVEZ ROSAMARIA | B147: 994336842
A148: BARRON ARTOLA ZULY JANETH | B148: 995829641
A149: SERPA FRIAS SOLON | B149: 997213990
A150: MALLAUPOMA POVEZ ANGELA | B150: 998862127
A151: CHEA WOO CARLOS GUILLERMO | B151: 999015993 | F151: CONSULTORIO PARTICULAR
...

Sheet Bonos2
A1: Servicios | B1: Precio Bono
A2: ANGIOGRAFIA CON FLUORESCEINA | B2: 100
A3: BIOMETRIA IOL MASTER 700 | B3: 30
A4: CAMPIMETRIA (CAMPO VISUAL) | B4: 30
A5: ECOGRAFIA OCULAR GENERAL SCAN A,B | B5: 30
A6: MICROSCOPIA ESPECULAR | B6: 30
A7: OCT ANGIOGRAFIA NERVIO OPTICO | B7: 50
A8: OCT DE MACULA | B8: 50
A9: OCT DE NERVIO OPTICO Y CELULAS GANGLION | B9: 50
A10: OCT DE SEGMENTO ANTERIOR (ANGULOS) | B10: 50
A11: PAQUIMETRIA | B11: 30
A12: TOPOGRAFIA CORNEAL | B12: 30
A13: FOTOCLINICA EN MOSAICO | B13: 50
... A18: ECOBIOMETRIA OCULAR UNILATERAL O BILATER | B18: 30

Sheet Base_Precisa
A1: FECHA | B1: MES | C1: INVNUM | D1: COMPROBANTE | E1: FACTURA | F1: TIPO PAGO | G1: # DOC | H1: PACIENTE | I1: DNI | J1: MEDICO | K1: INSTITUCIÓN | L1: CARTERA | M1: HISTORIA | N1: TELEFONO | O1: RAZON SOCIAL | P1: PREFACTURA | Q1: DESCRIPCION | R1: CANTIDAD | S1: DESCRIP PLAN | T1: CONTRATANTE | U1: ASEGURADORA | V1: SEDEXX | W1: FACTURADOR | X1: FAC TOTAL | Y1: CENTRO_COSTO | Z1: CONVENIO | AA1: SEDE | AB1: CELULAR | AC1: CUENTA BANCARIA | AD1: Bono
A2: 46174 | B2: Junio | C2: 97734 | D2: BO | E2: 5483 | F2: CO | G2: BO-5483 | H2: MARIN DIAZ JORGE MARCIAL | I2: 06105706 | J2: ORNA ACOSTA JORGE AQUILES | K2: HOSPITAL LOAYZA | L2: CRISTINA | M2: 0069701 | N2: 990056060 | O2: MARIN DIAZ JORGE MARCIAL | P2: 85829 | Q2: OCT DE MACULA | R2: 1 | S2: PRECISA | T2: POR ASIGNAR | U2: INSTITUTO MEDICO QUIRURGICO AREQUIPA S.A | V2: L.CENTRO | W2: ACABRERA | X2: 186.44 | Y2: LN. EXAMENES | Z2: CIAS. DE SEGURO | AA2: CENTRO | AB2: 999996347 | AC2: 052-7510523 | AD2: 50
A3: 46174 | B3: Junio | C3: 97768 | D3: BO | E3: 11380 | F3: CO | G3: BO-11380 | H3: DAVILA URIBE JOSELUIS FRANKLIN | I3: 63710675 | J3: PEÑA CAMARGO CRISTOPHER OMAR | K3: HOSPITAL SERGIO BERNALES | L3: CRISTINA | M3: 0069713 | N3: 916691513 | O3: DAVILA URIBE JOSELUIS FRANKLIN | P3: 85858 | Q3: OCT DE MACULA | R3: 1 | S3: PRECISA | T3: POR ASIGNAR | U3: INSTITUTO MEDICO QUIRURGICO AREQUIPA S.A | V3: L.CENTRO | W3: LMAGAN | X3: 186.44 | Y3: LN. EXAMENES | Z3: CIAS. DE SEGURO | AA3: CENTRO | AB3: 964328569 | AC3: 191-70241223029 | AD3: 50
A4: 46174 | B4: Junio | C4: 97737 | D4: BO | E4: 5485 | F4: CO | G4: BO-5485 | H4: JIMENEZ BORCKARDT MARIA ELENA | I4: 09175695 | J4: TORRES LEAL ADOLFO LEON | K4: CLÍNICA SAN FELIPE LA MOLINA | L4: CRISTINA | M4: 0069704 | N4: 962711137 | O4: JIMENEZ BORCKARDT MARIA ELENA | P4: 85831 | Q4: ECOGRAFIA OCULAR GENERAL SCAN A,B | R4: 1 | S4: PRECISA | T4: POR ASIGNAR | U4: INSTITUTO MEDICO QUIRURGICO AREQUIPA S.A | V4: L.CENTRO | W4: ACABRERA | X4: 135.59 | Y4: LN. EXAMENES | Z4: CIAS. DE SEGURO | AA4: CENTRO | AB4: 999421990 | AD4: 30
A5: 46174 | B5: Junio | C5: 97761 | D5: BO | E5: 11378 | F5: CO | G5: BO-11378 | H5: SANDOVAL SANTAMARIA ANTERO | I5: 17562410 | J5: HUARANGA RUIZ CORNEJO JORGE ERNESTO | K5: HOSPITAL MONGRUT | L5: CRISTINA | M5: 0069712 | N5: 956259223 | O5: SANDOVAL SANTAMARIA ANTERO | P5: 85854 | Q5: ECOGRAFIA OCULAR GENERAL SCAN A,B | R5: 1 | S5: PRECISA | T5: POR ASIGNAR | U5: INSTITUTO MEDICO QUIRURGICO AREQUIPA S.A | V5: L.CENTRO | W5: LMAGAN | X5: 135.59 | Y5: LN. EXAMENES | Z5: CIAS. DE SEGURO | AA5: CENTRO | AB5: 945319366 | AC5: 194-94066798065 | AD5: 30
A6: 46174 | B6: Junio | C6: 97762 | D6: BO | E6: 3764 | F6: CO | G6: BO-3764 | H6: DIAZ DIAZ MARIA JUANA | I6: 48820433 | J6: AGRAMONTE ZEA EDILBERTO | K6: HOSPITAL DE LA SOLIDARIDAD SJL | L6: CRISTINA | M6: 0068509 | N6: 980843789 | O6: DIAZ DIAZ MARIA JUANA | P6: 85855 | Q6: ECOGRAFIA OCULAR GENERAL SCAN A,B | R6: 1 | S6: PRECISA LN | T6: POR ASIGNAR | U6: INSTITUTO MEDICO QUIRURGICO AREQUIPA S.A | V6: L.NORTE | W6: BGALLOSA | X6: 135.59 | Y6: LN. EXAMENES | Z6: CIAS. DE SEGURO | AA6: NORTE | AB6: 987407712 | AC6: 0011-0190-0200333106 | AD6: 30
A7: 46174 | B7: Junio | C7: 97751 | D7: BO | E7: 11374 | F7: CO | G7: BO-11374 | H7: HERRERA GRANDA VANNIA LUZ | I7: 77928579 | J7: PEÑA CAMARGO CRISTOPHER OMAR | K7: HOSPITAL SERGIO BERNALES | L7: CRISTINA | M7: 0067338 | N7: 953421025 | O7: HERRERA GRANDA VANNIA LUZ | P7: 85844 | Q7: OCT DE NERVIO OPTICO Y CELULAS GANGLION | R7: 1 | S7: PRECISA | T7: POR ASIGNAR | U7: INSTITUTO MEDICO QUIRURGICO AREQUIPA S.A | V7: L.CENTRO | W7: LMAGAN | X7: 186.44 | Y7: LN. EXAMENES | Z7: CIAS. DE SEGURO | AA7: CENTRO | AB7: 964328569 | AC7: 191-70241223029 | AD7: 50
A8: 46175 | B8: Junio | C8: 97877 | D8: BO | E8: 5505 | F8: CO | G8: BO-5505 | H8: REATEGUI VALLES REITER | I8: 01092510 | J8: MANSILLA JUAN JOSÉ | K8: CONSULTORIO PARTICULAR | L8: CRISTINA | M8: 0069757 | N8: 931872630 | O8: REATEGUI VALLES REITER | P8: 85945 | Q8: USO DE EQUIPOS E INSUMO AVASTIN | R8: 1 | S8: PRECISA | T8: POR ASIGNAR | U8: INSTITUTO MEDICO QUIRURGICO AREQUIPA S.A | V8: L.CENTRO | W8: ACABRERA | X8: 254.24 | Y8: LN. PROCEDIMIENTO | Z8: CIAS. DE SEGURO | AA8: CENTRO
A9: 46176 | B9: Junio | C9: 97907 | D9: BO | E9: 5506 | F9: CO | G9: BO-5506 | H9: MOTTA MARTINEZ JUSTINA OTILIA | I9: 08795262 | J9: RODRIGUEZ CECILIA | K9: POLICLÍNICO DIVINO NIÑO JESÚS | L9: CRISTINA | M9: 0054360 | N9: 901653281 | O9: MOTTA MARTINEZ JUSTINA OTILIA | P9: 85960 | Q9: CAMPIMETRIA (CAMPO VISUAL) | R9: 1 | S9: PRECISA | T9: POR ASIGNAR | U9: INSTITUTO MEDICO QUIRURGICO AREQUIPA S.A | V9: L.CENTRO | W9: ACABRERA | X9: 135.59 | Y9: LN. EXAMENES | Z9: CIAS. DE SEGURO | AA9: CENTRO | AD9: 30
A10: 46176 | B10: Junio | C10: 97912 | D10: BO | E10: 11395 | F10: CO | G10: BO-11395 | H10: MEDINA SILVESTRE GERONIMO | I10: 06279020 | J10: GUTARRA PAUCAR JULIA KARINA | K10: CLÍNICA SAN CAMILO | L10: CRISTINA | M10: 0069754 | N10: 997332688 | O10: MEDINA SILVESTRE GERONIMO | P10: 85967 | Q10: OCT DE MACULA | R10: 1 | S10: PRECISA | T10: POR ASIGNAR | U10: INSTITUTO MEDICO QUIRURGICO AREQUIPA S.A | V10: L.CENTRO | W10: LMAGAN | X10: 186.44 | Y10: LN. EXAMENES | Z10: CIAS. DE SEGURO | AA10: CENTRO | AB10: 982673362 | AC10: 0011-0353-0200308107 | AD10: 50
A11: 46176 | B11: Junio | C11: 97912 | D11: BO | E11: 11395 | F11: CO | G11: BO-11395 | H11: MEDINA SILVESTRE GERONIMO | I11: 06279020 | J11: GUTARRA PAUCAR JULIA KARINA | K11: CLÍNICA SAN CAMILO | L11: CRISTINA | M11: 0069754 | N11: 997332688 | O11: MEDINA SILVESTRE GERONIMO | P11: 85967 | Q11: OCT DE NERVIO OPTICO Y CELULAS GANGLION | R11: 1 | S11: PRECISA | T11: POR ASIGNAR | U11: INSTITUTO MEDICO QUIRURGICO AREQUIPA S.A | V11: L.CENTRO | W11: LMAGAN | X11: 186.44 | Y11: LN. EXAMENES | Z11: CIAS. DE SEGURO | AA11: CENTRO | AB11: 982673362 | AC11: 0011-0353-0200308107 | AD11: 50
A12: 46176 | B12: Junio | C12: 97956 | D12: BO | E12: 11402 | F12: CO | G12: BO-11402 | H12: GARCIA DE SANCHEZ MATILDE | I12: 27062832 | J12: GUTARRA PAUCAR JULIA KARINA | K12: CLÍNICA SAN CAMILO | L12: CRISTINA | M12: 0069790 | N12: 917095913 | O12: GARCIA DE SANCHEZ MATILDE | P12: 86014 | Q12: OCT DE MACULA | R12: 1 | S12: PRECISA | T12: POR ASIGNAR | U12: INSTITUTO MEDICO QUIRURGICO AREQUIPA S.A | V12: L.CENTRO | W12: LMAGAN | X12: 186.44 | Y12: LN. EXAMENES | Z12: CIAS. DE SEGURO | AA12: CENTRO | AB12: 982673362 | AC12: 0011-0353-0200308107 | AD12: 50
A13: 46176 | B13: Junio | C13: 97956 | D13: BO | E13: 11402 | F13: CO | G13: BO-11402 | H13: GARCIA DE SANCHEZ MATILDE | I13: 27062832 | J13: GUTARRA PAUCAR JULIA KARINA | K13: CLÍNICA SAN CAMILO | L13: CRISTINA | M13: 0069790 | N13: 917095913 | O13: GARCIA DE SANCHEZ MATILDE | P13: 86014 | Q13: OCT DE NERVIO OPTICO Y CELULAS GANGLION | R13: 1 | S13: PRECISA | T13: POR ASIGNAR | U13: INSTITUTO MEDICO QUIRURGICO AREQUIPA S.A | V13: L.CENTRO | W13: LMAGAN | X13: 186.44 | Y13: LN. EXAMENES | Z13: CIAS. DE SEGURO | AA13: CENTRO | AB13: 982673362 | AC13: 0011-0353-0200308107 | AD13: 50
A14: 46176 | B14: Junio | C14: 97979 | D14: BO | E14: 11406 | F14: CO | G14: BO-11406 | H14: PEREZ SANCHEZ GIOVANNA MARIELA | I14: 25792949 | J14: BOBBIO PEREZ MILKO | K14: CONSULTORIO | L14: CRISTINA | M14: 0069797 | N14: 946068386 | O14: PEREZ SANCHEZ GIOVANNA MARIELA | P14: 86027 | Q14: OCT DE MACULA | R14: 1 | S14: PRECISA | T14: POR ASIGNAR | U14: INSTITUTO MEDICO QUIRURGICO AREQUIPA S.A | V14: L.CENTRO | W14: LMAGAN | X14: 186.44 | Y14: LN. EXAMENES | Z14: CIAS. DE SEGURO | AA14: CENTRO | AB14: 981214114 | AC14: 191-98432106068 | AD14: 50
A15: 46176 | B15: Junio | C15: 97979 | D15: BO | E15: 11406 | F15: CO | G15: BO-11406 | H15: PEREZ SANCHEZ GIOVANNA MARIELA | I15: 25792949 | J15: BOBBIO PEREZ MILKO | K15: CONSULTORIO | L15: CRISTINA | M15: 0069797 | N15: 946068386 | O15: PEREZ SANCHEZ GIOVANNA MARIELA | P15: 86027 | Q15: PAQUIMETRIA | R15: 1 | S15: PRECISA | T15: POR ASIGNAR | U15: INSTITUTO MEDICO QUIRURGICO AREQUIPA S.A | V15: L.CENTRO | W15: LMAGAN | X15: 152.54 | Y15: LN. EXAMENES | Z15: CIAS. DE SEGURO | AA15: CENTRO | AB15: 981214114 | AC15: 191-98432106068 | AD15: 30
A16: 46177 | B16: Junio | C16: 98036 | D16: BO | E16: 5516 | F16: CO | G16: BO-5516 | H16: PICO DE CRUZADO LUZ EMILIA | I16: 16550311 | J16: AGRAMONTE ZEA EDILBERTO | K16: HOSPITAL DE LA SOLIDARIDAD SJL | L16: CRISTINA | M16: 0069819 | N16: 985411444 | O16: PICO DE CRUZADO LUZ EMILIA | P16: 86087 | Q16: OCT DE MACULA | R16: 1 | S16: PRECISA | T16: POR ASIGNAR | U16: INSTITUTO MEDICO QUIRURGICO AREQUIPA S.A | V16: L.CENTRO | W16: ACABRERA | X16: 186.44 | Y16: LN. EXAMENES | Z16: CIAS. DE SEGURO | AA16: CENTRO | AB16: 987407712 | AC16: 0011-0190-0200333106 | AD16: 50
A17: 46177 | B17: Junio | C17: 98044 | D17: BO | E17: 11419 | F17: CO | G17: BO-11419 | H17: SACHA NAVARRO GERARDO JUNIOR | I17: 47180662 | J17: CACERES PINTO ALVARO DANIEL | K17: HOSPITAL INO | L17: CRISTINA | M17: 0069825 | N17: 958365826 | O17: SACHA NAVARRO GERARDO JUNIOR | P17: 86096 | Q17: FOTOCLINICA EN MOSAICO | R17: 1 | S17: PRECISA | T17: POR ASIGNAR | U17: INSTITUTO MEDICO QUIRURGICO AREQUIPA S.A | V17: L.CENTRO | W17: LMAGAN | X17: 169.49 | Y17: LN. EXAMENES | Z17: CIAS. DE SEGURO | AA17: CENTRO | AB17: 966697811 | AC17: 0011-0184-0200649518 | AD17: 50
A18: 46177 | B18: Junio | C18: 98044 | D18: BO | E18: 11419 | F18: CO | G18: BO-11419 | H18: SACHA NAVARRO GERARDO JUNIOR | I18: 47180662 | J18: CACERES PINTO ALVARO DANIEL | K18: HOSPITAL INO | L18: CRISTINA | M18: 0069825 | N18: 958365826 | O18: SACHA NAVARRO GERARDO JUNIOR | P18: 86096 | Q18: OCT DE MACULA | R18: 1 | S18: PRECISA | T18: POR ASIGNAR | U18: INSTITUTO MEDICO QUIRURGICO AREQUIPA S.A | V18: L.CENTRO | W18: LMAGAN | X18: 186.44 | Y18: LN. EXAMENES | Z18: CIAS. DE SEGURO | AA18: CENTRO | AB18: 966697811 | AC18: 0011-0184-0200649518 | AD18: 50
A19: 46177 | B19: Junio | C19: 98044 | D19: BO | E19: 11419 | F19: CO | G19: BO-11419 | H19: SACHA NAVARRO GERARDO JUNIOR | I19: 47180662 | J19: CACERES PINTO ALVARO DANIEL | K19: HOSPITAL INO | L19: CRISTINA | M19: 0069825 | N19: 958365826 | O19: SACHA NAVARRO GERARDO JUNIOR | P19: 86096 | Q19: OCT DE NERVIO OPTICO Y CELULAS GANGLION | R19: 1 | S19: PRECISA | T19: POR ASIGNAR | U19: INSTITUTO MEDICO QUIRURGICO AREQUIPA S.A | V19: L.CENTRO | W19: LMAGAN | X19: 186.44 | Y19: LN. EXAMENES | Z19: CIAS. DE SEGURO | AA19: CENTRO | AB19: 966697811 | AC19: 0011-0184-0200649518 | AD19: 50
A20: 46177 | B20: Junio | C20: 98041 | D20: FA | E20: 1025 | F20: CO | G20: FA-1025 | H20: NUÑEZ ALTIS ANTONIO SALOMON | I20: 09498424 | J20: VILLAR CURAHUA MARCELA ALEJANDRA | K20: GAMARRA SALUD | L20: CRISTINA | M20: 0069549 | N20: 928076253 | O20: GAMARRA HEALTHCARE CENTER S.A.C. | P20: 86093 | Q20: BIOMETRIA IOL MASTER 700 | R20: 1 | S20: PRECISA | T20: POR ASIGNAR | U20: INSTITUTO MEDICO QUIRURGICO AREQUIPA S.A | V20: L.CENTRO | W20: LMAGAN | X20: 152.54 | Y20: LN. EXAMENES | Z20: CIAS. DE SEGURO | AA20: CENTRO | AB20: 950133748 | AC20: 191-9953047026 | AD20: 30
A21: 46177 | B21: Junio | C21: 98041 | D21: FA | E21: 1025 | F21: CO | G21: FA-1025 | H21: NUÑEZ ALTIS ANTONIO SALOMON | I21: 09498424 | J21: VILLAR CURAHUA MARCELA ALEJANDRA | K21: GAMARRA SALUD | L21: CRISTINA | M21: 0069549 | N21: 928076253 | O21: GAMARRA HEALTHCARE CENTER S.A.C. | P21: 86093 | Q21: MICROSCOPIA ESPECULAR | R21: 1 | S21: PRECISA | T21: POR ASIGNAR | U21: INSTITUTO MEDICO QUIRURGICO AREQUIPA S.A | V21: L.CENTRO | W21: LMAGAN | X21: 135.59 | Y21: LN. EXAMENES | Z21: CIAS. DE SEGURO | AA21: CENTRO | AB21: 950133748 | AC21: 191-9953047026 | AD21: 30
A22: 46177 | B22: Junio | C22: 98051 | D22: FA | E22: 524 | F22: CO | G22: FA-524 | H22: GARCIA RICO ELVA JOSEFINA | I22: 16408791 | J22: VILLAR CURAHUA MARCELA ALEJANDRA | K22: GAMARRA SALUD | L22: CRISTINA | M22: 0067849 | N22: 902449032 | O22: GAMARRA HEALTHCARE CENTER S.A.C. | P22: 85864 | Q22: CIRUGIA DE DIA | R22: 1 | S22: PRECISA | T22: POR ASIGNAR | U22: INSTITUTO MEDICO QUIRURGICO AREQUIPA S.A | V22: L.CENTRO | W22: ACABRERA | X22: 0 | Y22: LN. CIRUGIA | Z22: CIAS. DE SEGURO | AA22: CENTRO | AB22: 950133748 | AC22: 191-9953047026
A23: 46177 | B23: Junio | C23: 98051 | D23: FA | E23: 524 | F23: CO | G23: FA-524 | H23: GARCIA RICO ELVA JOSEFINA | I23: 16408791 | J23: VILLAR CURAHUA MARCELA ALEJANDRA | K23: GAMARRA SALUD | L23: CRISTINA | M23: 0067849 | N23: 902449032 | O23: GAMARRA HEALTHCARE CENTER S.A.C. | P23: 85864 | Q23: FACOEMULSIFICACION PRIMIUM | R23: 1 | S23: PRECISA | T23: POR ASIGNAR | U23: INSTITUTO MEDICO QUIRURGICO AREQUIPA S.A | V23: L.CENTRO | W23: ACABRERA | X23: 1050.85 | Y23: LN. CIRUGIA | Z23: CIAS. DE SEGURO | AA23: CENTRO | AB23: 950133748 | AC23: 191-9953047026
A24: 46177 | B24: Junio | C24: 98052 | D24: FA | E24: 525 | F24: CO | G24: FA-525 | H24: NUÑEZ ALTIS ANTONIO SALOMON | I24: 09498424 | J24: VILLAR CURAHUA MARCELA ALEJANDRA | K24: GAMARRA SALUD | L24: CRISTINA | M24: 0069549 | N24: 928076253 | O24: GAMARRA HEALTHCARE CENTER S.A.C. | P24: 85863 | Q24: CIRUGIA DE DIA | R24: 1 | S24: PRECISA | T24: POR ASIGNAR | U24: INSTITUTO MEDICO QUIRURGICO AREQUIPA S.A | V24: L.CENTRO | W24: ACABRERA | X24: 0 | Y24: LN. CIRUGIA | Z24: CIAS. DE SEGURO | AA24: CENTRO | AB24: 950133748 | AC24: 191-9953047026
A25: 46177 | B25: Junio | C25: 98052 | D25: FA | E25: 525 | F25: CO | G25: FA-525 | H25: NUÑEZ ALTIS ANTONIO SALOMON | I25: 09498424 | J25: VILLAR CURAHUA MARCELA ALEJANDRA | K25: GAMARRA SALUD | L25: CRISTINA | M25: 0069549 | N25: 928076253 | O25: GAMARRA HEALTHCARE CENTER S.A.C. | P25: 85863 | Q25: FACOEMULSIFICACION PRIMIUM | R25: 1 | S25: PRECISA | T25: POR ASIGNAR | U25: INSTITUTO MEDICO QUIRURGICO AREQUIPA S.A | V25: L.CENTRO | W25: ACABRERA | X25: 1050.85 | Y25: LN. CIRUGIA | Z25: CIAS. DE SEGURO | AA25: CENTRO | AB25: 950133748 | AC25: 191-9953047026
A26: 46177 | B26: Junio | C26: 98035 | D26: BO | E26: 4221 | F26: CO | G26: BO-4221 | H26: PEÑA GARCIA BENIGNO OSCAR | I26: 48945300 | J26: RUIZ ROJAS PAUBLO ENRIQUE | K26: CONSULTORIO CUBANO COMAS | L26: CRISTINA | M26: 0069818 | N26: 922009271 | O26: PEÑA GARCIA BENIGNO OSCAR | P26: 86086 | Q26: OCT DE MACULA | R26: 1 | S26: PRECISA LN | T26: POR ASIGNAR | U26: INSTITUTO MEDICO QUIRURGICO AREQUIPA S.A | V26: L.NORTE | W26: AALARCON | X26: 186.44 | Y26: LN. EXAMENES | Z26: CIAS. DE SEGURO | AA26: NORTE | AB26: 992903716 | AC26: 191-91415089071 | AD26: 50
A27: 46177 | B27: Junio | C27: 98035 | D27: BO | E27: 4221 | F27: CO | G27: BO-4221 | H27: PEÑA GARCIA BENIGNO OSCAR | I27: 48945300 | J27: RUIZ ROJAS PAUBLO ENRIQUE | K27: CONSULTORIO CUBANO COMAS | L27: CRISTINA | M27: 0069818 | N27: 922009271 | O27: PEÑA GARCIA BENIGNO OSCAR | P27: 86086 | Q27: OCT DE NERVIO OPTICO Y CELULAS GANGLION | R27: 1 | S27: PRECISA LN | T27: POR ASIGNAR | U27: INSTITUTO MEDICO QUIRURGICO AREQUIPA S.A | V27: L.NORTE | W27: AALARCON | X27: 186.44 | Y27: LN. EXAMENES | Z27: CIAS. DE SEGURO | AA27: NORTE | AB27: 992903716 | AC27: 191-91415089071 | AD27: 50
A28: 46178 | B28: Junio | C28: 98106 | D28: BO | E28: 5526 | F28: CO | G28: BO-5526 | H28: VALERA BAZAN LAURA PIERI | I28: 08013693 | J28: CASTRO TAMANAJA VANIA VIVIAN | K28: HOSPITAL 2 DE MAYO | L28: CRISTINA | M28: 0056253 | N28: 4715484 | O28: VALERA BAZAN LAURA PIERI | P28: 86151 | Q28: OCT DE NERVIO OPTICO Y CELULAS GANGLION | R28: 1 | S28: PRECISA | T28: POR ASIGNAR | U28: INSTITUTO MEDICO QUIRURGICO AREQUIPA S.A | V28: L.CENTRO | W28: ACABRERA | X28: 186.44 | Y28: LN. EXAMENES | Z28: CIAS. DE SEGURO | AA28: CENTRO | AB28: 986661693 | AC28: 0011-0354-0200096288 | AD28: 50
A29: 46178 | B29: Junio | C29: 2353 | D29: NC | E29: 5527 | F29: CR | G29: NC-5527 | H29: BRAVO QUISPE VDA DE ANDIA ANGELICA RITA | I29: 07412423 | J29: FERNANDEZ GUTIERREZ OLGA PATRICIA | K29: CONSULTORIO PARTICULAR | L29: CR | M29: 0069850 | N29: 979750580 | O29: BRAVO QUISPE VDA DE ANDIA ANGELICA RITA | P29: 86154 | Q29: USO DE EQUIPOS E INSUMO IRIDOTOMIA | R29: 2 | S29: PRECISA | T29: POR ASIGNAR | U29: INSTITUTO MEDICO QUIRURGICO AREQUIPA S.A | V29: L.CENTRO | W29: ACABRERA | X29: -203.39 | Y29: LN. PROCEDIMIENTO | Z29: CIAS. DE SEGURO | AA29: CENTRO | AB29: 982536223 | AC29: 107-3174605363
A30: 46178 | B30: Junio | C30: 98110 | D30: FA | E30: 527 | F30: CO | G30: FA-527 | H30: BRAVO QUISPE VDA DE ANDIA ANGELICA RITA | I30: 07412423 | J30: FERNANDEZ GUTIERREZ OLGA PATRICIA | K30: CONSULTORIO PARTICULAR | L30: CRISTINA | M30: 0069850 | N30: 979750580 | O30: VEFER OFTALMOLOGOS S.A.C. | P30: 86155 | Q30: USO DE EQUIPOS E INSUMO IRIDOTOMIA | R30: 2 | S30: PRECISA | T30: POR ASIGNAR | U30: INSTITUTO MEDICO QUIRURGICO AREQUIPA S.A | V30: L.CENTRO | W30: ACABRERA | X30: 203.39 | Y30: LN. PROCEDIMIENTO | Z30: CIAS. DE SEGURO | AA30: CENTRO | AB30: 982536223 | AC30: 107-3174605363
A31: 46178 | B31: Junio | C31: 2353 | D31: BO | E31: 5527 | F31: CR | G31: BO-5527 | H31: BRAVO QUISPE VDA DE ANDIA ANGELICA RITA | I31: 07412423 | J31: FERNANDEZ GUTIERREZ OLGA PATRICIA | K31: CONSULTORIO PARTICULAR | L31: CR | M31: 0069850 | N31: 979750580 | O31: BRAVO QUISPE VDA DE ANDIA ANGELICA RITA | P31: 86154 | Q31: USO DE EQUIPOS E INSUMO IRIDOTOMIA | R31: 2 | S31: PRECISA | T31: POR ASIGNAR | U31: INSTITUTO MEDICO QUIRURGICO AREQUIPA S.A | V31: L.CENTRO | W31: ACABRERA | X31: 203.39 | Y31: LN. PROCEDIMIENTO | Z31: CIAS. DE SEGURO | AA31: CENTRO | AB31: 982536223 | AC31: 107-3174605363
A32: 46178 | B32: Junio | C32: 98108 | D32: FA | E32: 526 | F32: CO | G32: FA-526 | H32: ABAD OVALLE ARLINE MERCEDES | I32: 25532349 | L32: CRISTINA | M32: 0069694 | N32: 999999452 | O32: VEFER OFTALMOLOGOS S.A.C. | P32: 86152 | Q32: USO DE EQUIPOS E INSUMO IRIDOTOMIA | R32: 2 | S32: PRECISA | T32: POR ASIGNAR | U32: INSTITUTO MEDICO QUIRURGICO AREQUIPA S.A | V32: L.CENTRO | W32: ACABRERA | X32: 203.39 | Y32: LN. PROCEDIMIENTO | Z32: CIAS. DE SEGURO | AA32: CENTRO
A33: 46179 | B33: Junio | C33: 98152 | D33: BO | E33: 4244 | F33: CO | G33: BO-4244 | H33: OLIVO CASTRO JULIA GLADYS | I33: 15292242 | J33: RUIZ ROJAS PAUBLO ENRIQUE | K33: CONSULTORIO CUBANO COMAS | L33: CRISTINA | M33: 0069884 | N33: 952190646 | O33: OLIVO CASTRO JULIA GLADYS | P33: 86190 | Q33: OCT DE MACULA | R33: 1 | S33: PRECISA LN | T33: POR ASIGNAR | U33: INSTITUTO MEDICO QUIRURGICO AREQUIPA S.A | V33: L.NORTE | W33: AALARCON | X33: 186.44 | Y33: LN. EXAMENES | Z33: CIAS. DE SEGURO | AA33: NORTE | AB33: 992903716 | AC33: 191-91415089071 | AD33: 50
A34: 46179 | B34: Junio | C34: 98151 | D34: BO | E34: 11423 | F34: CO | G34: BO-11423 | H34: PACACHA FLORES BLANCA VALESKA | I34: 91733805 | J34: CRISPIN MORALES NANCY JENNY | K34: HOSPITAL ALMENARA | L34: CRISTINA | M34: 0069883 | N34: 970593962 | O34: PACACHA FLORES BLANCA VALESKA | P34: 86188 | Q34: TOPOGRAFIA CORNEAL | R34: 1 | S34: PRECISA | T34: POR ASIGNAR | U34: INSTITUTO MEDICO QUIRURGICO AREQUIPA S.A | V34: L.CENTRO | W34: LMAGAN | X34: 152.54 | Y34: LN. EXAMENES | Z34: CIAS. DE SEGURO | AA34: CENTRO | AB34: 978789268 | AC34: 193-90416675072 | AD34: 30
A35: 46179 | B35: Junio | C35: 98176 | D35: BO | E35: 11428 | F35: CO | G35: BO-11428 | H35: REYES SANCHEZ OLGA EULALIA | I35: 09330262 | J35: LLERENA MORALES OSCAR ADOLFO | K35: SANNA SAN MIGUEL | L35: CRISTINA | M35: 0069894 | N35: 947513770 | O35: REYES SANCHEZ OLGA EULALIA | P35: 86218 | Q35: CAMPIMETRIA (CAMPO VISUAL) | R35: 1 | S35: PRECISA | T35: POR ASIGNAR | U35: INSTITUTO MEDICO QUIRURGICO AREQUIPA S.A | V35: L.CENTRO | W35: LMAGAN | X35: 135.59 | Y35: LN. EXAMENES | Z35: CIAS. DE SEGURO | AA35: CENTRO | AB35: 987552890 | AC35: 098-7304409 | AD35: 30
A36: 46179 | B36: Junio | C36: 98176 | D36: BO | E36: 11428 | F36: CO | G36: BO-11428 | H36: REYES SANCHEZ OLGA EULALIA | I36: 09330262 | J36: LLERENA MORALES OSCAR ADOLFO | K36: SANNA SAN MIGUEL | L36: CRISTINA | M36: 0069894 | N36: 947513770 | O36: REYES SANCHEZ OLGA EULALIA | P36: 86218 | Q36: PAQUIMETRIA | R36: 1 | S36: PRECISA | T36: POR ASIGNAR | U36: INSTITUTO MEDICO QUIRURGICO AREQUIPA S.A | V36: L.CENTRO | W36: LMAGAN | X36: 152.54 | Y36: LN. EXAMENES | Z36: CIAS. DE SEGURO | AA36: CENTRO | AB36: 987552890 | AC36: 098-7304409 | AD36: 30
A37: 46179 | B37: Junio | C37: 98176 | D37: BO | E37: 11428 | F37: CO | G37: BO-11428 | H37: REYES SANCHEZ OLGA EULALIA | I37: 09330262 | J37: LLERENA MORALES OSCAR ADOLFO | K37: SANNA SAN MIGUEL | L37: CRISTINA | M37: 0069894 | N37: 947513770 | O37: REYES SANCHEZ OLGA EULALIA | P37: 86218 | Q37: OCT DE NERVIO OPTICO Y CELULAS GANGLION | R37: 1 | S37: PRECISA | T37: POR ASIGNAR | U37: INSTITUTO MEDICO QUIRURGICO AREQUIPA S.A | V37: L.CENTRO | W37: LMAGAN | X37: 186.44 | Y37: LN. EXAMENES | Z37: CIAS. DE SEGURO | AA37: CENTRO | AB37: 987552890 | AC37: 098-7304409 | AD37: 50
A38: 46179 | B38: Junio | C38: 98167 | D38: BO | E38: 4250 | F38: CO | G38: BO-4250 | H38: RONCAL ROMERO FANNYNG EDITH | I38: 44905743 | J38: ROJAS AQUINO EVELING KARINA | K38: POLICLÍNICO ESPÍRITU SANTO | L38: CRISTINA | M38: 0069844 | N38: 984441413 | O38: RONCAL ROMERO FANNYNG EDITH | P38: 86210 | Q38: OCT DE NERVIO OPTICO Y CELULAS GANGLION | R38: 1 | S38: PRECISA LN | T38: POR ASIGNAR | U38: INSTITUTO MEDICO QUIRURGICO AREQUIPA S.A | V38: L.NORTE | W38: AALARCON | X38: 186.44 | Y38: LN. EXAMENES | Z38: CIAS. DE SEGURO | AA38: NORTE | AB38: 955356636 | AC38: 009-3226956615 | AD38: 50
A39: 46182 | B39: Junio | C39: 98452 | D39: FA | E39: 532 | F39: CO | G39: FA-532 | H39: BENITES RAMOS ANTENOR HERMAN | I39: 07187063 | J39: VILLAR CURAHUA MARCELA ALEJANDRA | K39: GAMARRA SALUD | L39: CRISTINA | M39: 0069415 | N39: 943410784 | O39: GAMARRA HEALTHCARE CENTER S.A.C. | P39: 86345 | Q39: CIRUGIA DE DIA | R39: 1 | S39: PRECISA | T39: POR ASIGNAR | U39: INSTITUTO MEDICO QUIRURGICO AREQUIPA S.A | V39: L.CENTRO | W39: ACABRERA | X39: 0 | Y39: LN. CIRUGIA | Z39: CIAS. DE SEGURO | AA39: CENTRO | AB39: 950133748 | AC39: 191-9953047026
A40: 46182 | B40: Junio | C40: 98452 | D40: FA | E40: 532 | F40: CO | G40: FA-532 | H40: BENITES RAMOS ANTENOR HERMAN | I40: 07187063 | J40: VILLAR CURAHUA MARCELA ALEJANDRA | K40: GAMARRA SALUD | L40: CRISTINA | M40: 0069415 | N40: 943410784 | O40: GAMARRA HEALTHCARE CENTER S.A.C. | P40: 86345 | Q40: FACOEMULSIFICACION PRIMIUM | R40: 1 | S40: PRECISA | T40: POR ASIGNAR | U40: INSTITUTO MEDICO QUIRURGICO AREQUIPA S.A | V40: L.CENTRO | W40: ACABRERA | X40: 1050.85 | Y40: LN. CIRUGIA | Z40: CIAS. DE SEGURO | AA40: CENTRO | AB40: 950133748 | AC40: 191-9953047026
A41: 46182 | B41: Junio | C41: 98463 | D41: FA | E41: 533 | F41: CO | G41: FA-533 | H41: MAMANI SONCCO JUAN GREGORIO | I41: 07314057 | J41: VILLAR CURAHUA MARCELA ALEJANDRA | K41: GAMARRA SALUD | L41: CRISTINA | M41: 0069158 | N41: 987411587 | O41: GAMARRA HEALTHCARE CENTER S.A.C. | P41: 86342 | Q41: CIRUGIA DE DIA | R41: 1 | S41: PRECISA | T41: POR ASIGNAR | U41: INSTITUTO MEDICO QUIRURGICO AREQUIPA S.A | V41: L.CENTRO | W41: ACABRERA | X41: 0 | Y41: LN. CIRUGIA | Z41: CIAS. DE SEGURO | AA41: CENTRO | AB41: 950133748 | AC41: 191-9953047026
A42: 46182 | B42: Junio | C42: 98463 | D42: FA | E42: 533 | F42: CO | G42: FA-533 | H42: MAMANI SONCCO JUAN GREGORIO | I42: 07314057 | J42: VILLAR CURAHUA MARCELA ALEJANDRA | K42: GAMARRA SALUD | L42: CRISTINA | M42: 0069158 | N42: 987411587 | O42: GAMARRA HEALTHCARE CENTER S.A.C. | P42: 86342 | Q42: FACOEMULSIFICACION PRIMIUM | R42: 1 | S42: PRECISA | T42: POR ASIGNAR | U42: INSTITUTO MEDICO QUIRURGICO AREQUIPA S.A | V42: L.CENTRO | W42: ACABRERA | X42: 1050.85 | Y42: LN. CIRUGIA | Z42: CIAS. DE SEGURO | AA42: CENTRO | AB42: 950133748 | AC42: 191-9953047026
A43: 46182 | B43: Junio | C43: 98440 | D43: FA | E43: 1028 | F43: CO | G43: FA-1028 | H43: MATEO EYZAGUIRRE MARCO IVART | I43: 74312316 | J43: ACOSTA VIERA ALVARO | K43: CONSULTORIO PARTICULAR | L43: CRISTINA | M43: 0069588 | N43: 921508096 | O43: CENTRO CONTRA LA CEGUERA E.I.R.L. | P43: 86415 | Q43: USO DE EQUIPOS E INSUMO BLEFAROPLASTIA | R43: 1 | S43: PRECISA | T43: POR ASIGNAR | U43: INSTITUTO MEDICO QUIRURGICO AREQUIPA S.A | V43: L.CENTRO | W43: LMAGAN | X43: 169.49 | Y43: LN. PROCEDIMIENTO | Z43: CIAS. DE SEGURO | AA43: CENTRO | AB43: 969791876 | AC43: 0011-0814-0256063048
A44: 46182 | B44: Junio | C44: 98393 | D44: BO | E44: 5552 | F44: CO | G44: BO-5552 | H44: LAZARO CACHA JUAN CRISOSTOMO | I44: 31633639 | J44: FIERRO LEANDRO | K44: POLICLÍNICO DIVINO NIÑO JESÚS | L44: CRISTINA | M44: 0069870 | N44: 928408508 | O44: LAZARO CACHA JUAN CRISOSTOMO | P44: 86371 | Q44: PQ BIOMETRIA MICROSCOPIA | R44: 1 | S44: PRECISA | T44: POR ASIGNAR | U44: INSTITUTO MEDICO QUIRURGICO AREQUIPA S.A | V44: L.CENTRO | W44: ACABRERA | X44: 84.75 | Y44: LN. EXAMENES | Z44: CIAS. DE SEGURO | AA44: CENTRO
A45: 46182 | B45: Junio | C45: 98395 | D45: BO | E45: 11467 | F45: CO | G45: BO-11467 | H45: MENDOZA REYES BRIGIDA | I45: 08831402 | J45: FIERRO LEANDRO | K45: POLICLÍNICO DIVINO NIÑO JESÚS | L45: CRISTINA | M45: 0069872 | N45: 941194643 | O45: MENDOZA REYES BRIGIDA | P45: 86373 | Q45: PQ BIOMETRIA MICROSCOPIA | R45: 1 | S45: PRECISA | T45: POR ASIGNAR | U45: INSTITUTO MEDICO QUIRURGICO AREQUIPA S.A | V45: L.CENTRO | W45: LMAGAN | X45: 84.75 | Y45: LN. EXAMENES | Z45: CIAS. DE SEGURO | AA45: CENTRO
A46: 46182 | B46: Junio | C46: 98399 | D46: BO | E46: 5555 | F46: CO | G46: BO-5555 | H46: TINOCO OBREGON LUIS ALBERTO | I46: 15859654 | J46: FIERRO LEANDRO | K46: POLICLÍNICO DIVINO NIÑO JESÚS | L46: CRISTINA | M46: 0069871 | N46: 997639449 | O46: TINOCO OBREGON LUIS ALBERTO | P46: 86378 | Q46: PQ BIOMETRIA MICROSCOPIA | R46: 1 | S46: PRECISA | T46: POR ASIGNAR | U46: INSTITUTO MEDICO QUIRURGICO AREQUIPA S.A | V46: L.CENTRO | W46: ACABRERA | X46: 84.75 | Y46: LN. EXAMENES | Z46: CIAS. DE SEGURO | AA46: CENTRO
A47: 46182 | B47: Junio | C47: 98449 | D47: FA | E47: 530 | F47: CO | G47: FA-530 | H47: LAZARO CACHA JUAN CRISOSTOMO | I47: 31633639 | J47: FIERRO LEANDRO | K47: POLICLÍNICO DIVINO NIÑO JESÚS | L47: CRISTINA | M47: 0069870 | N47: 928408508 | O47: GRUPO MEDICO INTEGRAL SOCIEDAD ANONIMA CERRADA | P47: 86384 | Q47: CIRUGIA DE DIA | R47: 1 | S47: PRECISA | T47: POR ASIGNAR | U47: INSTITUTO MEDICO QUIRURGICO AREQUIPA S.A | V47: L.CENTRO | W47: ACABRERA | X47: 0 | Y47: LN. CIRUGIA | Z47: CIAS. DE SEGURO | AA47: CENTRO
A48: 46182 | B48: Junio | C48: 98449 | D48: FA | E48: 530 | F48: CO | G48: FA-530 | H48: LAZARO CACHA JUAN CRISOSTOMO | I48: 31633639 | J48: FIERRO LEANDRO | K48: POLICLÍNICO DIVINO NIÑO JESÚS | L48: CRISTINA | M48: 0069870 | N48: 928408508 | O48: GRUPO MEDICO INTEGRAL SOCIEDAD ANONIMA CERRADA | P48: 86384 | Q48: FACOEMULSIFICACION PRIMIUM | R48: 1 | S48: PRECISA | T48: POR ASIGNAR | U48: INSTITUTO MEDICO QUIRURGICO AREQUIPA S.A | V48: L.CENTRO | W48: ACABRERA | X48: 1525.42 | Y48: LN. CIRUGIA | Z48: CIAS. DE SEGURO | AA48: CENTRO
A49: 46182 | B49: Junio | C49: 98450 | D49: FA | E49: 531 | F49: CO | G49: FA-531 | H49: TINOCO OBREGON LUIS ALBERTO | I49: 15859654 | J49: FIERRO LEANDRO | K49: POLICLÍNICO DIVINO NIÑO JESÚS | L49: CRISTINA | M49: 0069871 | N49: 997639449 | O49: GRUPO MEDICO INTEGRAL SOCIEDAD ANONIMA CERRADA | P49: 86385 | Q49: CIRUGIA DE DIA | R49: 1 | S49: PRECISA | T49: POR ASIGNAR | U49: INSTITUTO MEDICO QUIRURGICO AREQUIPA S.A | V49: L.CENTRO | W49: ACABRERA | X49: 0 | Y49: LN. CIRUGIA | Z49: CIAS. DE SEGURO | AA49: CENTRO
A50: 46182 | B50: Junio | C50: 98450 | D50: FA | E50: 531 | F50: CO | G50: FA-531 | H50: TINOCO OBREGON LUIS ALBERTO | I50: 15859654 | J50: FIERRO LEANDRO | K50: POLICLÍNICO DIVINO NIÑO JESÚS | L50: CRISTINA | M50: 0069871 | N50: 997639449 | O50: GRUPO MEDICO INTEGRAL SOCIEDAD ANONIMA CERRADA | P50: 86385 | Q50: FACOEMULSIFICACION PRIMIUM | R50: 1 | S50: PRECISA | T50: POR ASIGNAR | U50: INSTITUTO MEDICO QUIRURGICO AREQUIPA S.A | V50: L.CENTRO | W50: ACABRERA | X50: 1525.42 | Y50: LN. CIRUGIA | Z50: CIAS. DE SEGURO | AA50: CENTRO
A51: 46182 | B51: Junio | C51: 98476 | D51: FA | E51: 1029 | F51: CO | G51: FA-1029 | H51: MENDOZA REYES BRIGIDA | I51: 08831402 | J51: FIERRO LEANDRO | K51: POLICLÍNICO DIVINO NIÑO JESÚS | L51: CRISTINA | M51: 0069872 | N51: 941194643 | O51: GRUPO MEDICO INTEGRAL SOCIEDAD ANONIMA CERRADA | P51: 86375 | Q51: CIRUGIA DE DIA | R51: 1 | S51: PRECISA | T51: POR ASIGNAR | U51: INSTITUTO MEDICO QUIRURGICO AREQUIPA S.A | V51: L.CENTRO | W51: LMAGAN | X51: 0 | Y51: LN. CIRUGIA | Z51: CIAS. DE SEGURO | AA51: CENTRO
A52: 46182 | B52: Junio | C52: 98476 | D52: FA | E52: 1029 | F52: CO | G52: FA-1029 | H52: MENDOZA REYES BRIGIDA | I52: 08831402 | J52: FIERRO LEANDRO | K52: POLICLÍNICO DIVINO NIÑO JESÚS | L52: CRISTINA | M52: 0069872 | N52: 941194643 | O52: GRUPO MEDICO INTEGRAL SOCIEDAD ANONIMA CERRADA | P52: 86375 | Q52: FACOEMULSIFICACION PRIMIUM | R52: 1 | S52: PRECISA | T52: POR ASIGNAR | U52: INSTITUTO MEDICO QUIRURGICO AREQUIPA S.A | V52: L.CENTRO | W52: LMAGAN | X52: 762.71 | Y52: LN. CIRUGIA | Z52: CIAS. DE SEGURO | AA52: CENTRO
A53: 46183 | B53: Junio | C53: 98511 | D53: BO | E53: 3829 | F53: CO | G53: BO-3829 | H53: VILLA GALVEZ MARIA ESPERANZA | I53: 08462757 | J53: ROJAS AQUINO EVELING KARINA | K53: POLICLÍNICO ESPÍRITU SANTO | L53: CRISTINA | M53: 0070015 | N53: 955008730 | O53: VILLA GALVEZ MARIA ESPERANZA | P53: 86473 | Q53: ECOGRAFIA OCULAR GENERAL SCAN A,B | R53: 1 | S53: PRECISA LN | T53: POR ASIGNAR | U53: INSTITUTO MEDICO QUIRURGICO AREQUIPA S.A | V53: L.NORTE | W53: BGALLOSA | X53: 135.59 | Y53: LN. EXAMENES | Z53: CIAS. DE SEGURO | AA53: NORTE | AB53: 955356636 | AC53: 009-3226956615 | AD53: 30
A54: 46184 | B54: Junio | C54: 98570 | D54: BO | E54: 5573 | F54: CO | G54: BO-5573 | H54: GAMARRA CHAVARRIA JUAN PASCUAL | I54: 15447914 | J54: FIERRO LEANDRO | K54: POLICLÍNICO DIVINO NIÑO JESÚS | L54: CRISTINA | M54: 0070007 | N54: 986955058 | O54: GAMARRA CHAVARRIA JUAN PASCUAL | P54: 86517 | Q54: PQ BIOMETRIA MICROSCOPIA | R54: 1 | S54: PRECISA | T54: POR ASIGNAR | U54: INSTITUTO MEDICO QUIRURGICO AREQUIPA S.A | V54: L.CENTRO | W54: ACABRERA | X54: 84.75 | Y54: LN. EXAMENES | Z54: CIAS. DE SEGURO | AA54: CENTRO
A55: 46184 | B55: Junio | C55: 98571 | D55: BO | E55: 11481 | F55: CO | G55: BO-11481 | H55: PASCO RAMOS DE HERRERA GLORIA ELISA | I55: 07017191 | J55: FIERRO LEANDRO | K55: POLICLÍNICO DIVINO NIÑO JESÚS | L55: CRISTINA | M55: 0070001 | N55: 997369213 | O55: PASCO RAMOS DE HERRERA GLORIA ELISA | P55: 86520 | Q55: PQ BIOMETRIA MICROSCOPIA | R55: 1 | S55: PRECISA | T55: POR ASIGNAR | U55: INSTITUTO MEDICO QUIRURGICO AREQUIPA S.A | V55: L.CENTRO | W55: LMAGAN | X55: 84.75 | Y55: LN. EXAMENES | Z55: CIAS. DE SEGURO | AA55: CENTRO
A56: 46184 | B56: Junio | C56: 98572 | D56: BO | E56: 11482 | F56: CO | G56: BO-11482 | H56: PASCO RAMOS DE HERRERA GLORIA ELISA | I56: 07017191 | J56: FIERRO LEANDRO | K56: POLICLÍNICO DIVINO NIÑO JESÚS | L56: CRISTINA | M56: 0070001 | N56: 997369213 | O56: PASCO RAMOS DE HERRERA GLORIA ELISA | P56: 86519 | Q56: ELECTROCARDIOGRAMA-EKG | R56: 1 | S56: PRECISA | T56: POR ASIGNAR | U56: INSTITUTO MEDICO QUIRURGICO AREQUIPA S.A | V56: L.CENTRO | W56: LMAGAN | X56: 127.12 | Y56: LN. EXAMENES | Z56: CIAS. DE SEGURO | AA56: CENTRO
A57: 46184 | B57: Junio | C57: 98573 | D57: BO | E57: 11483 | F57: CO | G57: BO-11483 | H57: PASCO RAMOS DE HERRERA GLORIA ELISA | I57: 07017191 | J57: FIERRO LEANDRO | K57: POLICLÍNICO DIVINO NIÑO JESÚS | L57: CRISTINA | M57: 0070001 | N57: 997369213 | O57: PASCO RAMOS DE HERRERA GLORIA ELISA | P57: 86518 | Q57: HEMOGRAMA COMPLETO | R57: 1 | S57: PRECISA | T57: POR ASIGNAR | U57: INSTITUTO MEDICO QUIRURGICO AREQUIPA S.A | V57: L.CENTRO | W57: LMAGAN | X57: 12.71 | Y57: LN. LABORATORIO | Z57: CIAS. DE SEGURO | AA57: CENTRO
A58: 46184 | B58: Junio | C58: 98573 | D58: BO | E58: 11483 | F58: CO | G58: BO-11483 | H58: PASCO RAMOS DE HERRERA GLORIA ELISA | I58: 07017191 | J58: FIERRO LEANDRO | K58: POLICLÍNICO DIVINO NIÑO JESÚS | L58: CRISTINA | M58: 0070001 | N58: 997369213 | O58: PASCO RAMOS DE HERRERA GLORIA ELISA | P58: 86518 | Q58: ORINA COMPLETO | R58: 1 | S58: PRECISA | T58: POR ASIGNAR | U58: INSTITUTO MEDICO QUIRURGICO AREQUIPA S.A | V58: L.CENTRO | W58: LMAGAN | X58: 21.19 | Y58: LN. LABORATORIO | Z58: CIAS. DE SEGURO | AA58: CENTRO
A59: 46184 | B59: Junio | C59: 98573 | D59: BO | E59: 11483 | F59: CO | G59: BO-11483 | H59: PASCO RAMOS DE HERRERA GLORIA ELISA | I59: 07017191 | J59: FIERRO LEANDRO | K59: POLICLÍNICO DIVINO NIÑO JESÚS | L59: CRISTINA | M59: 0070001 | N59: 997369213 | O59: PASCO RAMOS DE HERRERA GLORIA ELISA | P59: 86518 | Q59: GLUCOSA | R59: 1 | S59: PRECISA | T59: POR ASIGNAR | U59: INSTITUTO MEDICO QUIRURGICO AREQUIPA S.A | V59: L.CENTRO | W59: LMAGAN | X59: 12.71 | Y59: LN. LABORATORIO | Z59: CIAS. DE SEGURO | AA59: CENTRO
A60: 46184 | B60: Junio | C60: 98573 | D60: BO | E60: 11483 | F60: CO | G60: BO-11483 | H60: PASCO RAMOS DE HERRERA GLORIA ELISA | I60: 07017191 | J60: FIERRO LEANDRO | K60: POLICLÍNICO DIVINO NIÑO JESÚS | L60: CRISTINA | M60: 0070001 | N60: 997369213 | O60: PASCO RAMOS DE HERRERA GLORIA ELISA | P60: 86518 | Q60: TIEMPO DE COAGULACION Y SANGRIA | R60: 1 | S60: PRECISA | T60: POR ASIGNAR | U60: INSTITUTO MEDICO QUIRURGICO AREQUIPA S.A | V60: L.CENTRO | W60: LMAGAN | X60: 12.71 | Y60: LN. LABORATORIO | Z60: CIAS. DE SEGURO | AA60: CENTRO
A61: 46184 | B61: Junio | C61: 98573 | D61: BO | E61: 11483 | F61: CO | G61: BO-11483 | H61: PASCO RAMOS DE HERRERA GLORIA ELISA | I61: 07017191 | J61: FIERRO LEANDRO | K61: POLICLÍNICO DIVINO NIÑO JESÚS | L61: CRISTINA | M61: 0070001 | N61: 997369213 | O61: PASCO RAMOS DE HERRERA GLORIA ELISA | P61: 86518 | Q61: HIV 1,2 (TEST RAPIDO) | R61: 1 | S61: PRECISA | T61: POR ASIGNAR | U61: INSTITUTO MEDICO QUIRURGICO AREQUIPA S.A | V61: L.CENTRO | W61: LMAGAN | X61: 50.85 | Y61: LN. LABORATORIO | Z61: CIAS. DE SEGURO | AA61: CENTRO
A62: 46184 | B62: Junio | C62: 98577 | D62: BO | E62: 11486 | F62: CO | G62: BO-11486 | H62: SAUÑE AGUILAR MERCEDES | I62: 31032400 | J62: FIERRO LEANDRO | K62: POLICLÍNICO DIVINO NIÑO JESÚS | L62: CRISTINA | M62: 0069675 | N62: 940106575 | O62: SAUÑE AGUILAR MERCEDES | P62: 86525 | Q62: HEMOGRAMA COMPLETO | R62: 1 | S62: PRECISA | T62: POR ASIGNAR | U62: INSTITUTO MEDICO QUIRURGICO AREQUIPA S.A | V62: L.CENTRO | W62: LMAGAN | X62: 12.71 | Y62: LN. LABORATORIO | Z62: CIAS. DE SEGURO | AA62: CENTRO
A63: 46184 | B63: Junio | C63: 98577 | D63: BO | E63: 11486 | F63: CO | G63: BO-11486 | H63: SAUÑE AGUILAR MERCEDES | I63: 31032400 | J63: FIERRO LEANDRO | K63: POLICLÍNICO DIVINO NIÑO JESÚS | L63: CRISTINA | M63: 0069675 | N63: 940106575 | O63: SAUÑE AGUILAR MERCEDES | P63: 86525 | Q63: ORINA COMPLETO | R63: 1 | S63: PRECISA | T63: POR ASIGNAR | U63: INSTITUTO MEDICO QUIRURGICO AREQUIPA S.A | V63: L.CENTRO | W63: LMAGAN | X63: 21.19 | Y63: LN. LABORATORIO | Z63: CIAS. DE SEGURO | AA63: CENTRO
A64: 46184 | B64: Junio | C64: 98577 | D64: BO | E64: 11486 | F64: CO | G64: BO-11486 | H64: SAUÑE AGUILAR MERCEDES | I64: 31032400 | J64: FIERRO LEANDRO | K64: POLICLÍNICO DIVINO NIÑO JESÚS | L64: CRISTINA | M64: 0069675 | N64: 940106575 | O64: SAUÑE AGUILAR MERCEDES | P64: 86525 | Q64: GLUCOSA | R64: 1 | S64: PRECISA | T64: POR ASIGNAR | U64: INSTITUTO MEDICO QUIRURGICO AREQUIPA S.A | V64: L.CENTRO | W64: LMAGAN | X64: 12.71 | Y64: LN. LABORATORIO | Z64: CIAS. DE SEGURO | AA64: CENTRO
A65: 46184 | B65: Junio | C65: 98577 | D65: BO | E65: 11486 | F65: CO | G65: BO-11486 | H65: SAUÑE AGUILAR MERCEDES | I65: 31032400 | J65: FIERRO LEANDRO | K65: POLICLÍNICO DIVINO NIÑO JESÚS | L65: CRISTINA | M65: 0069675 | N65: 940106575 | O65: SAUÑE AGUILAR MERCEDES | P65: 86525 | Q65: TIEMPO DE COAGULACION Y SANGRIA | R65: 1 | S65: PRECISA | T65: POR ASIGNAR | U65: INSTITUTO MEDICO QUIRURGICO AREQUIPA S.A | V65: L.CENTRO | W65: LMAGAN | X65: 12.71 | Y65: LN. LABORATORIO | Z65: CIAS. DE SEGURO | AA65: CENTRO
... A69: 46184 | B69: Junio | C69: 98589 | D69: BO | E69: 11488 | F69: CO | G69: BO-11488 | H69: SAUÑE AGUILAR MERCEDES | I69: 31032400 | J69: FIERRO LEANDRO | K69: POLICLÍNICO DIVINO NIÑO JESÚS | L69: CRISTINA | M69: 0069675 | N69: 940106575 | O69: SAUÑE AGUILAR MERCEDES | P69: 86536 | Q69: PQ BIOMETRIA MICROSCOPIA | R69: 1 | S69: PRECISA | T69: POR ASIGNAR | U69: INSTITUTO MEDICO QUIRURGICO AREQUIPA S.A | V69: L.CENTRO | W69: LMAGAN | X69: 84.75 | Y69: LN. EXAMENES | Z69: CIAS. DE SEGURO | AA69: CENTRO
A70: 46184 | B70: Junio | C70: 98616 | D70: BO | E70: 11491 | F70: CO | G70: BO-11491 | H70: MUÑOZ OCAÑO ARMANDO | I70: 20976782 | J70: SILVA | L70: CRISTINA | M70: 0070068 | N70: 928786641 | O70: MUÑOZ OCAÑO ARMANDO | P70: 86562 | Q70: ECOGRAFIA OCULAR GENERAL SCAN A,B | R70: 1 | S70: PRECISA | T70: POR ASIGNAR | U70: INSTITUTO MEDICO QUIRURGICO AREQUIPA S.A | V70: L.CENTRO | W70: LMAGAN | X70: 135.59 | Y70: LN. EXAMENES | Z70: CIAS. DE SEGURO | AA70: CENTRO | AD70: 30
A71: 46185 | B71: Junio | C71: 98684 | D71: BO | E71: 11497 | F71: CO | G71: BO-11497 | H71: GUERRA VALLE LUZ MARGARITA | I71: 06106322 | J71: SAPAICO VICUÑA AUGUSTO RODRIGO | K71: HOSPITAL LOAYZA | L71: CRISTINA | M71: 0070101 | N71: 940296008 | O71: GUERRA VALLE LUZ MARGARITA | P71: 86622 | Q71: USO DE EQUIPOS E INSUMO IRIDOTOMIA | R71: 2 | S71: PRECISA | T71: POR ASIGNAR | U71: INSTITUTO MEDICO QUIRURGICO AREQUIPA S.A | V71: L.CENTRO | W71: LMAGAN | X71: 203.39 | Y71: LN. PROCEDIMIENTO | Z71: CIAS. DE SEGURO | AA71: CENTRO | AB71: 997145685 | AC71: 0011-0189-0200496417
A72: 46185 | B72: Junio | C72: 98697 | D72: FA | E72: 1032 | F72: CO | G72: FA-1032 | H72: SAUÑE AGUILAR MERCEDES | I72: 31032400 | J72: FIERRO LEANDRO | K72: POLICLÍNICO DIVINO NIÑO JESÚS | L72: CRISTINA | M72: 0069675 | N72: 940106575 | O72: GRUPO MEDICO INTEGRAL SOCIEDAD ANONIMA CERRADA | P72: 86543 | Q72: CIRUGIA DE DIA | R72: 1 | S72: PRECISA | T72: POR ASIGNAR | U72: INSTITUTO MEDICO QUIRURGICO AREQUIPA S.A | V72: L.CENTRO | W72: LMAGAN | X72: 0 | Y72: LN. CIRUGIA | Z72: CIAS. DE SEGURO | AA72: CENTRO
A73: 46185 | B73: Junio | C73: 98697 | D73: FA | E73: 1032 | F73: CO | G73: FA-1032 | H73: SAUÑE AGUILAR MERCEDES | I73: 31032400 | J73: FIERRO LEANDRO | K73: POLICLÍNICO DIVINO NIÑO JESÚS | L73: CRISTINA | M73: 0069675 | N73: 940106575 | O73: GRUPO MEDICO INTEGRAL SOCIEDAD ANONIMA CERRADA | P73: 86543 | Q73: FACOEMULSIFICACION PRIMIUM | R73: 1 | S73: PRECISA | T73: POR ASIGNAR | U73: INSTITUTO MEDICO QUIRURGICO AREQUIPA S.A | V73: L.CENTRO | W73: LMAGAN | X73: 762.71 | Y73: LN. CIRUGIA | Z73: CIAS. DE SEGURO | AA73: CENTRO
A74: 46185 | B74: Junio | C74: 98698 | D74: FA | E74: 1033 | F74: CO | G74: FA-1033 | H74: PASCO RAMOS DE HERRERA GLORIA ELISA | I74: 07017191 | J74: FIERRO LEANDRO | K74: POLICLÍNICO DIVINO NIÑO JESÚS | L74: CRISTINA | M74: 0070001 | N74: 997369213 | O74: GRUPO MEDICO INTEGRAL SOCIEDAD ANONIMA CERRADA | P74: 86542 | Q74: CIRUGIA DE DIA | R74: 1 | S74: PRECISA | T74: POR ASIGNAR | U74: INSTITUTO MEDICO QUIRURGICO AREQUIPA S.A | V74: L.CENTRO | W74: LMAGAN | X74: 0 | Y74: LN. CIRUGIA | Z74: CIAS. DE SEGURO | AA74: CENTRO
A75: 46185 | B75: Junio | C75: 98698 | D75: FA | E75: 1033 | F75: CO | G75: FA-1033 | H75: PASCO RAMOS DE HERRERA GLORIA ELISA | I75: 07017191 | J75: FIERRO LEANDRO | K75: POLICLÍNICO DIVINO NIÑO JESÚS | L75: CRISTINA | M75: 0070001 | N75: 997369213 | O75: GRUPO MEDICO INTEGRAL SOCIEDAD ANONIMA CERRADA | P75: 86542 | Q75: FACOEMULSIFICACION PRIMIUM | R75: 1 | S75: PRECISA | T75: POR ASIGNAR | U75: INSTITUTO MEDICO QUIRURGICO AREQUIPA S.A | V75: L.CENTRO | W75: LMAGAN | X75: 1525.42 | Y75: LN. CIRUGIA | Z75: CIAS. DE SEGURO | AA75: CENTRO
A76: 46185 | B76: Junio | C76: 98661 | D76: BO | E76: 11495 | F76: CO | G76: BO-11495 | H76: GALLEGOS BENAVIDES CRISTINA ANA | I76: 07136272 | J76: CARDENAS ORTEGA MARISA | K76: CONSULTORIO | L76: CRISTINA | M76: 0070089 | N76: 979097585 | O76: GALLEGOS BENAVIDES CRISTINA ANA | P76: 86601 | Q76: OCT DE MACULA | R76: 1 | S76: PRECISA | T76: POR ASIGNAR | U76: INSTITUTO MEDICO QUIRURGICO AREQUIPA S.A | V76: L.CENTRO | W76: LMAGAN | X76: 186.44 | Y76: LN. EXAMENES | Z76: CIAS. DE SEGURO | AA76: CENTRO | AB76: 947054605 | AC76: 193-34139202041 | AD76: 50
A77: 46185 | B77: Junio | C77: 2358 | D77: NC | E77: 11496 | F77: CR | G77: NC-11496 | H77: MONTALVO SUAREZ ESTHER ESPERANZA | I77: 08507757 | J77: HUAMAN RIOS LUIS ENRIQUE | K77: HOSPITAL SERGIO BERNALES | L77: CR | M77: 0070099 | N77: 990523847 | O77: MONTALVO SUAREZ ESTHER ESPERANZA | P77: 86611 | Q77: OCT DE NERVIO OPTICO Y CELULAS GANGLION | R77: 1 | S77: PRECISA | T77: POR ASIGNAR | U77: INSTITUTO MEDICO QUIRURGICO AREQUIPA S.A | V77: L.CENTRO | W77: LMAGAN | X77: -186.44 | Y77: LN. EXAMENES | Z77: CIAS. DE SEGURO | AA77: CENTRO | AB77: 999986041 | AC77: 191-30583545068 | AD77: 50
A78: 46185 | B78: Junio | C78: 98676 | D78: FA | E78: 1030 | F78: CO | G78: FA-1030 | H78: MONTALVO SUAREZ ESTHER ESPERANZA | I78: 08507757 | J78: HUAMAN RIOS LUIS ENRIQUE | K78: HOSPITAL SERGIO BERNALES | L78: CRISTINA | M78: 0070099 | N78: 990523847 | O78: VDAXIOM S.A.C. | P78: 86613 | Q78: OCT DE NERVIO OPTICO Y CELULAS GANGLION | R78: 1 | S78: PRECISA | T78: POR ASIGNAR | U78: INSTITUTO MEDICO QUIRURGICO AREQUIPA S.A | V78: L.CENTRO | W78: LMAGAN | X78: 186.44 | Y78: LN. EXAMENES | Z78: CIAS. DE SEGURO | AA78: CENTRO | AB78: 999986041 | AC78: 191-30583545068 | AD78: 50
A79: 46185 | B79: Junio | C79: 2358 | D79: BO | E79: 11496 | F79: CR | G79: BO-11496 | H79: MONTALVO SUAREZ ESTHER ESPERANZA | I79: 08507757 | J79: HUAMAN RIOS LUIS ENRIQUE | K79: HOSPITAL SERGIO BERNALES | L79: CR | M79: 0070099 | N79: 990523847 | O79: MONTALVO SUAREZ ESTHER ESPERANZA | P79: 86611 | Q79: OCT DE NERVIO OPTICO Y CELULAS GANGLION | R79: 1 | S79: PRECISA | T79: POR ASIGNAR | U79: INSTITUTO MEDICO QUIRURGICO AREQUIPA S.A | V79: L.CENTRO | W79: LMAGAN | X79: 186.44 | Y79: LN. EXAMENES | Z79: CIAS. DE SEGURO | AA79: CENTRO | AB79: 999986041 | AC79: 191-30583545068 | AD79: 50
A80: 46185 | B80: Junio | C80: 98645 | D80: BO | E80: 5580 | F80: CO | G80: BO-5580 | H80: CUBA HIDALGO VDA DE TOSCA JULIA JESUS | I80: 08052088 | J80: DIANA DAVALOS SORIA | K80: HOSPITAL CAYETANO HEREDIA | L80: CRISTINA | M80: 0070081 | N80: 955702271 | O80: CUBA HIDALGO VDA DE TOSCA JULIA JESUS | P80: 86587 | Q80: CAMPIMETRIA (CAMPO VISUAL) | R80: 1 | S80: PRECISA | T80: POR ASIGNAR | U80: INSTITUTO MEDICO QUIRURGICO AREQUIPA S.A | V80: L.CENTRO | W80: ACABRERA | X80: 135.59 | Y80: LN. EXAMENES | Z80: CIAS. DE SEGURO | AA80: CENTRO | AC80: 191-00494902000 | AD80: 30
A81: 46185 | B81: Junio | C81: 98694 | D81: FA | E81: 1031 | F81: CO | G81: FA-1031 | H81: CARAZAS CERRILLO DE APAZA GREGORIA | I81: 08985710 | J81: MANCHEGO LOMBARDI MICHAEL | K81: CONSULTORIO PARTICULAR | L81: CRISTINA | M81: 0070006 | N81: NO TIENE | O81: CENTRO OFTALMOLOGICO OFTALMOCARE S.R.L. | P81: 86633 | Q81: USO DE EQUIPOS E INSUMO AVASTIN | R81: 1 | S81: PRECISA | T81: POR ASIGNAR | U81: INSTITUTO MEDICO QUIRURGICO AREQUIPA S.A | V81: L.CENTRO | W81: LMAGAN | X81: 254.24 | Y81: LN. PROCEDIMIENTO | Z81: CIAS. DE SEGURO | AA81: CENTRO | AB81: 970582106 | AC81: 639-3004120188
A82: 46188 | B82: Junio | C82: 98853 | D82: BO | E82: 5605 | F82: CO | G82: BO-5605 | H82: TORRELIO GUERRERO LIDIA ZOTICA | I82: 06689006 | J82: SAPAICO VICUÑA AUGUSTO RODRIGO | K82: HOSPITAL LOAYZA | L82: CRISTINA | M82: 0070124 | N82: 999488621 | O82: TORRELIO GUERRERO LIDIA ZOTICA | P82: 86768 | Q82: BIOMETRIA IOL MASTER 700 | R82: 1 | S82: PRECISA | T82: POR ASIGNAR | U82: INSTITUTO MEDICO QUIRURGICO AREQUIPA S.A | V82: L.CENTRO | W82: ACABRERA | X82: 152.54 | Y82: LN. EXAMENES | Z82: CIAS. DE SEGURO | AA82: CENTRO | AB82: 997145685 | AC82: 0011-0189-0200496417 | AD82: 30
A83: 46188 | B83: Junio | C83: 98811 | D83: BO | E83: 11521 | F83: CO | G83: BO-11521 | H83: OCAS ROSALES RONALD JEANCARLOS | I83: 45170637 | J83: ALEMAÑY ERNESTO | K83: CLINICA LA LUZ | L83: CRISTINA | M83: 0070158 | N83: 999322893 | O83: OCAS ROSALES RONALD JEANCARLOS | P83: 86729 | Q83: ANGIOGRAFIA CON FLUORESCEINA | R83: 1 | S83: PRECISA | T83: POR ASIGNAR | U83: INSTITUTO MEDICO QUIRURGICO AREQUIPA S.A | V83: L.CENTRO | W83: LMAGAN | X83: 338.98 | Y83: LN. EXAMENES | Z83: CIAS. DE SEGURO | AA83: CENTRO | AB83: 978548687 | AC83: 0011-0732-0200152751 | AD83: 100
A84: 46189 | B84: Junio | C84: 98957 | D84: BO | E84: 11554 | F84: CO | G84: BO-11554 | H84: CANCHAYA CAYO JULIO LEONCIO | I84: 44212852 | J84: AGRAMONTE ZEA EDILBERTO | K84: HOSPITAL DE LA SOLIDARIDAD SJL | L84: CRISTINA | M84: 0070227 | N84: 964246765 | O84: CANCHAYA CAYO JULIO LEONCIO | P84: 86868 | Q84: CAMPIMETRIA (CAMPO VISUAL) | R84: 1 | S84: PRECISA | T84: INSTITUTO MEDICO QUIRURGICO AREQUIPA S.A | U84: INSTITUTO MEDICO QUIRURGICO AREQUIPA S.A | V84: L.CENTRO | W84: LMAGAN | X84: 135.59 | Y84: LN. EXAMENES | Z84: CIAS. DE SEGURO | AA84: CENTRO | AB84: 987407712 | AC84: 0011-0190-0200333106 | AD84: 30
A85: 46189 | B85: Junio | C85: 98957 | D85: BO | E85: 11554 | F85: CO | G85: BO-11554 | H85: CANCHAYA CAYO JULIO LEONCIO | I85: 44212852 | J85: AGRAMONTE ZEA EDILBERTO | K85: HOSPITAL DE LA SOLIDARIDAD SJL | L85: CRISTINA | M85: 0070227 | N85: 964246765 | O85: CANCHAYA CAYO JULIO LEONCIO | P85: 86868 | Q85: OCT DE NERVIO OPTICO Y CELULAS GANGLION | R85: 1 | S85: PRECISA | T85: INSTITUTO MEDICO QUIRURGICO AREQUIPA S.A | U85: INSTITUTO MEDICO QUIRURGICO AREQUIPA S.A | V85: L.CENTRO | W85: LMAGAN | X85: 186.44 | Y85: LN. EXAMENES | Z85: CIAS. DE SEGURO | AA85: CENTRO | AB85: 987407712 | AC85: 0011-0190-0200333106 | AD85: 50
A86: 46189 | B86: Junio | C86: 98957 | D86: BO | E86: 11554 | F86: CO | G86: BO-11554 | H86: CANCHAYA CAYO JULIO LEONCIO | I86: 44212852 | J86: AGRAMONTE ZEA EDILBERTO | K86: HOSPITAL DE LA SOLIDARIDAD SJL | L86: CRISTINA | M86: 0070227 | N86: 964246765 | O86: CANCHAYA CAYO JULIO LEONCIO | P86: 86868 | Q86: PAQUIMETRIA | R86: 1 | S86: PRECISA | T86: INSTITUTO MEDICO QUIRURGICO AREQUIPA S.A | U86: INSTITUTO MEDICO QUIRURGICO AREQUIPA S.A | V86: L.CENTRO | W86: LMAGAN | X86: 152.54 | Y86: LN. EXAMENES | Z86: CIAS. DE SEGURO | AA86: CENTRO | AB86: 987407712 | AC86: 0011-0190-0200333106 | AD86: 30
A87: 46189 | B87: Junio | C87: 98947 | D87: BO | E87: 11552 | F87: CO | G87: BO-11552 | H87: QUIPUSCO BERNAL MIGUEL WENCESLAO | I87: 06057576 | J87: CACERES PINTO ALVARO DANIEL | K87: HOSPITAL INO | L87: CRISTINA | M87: 0054107 | N87: 998759676 | O87: QUIPUSCO BERNAL MIGUEL WENCESLAO | P87: 86860 | Q87: OCT DE NERVIO OPTICO Y CELULAS GANGLION | R87: 1 | S87: PRECISA | T87: INSTITUTO MEDICO QUIRURGICO AREQUIPA S.A | U87: INSTITUTO MEDICO QUIRURGICO AREQUIPA S.A | V87: L.CENTRO | W87: LMAGAN | X87: 186.44 | Y87: LN. EXAMENES | Z87: CIAS. DE SEGURO | AA87: CENTRO | AB87: 966697811 | AC87: 0011-0184-0200649518 | AD87: 50
A88: 46189 | B88: Junio | C88: 98965 | D88: BO | E88: 11556 | F88: CO | G88: BO-11556 | H88: RODRIGUEZ VELA KATHERINE FIORELLA | I88: 76232484 | J88: FIERRO LEANDRO | K88: POLICLÍNICO DIVINO NIÑO JESÚS | L88: CRISTINA | M88: 0070028 | N88: 906 777 340 | O88: RODRIGUEZ VELA KATHERINE FIORELLA | P88: 86877 | Q88: BIOMETRIA IOL MASTER 700 | R88: 1 | S88: PRECISA | T88: INSTITUTO MEDICO QUIRURGICO AREQUIPA S.A | U88: INSTITUTO MEDICO QUIRURGICO AREQUIPA S.A | V88: L.CENTRO | W88: LMAGAN | X88: 42.37 | Y88: LN. EXAMENES | Z88: CIAS. DE SEGURO | AA88: CENTRO | AD88: 30
A89: 46189 | B89: Junio | C89: 98965 | D89: BO | E89: 11556 | F89: CO | G89: BO-11556 | H89: RODRIGUEZ VELA KATHERINE FIORELLA | I89: 76232484 | J89: FIERRO LEANDRO | K89: POLICLÍNICO DIVINO NIÑO JESÚS | L89: CRISTINA | M89: 0070028 | N89: 906 777 340 | O89: RODRIGUEZ VELA KATHERINE FIORELLA | P89: 86877 | Q89: MICROSCOPIA ESPECULAR | R89: 1 | S89: PRECISA | T89: INSTITUTO MEDICO QUIRURGICO AREQUIPA S.A | U89: INSTITUTO MEDICO QUIRURGICO AREQUIPA S.A | V89: L.CENTRO | W89: LMAGAN | X89: 42.37 | Y89: LN. EXAMENES | Z89: CIAS. DE SEGURO | AA89: CENTRO | AD89: 30
A90: 46189 | B90: Junio | C90: 98915 | D90: BO | E90: 11546 | F90: CO | G90: BO-11546 | H90: MANCO CESPEDES EMMA IMELDA | I90: 08826096 | J90: ESPEJO ALVA JULIO EDWIN | K90: CONSULTORIO PARTICULAR | L90: CRISTINA | M90: 0070206 | N90: 964035237 | O90: MANCO CESPEDES EMMA IMELDA | P90: 86820 | Q90: OCT DE MACULA | R90: 1 | S90: PRECISA | T90: POR ASIGNAR | U90: INSTITUTO MEDICO QUIRURGICO AREQUIPA S.A | V90: L.CENTRO | W90: LMAGAN | X90: 186.44 | Y90: LN. EXAMENES | Z90: CIAS. DE SEGURO | AA90: CENTRO | AB90: 981227454 | AC90: 087-3150119440 | AD90: 50
A91: 46189 | B91: Junio | C91: 98930 | D91: BO | E91: 5621 | F91: CO | G91: BO-5621 | H91: ESPINOZA BEDRIÑANA SUSANA | I91: 08578137 | J91: HUAMAN CUICAPUSA KELLY | L91: CRISTINA | M91: 0070218 | N91: 991432739 | O91: ESPINOZA BEDRIÑANA SUSANA | P91: 86839 | Q91: CAMPIMETRIA (CAMPO VISUAL) | R91: 1 | S91: PRECISA | T91: INSTITUTO MEDICO QUIRURGICO AREQUIPA S.A | U91: INSTITUTO MEDICO QUIRURGICO AREQUIPA S.A | V91: L.CENTRO | W91: ACABRERA | X91: 135.59 | Y91: LN. EXAMENES | Z91: CIAS. DE SEGURO | AA91: CENTRO | AD91: 30
A92: 46190 | B92: Junio | C92: 99046 | D92: BO | E92: 11571 | F92: CO | G92: BO-11571 | H92: AURIS ZENTENO DE TELLO ZENAIDA MARINA | I92: 09212243 | J92: ORNA ACOSTA JORGE AQUILES | K92: HOSPITAL LOAYZA | L92: CRISTINA | M92: 0070254 | N92: 965361980 | O92: AURIS ZENTENO DE TELLO ZENAIDA MARINA | P92: 86936 | Q92: USO DE EQUIPOS E INSUMO CAPSULOTOMIA | R92: 1 | S92: PRECISA | T92: INSTITUTO MEDICO QUIRURGICO AREQUIPA S.A | U92: INSTITUTO MEDICO QUIRURGICO AREQUIPA S.A | V92: L.CENTRO | W92: LMAGAN | X92: 101.69 | Y92: LN. PROCEDIMIENTO | Z92: CIAS. DE SEGURO | AA92: CENTRO | AB92: 999996347 | AC92: 052-7510523
A93: 46190 | B93: Junio | C93: 99113 | D93: BO | E93: 11578 | F93: CO | G93: BO-11578 | H93: SACA TICONA NELSON | I93: 42449449 | J93: AGRAMONTE ZEA EDILBERTO | K93: HOSPITAL DE LA SOLIDARIDAD SJL | L93: CRISTINA | M93: 0070273 | N93: 945692301 | O93: SACA TICONA NELSON | P93: 86964 | Q93: OCT DE NERVIO OPTICO Y CELULAS GANGLION | R93: 1 | S93: PRECISA | T93: INSTITUTO MEDICO QUIRURGICO AREQUIPA S.A | U93: INSTITUTO MEDICO QUIRURGICO AREQUIPA S.A | V93: L.CENTRO | W93: LMAGAN | X93: 186.44 | Y93: LN. EXAMENES | Z93: CIAS. DE SEGURO | AA93: CENTRO | AB93: 987407712 | AC93: 0011-0190-0200333106 | AD93: 50
A94: 46190 | B94: Junio | C94: 98996 | D94: FA | E94: 1037 | F94: CO | G94: FA-1037 | H94: BARAHONA VERASTEGUI MEDARDO | I94: 08834924 | J94: FIERRO LEANDRO | K94: POLICLÍNICO DIVINO NIÑO JESÚS | L94: CRISTINA | M94: 0070031 | N94: 981607915 | O94: GRUPO MEDICO INTEGRAL SOCIEDAD ANONIMA CERRADA | P94: 86546 | Q94: CIRUGIA DE DIA | R94: 1 | S94: PRECISA | T94: POR ASIGNAR | U94: INSTITUTO MEDICO QUIRURGICO AREQUIPA S.A | V94: L.CENTRO | W94: LMAGAN | X94: 0 | Y94: LN. CIRUGIA | Z94: CIAS. DE SEGURO | AA94: CENTRO
A95: 46190 | B95: Junio | C95: 98996 | D95: FA | E95: 1037 | F95: CO | G95: FA-1037 | H95: BARAHONA VERASTEGUI MEDARDO | I95: 08834924 | J95: FIERRO LEANDRO | K95: POLICLÍNICO DIVINO NIÑO JESÚS | L95: CRISTINA | M95: 0070031 | N95: 981607915 | O95: GRUPO MEDICO INTEGRAL SOCIEDAD ANONIMA CERRADA | P95: 86546 | Q95: FACOEMULSIFICACION PRIMIUM | R95: 1 | S95: PRECISA | T95: POR ASIGNAR | U95: INSTITUTO MEDICO QUIRURGICO AREQUIPA S.A | V95: L.CENTRO | W95: LMAGAN | X95: 762.71 | Y95: LN. CIRUGIA | Z95: CIAS. DE SEGURO | AA95: CENTRO
A96: 46190 | B96: Junio | C96: 99003 | D96: FA | E96: 1040 | F96: CO | G96: FA-1040 | H96: RODRIGUEZ VELA KATHERINE FIORELLA | I96: 76232484 | J96: FIERRO LEANDRO | K96: POLICLÍNICO DIVINO NIÑO JESÚS | L96: CRISTINA | M96: 0070028 | N96: 906 777 340 | O96: GRUPO MEDICO INTEGRAL SOCIEDAD ANONIMA CERRADA | P96: 86827 | Q96: CIRUGIA DE DIA | R96: 1 | S96: PRECISA | T96: POR ASIGNAR | U96: INSTITUTO MEDICO QUIRURGICO AREQUIPA S.A | V96: L.CENTRO | W96: LMAGAN | X96: 0 | Y96: LN. CIRUGIA | Z96: CIAS. DE SEGURO | AA96: CENTRO
A97: 46190 | B97: Junio | C97: 99003 | D97: FA | E97: 1040 | F97: CO | G97: FA-1040 | H97: RODRIGUEZ VELA KATHERINE FIORELLA | I97: 76232484 | J97: FIERRO LEANDRO | K97: POLICLÍNICO DIVINO NIÑO JESÚS | L97: CRISTINA | M97: 0070028 | N97: 906 777 340 | O97: GRUPO MEDICO INTEGRAL SOCIEDAD ANONIMA CERRADA | P97: 86827 | Q97: CIRUGIA REFRACTIVA TRANS PRK | R97: 1 | S97: PRECISA | T97: POR ASIGNAR | U97: INSTITUTO MEDICO QUIRURGICO AREQUIPA S.A | V97: L.CENTRO | W97: LMAGAN | X97: 550.85 | Y97: LN. CIRUGIA | Z97: CIAS. DE SEGURO | AA97: CENTRO
A98: 46190 | B98: Junio | C98: 99095 | D98: BO | E98: 11575 | F98: CO | G98: BO-11575 | H98: BAUTISTA LOPEZ HERMINIA | I98: 21840481 | J98: SUAREZ ALVARADO SUSANA | K98: CLINICA INTERNACIONAL SURCO | L98: CRISTINA | M98: 0044128 | N98: 999166413 | O98: BAUTISTA LOPEZ HERMINIA | P98: 86938 | Q98: CIRUGIA DE DIA | R98: 1 | S98: PRECISA | T98: INSTITUTO MEDICO QUIRURGICO AREQUIPA S.A | U98: INSTITUTO MEDICO QUIRURGICO AREQUIPA S.A | V98: L.CENTRO | W98: LMAGAN | X98: 0 | Y98: LN. CIRUGIA | Z98: CIAS. DE SEGURO | AA98: CENTRO
A99: 46190 | B99: Junio | C99: 99095 | D99: BO | E99: 11575 | F99: CO | G99: BO-11575 | H99: BAUTISTA LOPEZ HERMINIA | I99: 21840481 | J99: SUAREZ ALVARADO SUSANA | K99: CLINICA INTERNACIONAL SURCO | L99: CRISTINA | M99: 0044128 | N99: 999166413 | O99: BAUTISTA LOPEZ HERMINIA | P99: 86938 | Q99: CONJUNTIVOPLASTIA | R99: 1 | S99: PRECISA | T99: INSTITUTO MEDICO QUIRURGICO AREQUIPA S.A | U99: INSTITUTO MEDICO QUIRURGICO AREQUIPA S.A | V99: L.CENTRO | W99: LMAGAN | X99: 139.83 | Y99: LN. CIRUGIA | Z99: CIAS. DE SEGURO | AA99: CENTRO
A100: 46191 | B100: Junio | C100: 99135 | D100: BO | E100: 5638 | F100: CO | G100: BO-5638 | H100: DIAZ ESCOBAL AUGUSTO | I100: 08560804 | J100: VILLAR CURAHUA MARCELA ALEJANDRA | K100: GAMARRA SALUD | L100: CRISTINA | M100: 0070232 | N100: 923538499 | O100: DIAZ ESCOBAL AUGUSTO | P100: 86977 | Q100: BIOMETRIA IOL MASTER 700 | R100: 1 | S100: PRECISA | T100: INSTITUTO MEDICO QUIRURGICO AREQUIPA S.A | U100: INSTITUTO MEDICO QUIRURGICO AREQUIPA S.A | V100: L.CENTRO | W100: ACABRERA | X100: 42.37 | Y100: LN. EXAMENES | Z100: CIAS. DE SEGURO | AA100: CENTRO | AB100: 950133748 | AC100: 191-9953047026 | AD100: 30
A101: 46191 | B101: Junio | C101: 99135 | D101: BO | E101: 5638 | F101: CO | G101: BO-5638 | H101: DIAZ ESCOBAL AUGUSTO | I101: 08560804 | J101: VILLAR CURAHUA MARCELA ALEJANDRA | K101: GAMARRA SALUD | L101: CRISTINA | M101: 0070232 | N101: 923538499 | O101: DIAZ ESCOBAL AUGUSTO | P101: 86977 | Q101: MICROSCOPIA ESPECULAR | R101: 1 | S101: PRECISA | T101: INSTITUTO MEDICO QUIRURGICO AREQUIPA S.A | U101: INSTITUTO MEDICO QUIRURGICO AREQUIPA S.A | V101: L.CENTRO | W101: ACABRERA | X101: 42.37 | Y101: LN. EXAMENES | Z101: CIAS. DE SEGURO | AA101: CENTRO | AB101: 950133748 | AC101: 191-9953047026 | AD101: 30
A102: 46191 | B102: Junio | C102: 99177 | D102: BO | E102: 3911 | F102: CO | G102: BO-3911 | H102: ALANIA SUAREZ DE GIL DIONICIA | I102: 07738357 | J102: RUIZ ROJAS PAUBLO ENRIQUE | K102: CONSULTORIO CUBANO COMAS | L102: CRISTINA | M102: 0070290 | N102: 991819463 | O102: ALANIA SUAREZ DE GIL DIONICIA | P102: 87014 | Q102: OCT DE MACULA | R102: 1 | S102: PRECISA LN | T102: POR ASIGNAR | U102: INSTITUTO MEDICO QUIRURGICO AREQUIPA S.A | V102: L.NORTE | W102: BGALLOSA | X102: 186.44 | Y102: LN. EXAMENES | Z102: CIAS. DE SEGURO | AA102: NORTE | AB102: 992903716 | AC102: 191-91415089071 | AD102: 50
A103: 46191 | B103: Junio | C103: 99136 | D103: BO | E103: 5639 | F103: CO | G103: BO-5639 | H103: DIAZ ESCOBAL AUGUSTO | I103: 08560804 | J103: FIERRO LEANDRO | K103: POLICLÍNICO DIVINO NIÑO JESÚS | L103: CRISTINA | M103: 0070232 | N103: 923538499 | O103: DIAZ ESCOBAL AUGUSTO | P103: 86978 | Q103: HEMOGRAMA COMPLETO | R103: 1 | S103: PRECISA | T103: INSTITUTO MEDICO QUIRURGICO AREQUIPA S.A | U103: INSTITUTO MEDICO QUIRURGICO AREQUIPA S.A | V103: L.CENTRO | W103: ACABRERA | X103: 12.71 | Y103: LN. LABORATORIO | Z103: CIAS. DE SEGURO | AA103: CENTRO
...

Sheet Cálculo_Categorías
A1: REPORTE DE FACTURACIÓN Y CATEGORIZACIÓN MÉDICO/INSTITUCIÓN
A3: Filtro de Mes | C3: S/. | E3: Filtro de Mes | G3: S/.
A4: Mes | B4: TODOS | C4: =+SUM(Tabla5[FACTURACIÓN]) -> 166117.68 | E4: Mes | F4: TODOS | G4: =+SUM(Tabla9[FACTURACIÓN]) -> 165507.54
A6: REPORTE DE MÉDICOS Y CATEGORIZACIÓN | E6: REPORTE DE INSTITUCIONES Y CATEGORIZACIÓN
A7: MEDICO | B7: FACTURACIÓN | C7: CATEGORÍA | E7: INSTITUCIÓN | F7: FACTURACIÓN | G7: CATEGORÍA
A8: ORNA ACOSTA JORGE AQUILES | B8: =+IF($B$4="TODOS",SUMIFS(Base_Precisa!X:X,Base_Precisa!J:J,Cálculo_Categorías!A8),SUMIFS(Base_Precisa!X:X,Base_Precisa!J:J,Cálculo_Categorías!A8,Base_Precisa!B:B,Cálculo_Categorías!$B$4)) -> 1271.17 | C8: {=+_xlfn.IFS(Tabla5[[#This Row],[FACTURACIÓN]]<500,"A",Tabla5[[#This Row],[FACTURACIÓN]]<1000,"AA",Tabla5[[#This Row],[FACTURACIÓN]]>=1000,"AAA")} -> AAA | E8: HOSPITAL LOAYZA | F8: =+IF($F$4="TODOS",SUMIFS(Base_Precisa!X:X,Base_Precisa!K:K,Cálculo_Categorías!E8),SUMIFS(Base_Precisa!X:X,Base_Precisa!K:K,Cálculo_Categorías!E8,Base_Precisa!B:B,Cálculo_Categorías!$F$4)) -> 12203.24 | G8: {=+_xlfn.IFS(Tabla9[[#This Row],[FACTURACIÓN]]<200,"Sin Categoría",Tabla9[[#This Row],[FACTURACIÓN]]<500,"A",Tabla9[[#This Row],[FACTURACIÓN]]<1000,"AA",Tabla9[[#This Row],[FACTURACIÓN]]>=1000,"AAA")} -> AAA
A9: PEÑA CAMARGO CRISTOPHER OMAR | B9: =+IF($B$4="TODOS",SUMIFS(Base_Precisa!X:X,Base_Precisa!J:J,Cálculo_Categorías!A9),SUMIFS(Base_Precisa!X:X,Base_Precisa!J:J,Cálculo_Categorías!A9,Base_Precisa!B:B,Cálculo_Categorías!$B$4)) -> 372.88 | C9: {=+_xlfn.IFS(Tabla5[[#This Row],[FACTURACIÓN]]<500,"A",Tabla5[[#This Row],[FACTURACIÓN]]<1000,"AA",Tabla5[[#This Row],[FACTURACIÓN]]>=1000,"AAA")} -> A | E9: HOSPITAL SERGIO BERNALES | F9: =+IF($F$4="TODOS",SUMIFS(Base_Precisa!X:X,Base_Precisa!K:K,Cálculo_Categorías!E9),SUMIFS(Base_Precisa!X:X,Base_Precisa!K:K,Cálculo_Categorías!E9,Base_Precisa!B:B,Cálculo_Categorías!$F$4)) -> 1779.64 | G9: {=+_xlfn.IFS(Tabla9[[#This Row],[FACTURACIÓN]]<200,"Sin Categoría",Tabla9[[#This Row],[FACTURACIÓN]]<500,"A",Tabla9[[#This Row],[FACTURACIÓN]]<1000,"AA",Tabla9[[#This Row],[FACTURACIÓN]]>=1000,"AAA")} -> AAA
A10: TORRES LEAL ADOLFO LEON | B10: =+IF($B$4="TODOS",SUMIFS(Base_Precisa!X:X,Base_Precisa!J:J,Cálculo_Categorías!A10),SUMIFS(Base_Precisa!X:X,Base_Precisa!J:J,Cálculo_Categorías!A10,Base_Precisa!B:B,Cálculo_Categorías!$B$4)) -> 271.18 | C10: {=+_xlfn.IFS(Tabla5[[#This Row],[FACTURACIÓN]]<500,"A",Tabla5[[#This Row],[FACTURACIÓN]]<1000,"AA",Tabla5[[#This Row],[FACTURACIÓN]]>=1000,"AAA")} -> A | E10: CLÍNICA SAN FELIPE LA MOLINA | F10: =+IF($F$4="TODOS",SUMIFS(Base_Precisa!X:X,Base_Precisa!K:K,Cálculo_Categorías!E10),SUMIFS(Base_Precisa!X:X,Base_Precisa!K:K,Cálculo_Categorías!E10,Base_Precisa!B:B,Cálculo_Categorías!$F$4)) -> 271.18 | G10: {=+_xlfn.IFS(Tabla9[[#This Row],[FACTURACIÓN]]<200,"Sin Categoría",Tabla9[[#This Row],[FACTURACIÓN]]<500,"A",Tabla9[[#This Row],[FACTURACIÓN]]<1000,"AA",Tabla9[[#This Row],[FACTURACIÓN]]>=1000,"AAA")} -> A
A11: HUARANGA RUIZ CORNEJO JORGE ERNESTO | B11: =+IF($B$4="TODOS",SUMIFS(Base_Precisa!X:X,Base_Precisa!J:J,Cálculo_Categorías!A11),SUMIFS(Base_Precisa!X:X,Base_Precisa!J:J,Cálculo_Categorías!A11,Base_Precisa!B:B,Cálculo_Categorías!$B$4)) -> 898.29 | C11: {=+_xlfn.IFS(Tabla5[[#This Row],[FACTURACIÓN]]<500,"A",Tabla5[[#This Row],[FACTURACIÓN]]<1000,"AA",Tabla5[[#This Row],[FACTURACIÓN]]>=1000,"AAA")} -> AA | E11: HOSPITAL MONGRUT | F11: =+IF($F$4="TODOS",SUMIFS(Base_Precisa!X:X,Base_Precisa!K:K,Cálculo_Categorías!E11),SUMIFS(Base_Precisa!X:X,Base_Precisa!K:K,Cálculo_Categorías!E11,Base_Precisa!B:B,Cálculo_Categorías!$F$4)) -> 898.29 | G11: {=+_xlfn.IFS(Tabla9[[#This Row],[FACTURACIÓN]]<200,"Sin Categoría",Tabla9[[#This Row],[FACTURACIÓN]]<500,"A",Tabla9[[#This Row],[FACTURACIÓN]]<1000,"AA",Tabla9[[#This Row],[FACTURACIÓN]]>=1000,"AAA")} -> AA
A12: AGRAMONTE ZEA EDILBERTO | B12: =+IF($B$4="TODOS",SUMIFS(Base_Precisa!X:X,Base_Precisa!J:J,Cálculo_Categorías!A12),SUMIFS(Base_Precisa!X:X,Base_Precisa!J:J,Cálculo_Categorías!A12,Base_Precisa!B:B,Cálculo_Categorías!$B$4)) -> 4338.93 | C12: {=+_xlfn.IFS(Tabla5[[#This Row],[FACTURACIÓN]]<500,"A",Tabla5[[#This Row],[FACTURACIÓN]]<1000,"AA",Tabla5[[#This Row],[FACTURACIÓN]]>=1000,"AAA")} -> AAA | E12: HOSPITAL DE LA SOLIDARIDAD SJL | F12: =+IF($F$4="TODOS",SUMIFS(Base_Precisa!X:X,Base_Precisa!K:K,Cálculo_Categorías!E12),SUMIFS(Base_Precisa!X:X,Base_Precisa!K:K,Cálculo_Categorías!E12,Base_Precisa!B:B,Cálculo_Categorías!$F$4)) -> 4338.93 | G12: {=+_xlfn.IFS(Tabla9[[#This Row],[FACTURACIÓN]]<200,"Sin Categoría",Tabla9[[#This Row],[FACTURACIÓN]]<500,"A",Tabla9[[#This Row],[FACTURACIÓN]]<1000,"AA",Tabla9[[#This Row],[FACTURACIÓN]]>=1000,"AAA")} -> AAA
A13: MANSILLA JUAN JOSÉ | B13: =+IF($B$4="TODOS",SUMIFS(Base_Precisa!X:X,Base_Precisa!J:J,Cálculo_Categorías!A13),SUMIFS(Base_Precisa!X:X,Base_Precisa!J:J,Cálculo_Categorías!A13,Base_Precisa!B:B,Cálculo_Categorías!$B$4)) -> 355.93 | C13: {=+_xlfn.IFS(Tabla5[[#This Row],[FACTURACIÓN]]<500,"A",Tabla5[[#This Row],[FACTURACIÓN]]<1000,"AA",Tabla5[[#This Row],[FACTURACIÓN]]>=1000,"AAA")} -> A | E13: CONSULTORIO PARTICULAR | F13: =+IF($F$4="TODOS",SUMIFS(Base_Precisa!X:X,Base_Precisa!K:K,Cálculo_Categorías!E13),SUMIFS(Base_Precisa!X:X,Base_Precisa!K:K,Cálculo_Categorías!E13,Base_Precisa!B:B,Cálculo_Categorías!$F$4)) -> 21639.64 | G13: {=+_xlfn.IFS(Tabla9[[#This Row],[FACTURACIÓN]]<200,"Sin Categoría",Tabla9[[#This Row],[FACTURACIÓN]]<500,"A",Tabla9[[#This Row],[FACTURACIÓN]]<1000,"AA",Tabla9[[#This Row],[FACTURACIÓN]]>=1000,"AAA")} -> AAA
A14: CELIA RODRIGUEZ | B14: =+IF($B$4="TODOS",SUMIFS(Base_Precisa!X:X,Base_Precisa!J:J,Cálculo_Categorías!A14),SUMIFS(Base_Precisa!X:X,Base_Precisa!J:J,Cálculo_Categorías!A14,Base_Precisa!B:B,Cálculo_Categorías!$B$4)) -> 0 | C14: {=+_xlfn.IFS(Tabla5[[#This Row],[FACTURACIÓN]]<500,"A",Tabla5[[#This Row],[FACTURACIÓN]]<1000,"AA",Tabla5[[#This Row],[FACTURACIÓN]]>=1000,"AAA")} -> A | E14: CLÍNICA SAN CAMILO | F14: =+IF($F$4="TODOS",SUMIFS(Base_Precisa!X:X,Base_Precisa!K:K,Cálculo_Categorías!E14),SUMIFS(Base_Precisa!X:X,Base_Precisa!K:K,Cálculo_Categorías!E14,Base_Precisa!B:B,Cálculo_Categorías!$F$4)) -> 3809.29 | G14: {=+_xlfn.IFS(Tabla9[[#This Row],[FACTURACIÓN]]<200,"Sin Categoría",Tabla9[[#This Row],[FACTURACIÓN]]<500,"A",Tabla9[[#This Row],[FACTURACIÓN]]<1000,"AA",Tabla9[[#This Row],[FACTURACIÓN]]>=1000,"AAA")} -> AAA
A15: GUTARRA PAUCAR JULIA KARINA | B15: =+IF($B$4="TODOS",SUMIFS(Base_Precisa!X:X,Base_Precisa!J:J,Cálculo_Categorías!A15),SUMIFS(Base_Precisa!X:X,Base_Precisa!J:J,Cálculo_Categorías!A15,Base_Precisa!B:B,Cálculo_Categorías!$B$4)) -> 3809.29 | C15: {=+_xlfn.IFS(Tabla5[[#This Row],[FACTURACIÓN]]<500,"A",Tabla5[[#This Row],[FACTURACIÓN]]<1000,"AA",Tabla5[[#This Row],[FACTURACIÓN]]>=1000,"AAA")} -> AAA | E15: CONSULTORIO | F15: =+IF($F$4="TODOS",SUMIFS(Base_Precisa!X:X,Base_Precisa!K:K,Cálculo_Categorías!E15),SUMIFS(Base_Precisa!X:X,Base_Precisa!K:K,Cálculo_Categorías!E15,Base_Precisa!B:B,Cálculo_Categorías!$F$4)) -> 1084.74 | G15: {=+_xlfn.IFS(Tabla9[[#This Row],[FACTURACIÓN]]<200,"Sin Categoría",Tabla9[[#This Row],[FACTURACIÓN]]<500,"A",Tabla9[[#This Row],[FACTURACIÓN]]<1000,"AA",Tabla9[[#This Row],[FACTURACIÓN]]>=1000,"AAA")} -> AAA
A16: BOBBIO PEREZ MILKO | B16: =+IF($B$4="TODOS",SUMIFS(Base_Precisa!X:X,Base_Precisa!J:J,Cálculo_Categorías!A16),SUMIFS(Base_Precisa!X:X,Base_Precisa!J:J,Cálculo_Categorías!A16,Base_Precisa!B:B,Cálculo_Categorías!$B$4)) -> 338.98 | C16: {=+_xlfn.IFS(Tabla5[[#This Row],[FACTURACIÓN]]<500,"A",Tabla5[[#This Row],[FACTURACIÓN]]<1000,"AA",Tabla5[[#This Row],[FACTURACIÓN]]>=1000,"AAA")} -> A | E16: HOSPITAL INO | F16: =+IF($F$4="TODOS",SUMIFS(Base_Precisa!X:X,Base_Precisa!K:K,Cálculo_Categorías!E16),SUMIFS(Base_Precisa!X:X,Base_Precisa!K:K,Cálculo_Categorías!E16,Base_Precisa!B:B,Cálculo_Categorías!$F$4)) -> 1322.02 | G16: {=+_xlfn.IFS(Tabla9[[#This Row],[FACTURACIÓN]]<200,"Sin Categoría",Tabla9[[#This Row],[FACTURACIÓN]]<500,"A",Tabla9[[#This Row],[FACTURACIÓN]]<1000,"AA",Tabla9[[#This Row],[FACTURACIÓN]]>=1000,"AAA")} -> AAA
A17: CACERES PINTO ALVARO DANIEL | B17: =+IF($B$4="TODOS",SUMIFS(Base_Precisa!X:X,Base_Precisa!J:J,Cálculo_Categorías!A17),SUMIFS(Base_Precisa!X:X,Base_Precisa!J:J,Cálculo_Categorías!A17,Base_Precisa!B:B,Cálculo_Categorías!$B$4)) -> 881.35 | C17: {=+_xlfn.IFS(Tabla5[[#This Row],[FACTURACIÓN]]<500,"A",Tabla5[[#This Row],[FACTURACIÓN]]<1000,"AA",Tabla5[[#This Row],[FACTURACIÓN]]>=1000,"AAA")} -> AA | E17: GAMARRA SALUD | F17: =+IF($F$4="TODOS",SUMIFS(Base_Precisa!X:X,Base_Precisa!K:K,Cálculo_Categorías!E17),SUMIFS(Base_Precisa!X:X,Base_Precisa!K:K,Cálculo_Categorías!E17,Base_Precisa!B:B,Cálculo_Categorías!$F$4)) -> 30101.66 | G17: {=+_xlfn.IFS(Tabla9[[#This Row],[FACTURACIÓN]]<200,"Sin Categoría",Tabla9[[#This Row],[FACTURACIÓN]]<500,"A",Tabla9[[#This Row],[FACTURACIÓN]]<1000,"AA",Tabla9[[#This Row],[FACTURACIÓN]]>=1000,"AAA")} -> AAA
A18: VILLAR CURAHUA MARCELA ALEJANDRA | B18: =+IF($B$4="TODOS",SUMIFS(Base_Precisa!X:X,Base_Precisa!J:J,Cálculo_Categorías!A18),SUMIFS(Base_Precisa!X:X,Base_Precisa!J:J,Cálculo_Categorías!A18,Base_Precisa!B:B,Cálculo_Categorías!$B$4)) -> 30101.66 | C18: {=+_xlfn.IFS(Tabla5[[#This Row],[FACTURACIÓN]]<500,"A",Tabla5[[#This Row],[FACTURACIÓN]]<1000,"AA",Tabla5[[#This Row],[FACTURACIÓN]]>=1000,"AAA")} -> AAA | E18: CONSULTORIO CUBANO COMAS | F18: =+IF($F$4="TODOS",SUMIFS(Base_Precisa!X:X,Base_Precisa!K:K,Cálculo_Categorías!E18),SUMIFS(Base_Precisa!X:X,Base_Precisa!K:K,Cálculo_Categorías!E18,Base_Precisa!B:B,Cálculo_Categorías!$F$4)) -> 4033.85 | G18: {=+_xlfn.IFS(Tabla9[[#This Row],[FACTURACIÓN]]<200,"Sin Categoría",Tabla9[[#This Row],[FACTURACIÓN]]<500,"A",Tabla9[[#This Row],[FACTURACIÓN]]<1000,"AA",Tabla9[[#This Row],[FACTURACIÓN]]>=1000,"AAA")} -> AAA
A19: RUIZ ROJAS PAUBLO ENRIQUE | B19: =+IF($B$4="TODOS",SUMIFS(Base_Precisa!X:X,Base_Precisa!J:J,Cálculo_Categorías!A19),SUMIFS(Base_Precisa!X:X,Base_Precisa!J:J,Cálculo_Categorías!A19,Base_Precisa!B:B,Cálculo_Categorías!$B$4)) -> 4033.85 | C19: {=+_xlfn.IFS(Tabla5[[#This Row],[FACTURACIÓN]]<500,"A",Tabla5[[#This Row],[FACTURACIÓN]]<1000,"AA",Tabla5[[#This Row],[FACTURACIÓN]]>=1000,"AAA")} -> AAA | E19: HOSPITAL 2 DE MAYO | F19: =+IF($F$4="TODOS",SUMIFS(Base_Precisa!X:X,Base_Precisa!K:K,Cálculo_Categorías!E19),SUMIFS(Base_Precisa!X:X,Base_Precisa!K:K,Cálculo_Categorías!E19,Base_Precisa!B:B,Cálculo_Categorías!$F$4)) -> 559.32 | G19: {=+_xlfn.IFS(Tabla9[[#This Row],[FACTURACIÓN]]<200,"Sin Categoría",Tabla9[[#This Row],[FACTURACIÓN]]<500,"A",Tabla9[[#This Row],[FACTURACIÓN]]<1000,"AA",Tabla9[[#This Row],[FACTURACIÓN]]>=1000,"AAA")} -> AA
... A45: DURAN ESPINOZA CESAR ARTURO | B45: =+IF($B$4="TODOS",SUMIFS(Base_Precisa!X:X,Base_Precisa!J:J,Cálculo_Categorías!A45),SUMIFS(Base_Precisa!X:X,Base_Precisa!J:J,Cálculo_Categorías!A45,Base_Precisa!B:B,Cálculo_Categorías!$B$4)) -> 661.01 | C45: {=+_xlfn.IFS(Tabla5[[#This Row],[FACTURACIÓN]]<500,"A",Tabla5[[#This Row],[FACTURACIÓN]]<1000,"AA",Tabla5[[#This Row],[FACTURACIÓN]]>=1000,"AAA")} -> AA | E45: CLINICA DIVINO NIÑO JESÚS | F45: =+IF($F$4="TODOS",SUMIFS(Base_Precisa!X:X,Base_Precisa!K:K,Cálculo_Categorías!E45),SUMIFS(Base_Precisa!X:X,Base_Precisa!K:K,Cálculo_Categorías!E45,Base_Precisa!B:B,Cálculo_Categorías!$F$4)) -> 0 | G45: {=+_xlfn.IFS(Tabla9[[#This Row],[FACTURACIÓN]]<200,"Sin Categoría",Tabla9[[#This Row],[FACTURACIÓN]]<500,"A",Tabla9[[#This Row],[FACTURACIÓN]]<1000,"AA",Tabla9[[#This Row],[FACTURACIÓN]]>=1000,"AAA")} -> Sin Categoría
A46: PALACIOS URIBE PAMELA CAROLINA | B46: =+IF($B$4="TODOS",SUMIFS(Base_Precisa!X:X,Base_Precisa!J:J,Cálculo_Categorías!A46),SUMIFS(Base_Precisa!X:X,Base_Precisa!J:J,Cálculo_Categorías!A46,Base_Precisa!B:B,Cálculo_Categorías!$B$4)) -> 0 | C46: {=+_xlfn.IFS(Tabla5[[#This Row],[FACTURACIÓN]]<500,"A",Tabla5[[#This Row],[FACTURACIÓN]]<1000,"AA",Tabla5[[#This Row],[FACTURACIÓN]]>=1000,"AAA")} -> A
A47: JAVE ESCALANTE LIZETH | B47: =+IF($B$4="TODOS",SUMIFS(Base_Precisa!X:X,Base_Precisa!J:J,Cálculo_Categorías!A47),SUMIFS(Base_Precisa!X:X,Base_Precisa!J:J,Cálculo_Categorías!A47,Base_Precisa!B:B,Cálculo_Categorías!$B$4)) -> 4466.04 | C47: {=+_xlfn.IFS(Tabla5[[#This Row],[FACTURACIÓN]]<500,"A",Tabla5[[#This Row],[FACTURACIÓN]]<1000,"AA",Tabla5[[#This Row],[FACTURACIÓN]]>=1000,"AAA")} -> AAA
A48: ALDAVE | B48: =+IF($B$4="TODOS",SUMIFS(Base_Precisa!X:X,Base_Precisa!J:J,Cálculo_Categorías!A48),SUMIFS(Base_Precisa!X:X,Base_Precisa!J:J,Cálculo_Categorías!A48,Base_Precisa!B:B,Cálculo_Categorías!$B$4)) -> 0 | C48: {=+_xlfn.IFS(Tabla5[[#This Row],[FACTURACIÓN]]<500,"A",Tabla5[[#This Row],[FACTURACIÓN]]<1000,"AA",Tabla5[[#This Row],[FACTURACIÓN]]>=1000,"AAA")} -> A
A49: ROMERO EDUARDO | B49: =+IF($B$4="TODOS",SUMIFS(Base_Precisa!X:X,Base_Precisa!J:J,Cálculo_Categorías!A49),SUMIFS(Base_Precisa!X:X,Base_Precisa!J:J,Cálculo_Categorías!A49,Base_Precisa!B:B,Cálculo_Categorías!$B$4)) -> 0 | C49: {=+_xlfn.IFS(Tabla5[[#This Row],[FACTURACIÓN]]<500,"A",Tabla5[[#This Row],[FACTURACIÓN]]<1000,"AA",Tabla5[[#This Row],[FACTURACIÓN]]>=1000,"AAA")} -> A
A50: LLERENA LOYOLA ELSA YESENIA | B50: =+IF($B$4="TODOS",SUMIFS(Base_Precisa!X:X,Base_Precisa!J:J,Cálculo_Categorías!A50),SUMIFS(Base_Precisa!X:X,Base_Precisa!J:J,Cálculo_Categorías!A50,Base_Precisa!B:B,Cálculo_Categorías!$B$4)) -> 2728.78 | C50: {=+_xlfn.IFS(Tabla5[[#This Row],[FACTURACIÓN]]<500,"A",Tabla5[[#This Row],[FACTURACIÓN]]<1000,"AA",Tabla5[[#This Row],[FACTURACIÓN]]>=1000,"AAA")} -> AAA
A51: GAMERO FERNANDEZ EBERTH | B51: =+IF($B$4="TODOS",SUMIFS(Base_Precisa!X:X,Base_Precisa!J:J,Cálculo_Categorías!A51),SUMIFS(Base_Precisa!X:X,Base_Precisa!J:J,Cálculo_Categorías!A51,Base_Precisa!B:B,Cálculo_Categorías!$B$4)) -> 0 | C51: {=+_xlfn.IFS(Tabla5[[#This Row],[FACTURACIÓN]]<500,"A",Tabla5[[#This Row],[FACTURACIÓN]]<1000,"AA",Tabla5[[#This Row],[FACTURACIÓN]]>=1000,"AAA")} -> A
A52: TERAN SANCHEZ GUILLERMO ALFONSO | B52: =+IF($B$4="TODOS",SUMIFS(Base_Precisa!X:X,Base_Precisa!J:J,Cálculo_Categorías!A52),SUMIFS(Base_Precisa!X:X,Base_Precisa!J:J,Cálculo_Categorías!A52,Base_Precisa!B:B,Cálculo_Categorías!$B$4)) -> 254.23 | C52: {=+_xlfn.IFS(Tabla5[[#This Row],[FACTURACIÓN]]<500,"A",Tabla5[[#This Row],[FACTURACIÓN]]<1000,"AA",Tabla5[[#This Row],[FACTURACIÓN]]>=1000,"AAA")} -> A
A53: CHACÓN ENRIQUE | B53: =+IF($B$4="TODOS",SUMIFS(Base_Precisa!X:X,Base_Precisa!J:J,Cálculo_Categorías!A53),SUMIFS(Base_Precisa!X:X,Base_Precisa!J:J,Cálculo_Categorías!A53,Base_Precisa!B:B,Cálculo_Categorías!$B$4)) -> 796.6 | C53: {=+_xlfn.IFS(Tabla5[[#This Row],[FACTURACIÓN]]<500,"A",Tabla5[[#This Row],[FACTURACIÓN]]<1000,"AA",Tabla5[[#This Row],[FACTURACIÓN]]>=1000,"AAA")} -> AA
A54: HUANAMPA CARLOS | B54: =+IF($B$4="TODOS",SUMIFS(Base_Precisa!X:X,Base_Precisa!J:J,Cálculo_Categorías!A54),SUMIFS(Base_Precisa!X:X,Base_Precisa!J:J,Cálculo_Categorías!A54,Base_Precisa!B:B,Cálculo_Categorías!$B$4)) -> 338.98 | C54: {=+_xlfn.IFS(Tabla5[[#This Row],[FACTURACIÓN]]<500,"A",Tabla5[[#This Row],[FACTURACIÓN]]<1000,"AA",Tabla5[[#This Row],[FACTURACIÓN]]>=1000,"AAA")} -> A
A55: SANCHEZ CUEVA SERGIO | B55: =+IF($B$4="TODOS",SUMIFS(Base_Precisa!X:X,Base_Precisa!J:J,Cálculo_Categorías!A55),SUMIFS(Base_Precisa!X:X,Base_Precisa!J:J,Cálculo_Categorías!A55,Base_Precisa!B:B,Cálculo_Categorías!$B$4)) -> 677.96 | C55: {=+_xlfn.IFS(Tabla5[[#This Row],[FACTURACIÓN]]<500,"A",Tabla5[[#This Row],[FACTURACIÓN]]<1000,"AA",Tabla5[[#This Row],[FACTURACIÓN]]>=1000,"AAA")} -> AA
A56: CABRERA YAIMA | B56: =+IF($B$4="TODOS",SUMIFS(Base_Precisa!X:X,Base_Precisa!J:J,Cálculo_Categorías!A56),SUMIFS(Base_Precisa!X:X,Base_Precisa!J:J,Cálculo_Categorías!A56,Base_Precisa!B:B,Cálculo_Categorías!$B$4)) -> 0 | C56: {=+_xlfn.IFS(Tabla5[[#This Row],[FACTURACIÓN]]<500,"A",Tabla5[[#This Row],[FACTURACIÓN]]<1000,"AA",Tabla5[[#This Row],[FACTURACIÓN]]>=1000,"AAA")} -> A
A57: BARRANTES RAMIREZ ELENA JESUS AMERICA | B57: =+IF($B$4="TODOS",SUMIFS(Base_Precisa!X:X,Base_Precisa!J:J,Cálculo_Categorías!A57),SUMIFS(Base_Precisa!X:X,Base_Precisa!J:J,Cálculo_Categorías!A57,Base_Precisa!B:B,Cálculo_Categorías!$B$4)) -> 288.13 | C57: {=+_xlfn.IFS(Tabla5[[#This Row],[FACTURACIÓN]]<500,"A",Tabla5[[#This Row],[FACTURACIÓN]]<1000,"AA",Tabla5[[#This Row],[FACTURACIÓN]]>=1000,"AAA")} -> A
... A106: MUNAYCO GUILLEN FERNANDO | B106: =+IF($B$4="TODOS",SUMIFS(Base_Precisa!X:X,Base_Precisa!J:J,Cálculo_Categorías!A106),SUMIFS(Base_Precisa!X:X,Base_Precisa!J:J,Cálculo_Categorías!A106,Base_Precisa!B:B,Cálculo_Categorías!$B$4)) -> 644.06 | C106: {=+_xlfn.IFS(Tabla5[[#This Row],[FACTURACIÓN]]<500,"A",Tabla5[[#This Row],[FACTURACIÓN]]<1000,"AA",Tabla5[[#This Row],[FACTURACIÓN]]>=1000,"AAA")} -> AA

Sheet Categoría_Médicos
A1: OCTUBRE | F1: SETIEMBRE | K1: AGOSTO | P1: JULIO
A2: DETALLE | B2: S/. | C2: # | D2: % | F2: DETALLE | G2: S/. | H2: # | I2: % | K2: DETALLE | L2: S/. | M2: # | N2: % | P2: DETALLE | Q2: S/. | R2: # | S2: %
A3: AAA | B3: =+SUMIF(Tabla421[CATEGORÍA],"AAA",Tabla421[FACTURACIÓN]) -> 4313.56 | C3: =+COUNTIF(Tabla4[CATEGORÍA],"AAA") -> 10 | D3: =C3/$H$6 -> 0.24390244 | F3: AAA | G3: =+SUMIF(Tabla4[CATEGORÍA],"AAA",Tabla4[FACTURACIÓN]) -> 34864.21 | H3: =+COUNTIF(Tabla4[CATEGORÍA],"AAA") -> 10 | I3: =H3/$H$6 -> 0.24390244 | K3: AAA | L3: =+SUMIF(Tabla6[CATEGORÍA],"AAA",Tabla6[FACTURACIÓN]) -> 18588.94 | M3: =+COUNTIF(Tabla6[CATEGORÍA],"AAA") -> 5 | N3: =M3/$M$6 -> 0.086206897 | P3: AAA | Q3: =+SUMIF(Tabla8[CATEGORÍA],"AAA",Tabla8[FACTURACIÓN]) -> 18406.77 | R3: =+COUNTIF(Tabla8[CATEGORÍA],"AAA") -> 4 | S3: =R3/$R$7 -> 0.12121212
A4: AA | B4: =+SUMIF(Tabla4[CATEGORÍA],"AA",Tabla4[FACTURACIÓN]) -> 3830.47 | C4: =+COUNTIF(Tabla4[CATEGORÍA],"AA") -> 5 | D4: =C4/$H$6 -> 0.12195122 | F4: AA | G4: =+SUMIF(Tabla4[CATEGORÍA],"AA",Tabla4[FACTURACIÓN]) -> 3830.47 | H4: =+COUNTIF(Tabla4[CATEGORÍA],"AA") -> 5 | I4: =H4/$H$6 -> 0.12195122 | K4: AA | L4: =+SUMIF(Tabla6[CATEGORÍA],"AA",Tabla6[FACTURACIÓN]) -> 8491.44 | M4: =+COUNTIF(Tabla6[CATEGORÍA],"AA") -> 11 | N4: =M4/$M$6 -> 0.18965517 | P4: AA | Q4: =+SUMIF(Tabla8[CATEGORÍA],"AA",Tabla8[FACTURACIÓN]) -> 7512.65 | R4: =+COUNTIF(Tabla8[CATEGORÍA],"AA") -> 10 | S4: =R4/$R$7 -> 0.3030303
A5: A | B5: =+SUMIF(Tabla421[CATEGORÍA],"A",Tabla421[FACTURACIÓN]) -> 1970.31 | C5: =+COUNTIF(Tabla4[CATEGORÍA],"A") -> 26 | D5: =C5/$H$6 -> 0.63414634 | F5: A | G5: =+SUMIF(Tabla4[CATEGORÍA],"A",Tabla4[FACTURACIÓN]) -> 6262.63 | H5: =+COUNTIF(Tabla4[CATEGORÍA],"A") -> 26 | I5: =H5/$H$6 -> 0.63414634 | K5: A | L5: =+SUMIF(Tabla6[CATEGORÍA],"A",Tabla6[FACTURACIÓN]) -> 9296.47 | M5: =+COUNTIF(Tabla6[CATEGORÍA],"A") -> 42 | N5: =M5/$M$6 -> 0.72413793 | P5: A | Q5: =+SUMIF(Tabla8[CATEGORÍA],"A",Tabla8[FACTURACIÓN]) -> 3728.77 | R5: =+COUNTIF(Tabla8[CATEGORÍA],"A") -> 11 | S5: =R5/$R$7 -> 0.33333333
A6: Total | B6: =+SUM(Tabla421[FACTURACIÓN]) -> 6283.87 | C6: =+COUNT(Tabla421[FACTURACIÓN]) -> 10 | D6: =C6/$H$6 -> 0.24390244 | F6: Total | G6: =+SUM(Tabla4[FACTURACIÓN]) -> 44957.31 | H6: =+COUNT(Tabla4[FACTURACIÓN]) -> 41 | I6: =H6/$H$6 -> 1 | K6: Total | L6: =+SUM(Tabla6[FACTURACIÓN]) -> 36376.85 | M6: =+COUNT(Tabla6[FACTURACIÓN]) -> 58 | N6: =M6/$M$6 -> 1 | P6: Sin Categoría | Q6: =+SUMIF(Tabla8[CATEGORÍA],"Sin Categoría",Tabla8[FACTURACIÓN]) -> 1237.27 | R6: =+COUNTIF(Tabla8[CATEGORÍA],"Sin Categoría") -> 8 | S6: =R6/$R$7 -> 0.24242424
A7: MEDICO | B7: FACTURACIÓN | C7: CATEGORÍA | F7: MEDICO | G7: FACTURACIÓN | H7: CATEGORÍA | K7: MEDICO | L7: FACTURACIÓN | M7: CATEGORÍA | P7: Total | Q7: =+SUM(Tabla8[FACTURACIÓN]) -> 30885.46 | R7: =+COUNT(Tabla8[FACTURACIÓN]) -> 33 | S7: =R7/$R$7 -> 1
A8: VILLAR CURAHUA MARCELA ALEJANDRA | B8: 1305.09 | C8: AAA | F8: ORNA ACOSTA JORGE AQUILES | G8: 135.59 | H8: A | K8: ORNA ACOSTA JORGE AQUILES | L8: 186.44 | M8: A | P8: MEDICO | Q8: FACTURACIÓN | R8: CATEGORÍA
A9: FERNANDEZ GUTIERREZ OLGA PATRICIA | B9: 326.27 | C9: A | F9: HUARANGA RUIZ CORNEJO JORGE ERNESTO | G9: 474.57 | H9: A | K9: TORRES LEAL ADOLFO LEON | L9: 135.59 | M9: A | P9: FIERRO LEANDRO | Q9: 10927.98 | R9: AAA
A10: SAPAICO VICUÑA AUGUSTO RODRIGO | B10: 1258.47 | C10: AAA | F10: AGRAMONTE ZEA EDILBERTO | G10: 1660.99 | H10: AAA | K10: HUARANGA RUIZ CORNEJO JORGE ERNESTO | L10: 135.59 | M10: A | P10: VILLAR CURAHUA MARCELA ALEJANDRA | Q10: 5067.78 | R10: AAA
A11: MANCHEGO LOMBARDI MICHAEL | B11: 457.62 | C11: A | F11: GUTARRA PAUCAR JULIA KARINA | G11: 135.59 | H11: A | K11: AGRAMONTE ZEA EDILBERTO | L11: 898.3 | M11: AA | P11: CRISPIN MORALES NANCY JENNY | Q11: 1275.43 | R11: AAA
A12: PALACIOS URIBE PAMELA CAROLINA | B12: 1750 | C12: AAA | F12: VILLAR CURAHUA MARCELA ALEJANDRA | G12: 8864.4 | H12: AAA | K12: GUTARRA PAUCAR JULIA KARINA | L12: 2283.88 | M12: AAA | P12: RUIZ ROJAS PAUBLO ENRIQUE | Q12: 1135.58 | R12: AAA
A13: RAMIREZ ORBE JOSÉ LUIS | B13: 101.69 | C13: A | F13: RUIZ ROJAS PAUBLO ENRIQUE | G13: 728.8 | H13: AA | K13: VILLAR CURAHUA MARCELA ALEJANDRA | L13: 5872.87 | M13: AAA | P13: SAPAICO VICUÑA AUGUSTO RODRIGO | Q13: 983.04 | R13: AA
A14: BARZOLA CORDERO VIOLETA | B14: 288.13 | C14: A | F14: FERNANDEZ GUTIERREZ OLGA PATRICIA | G14: 322.03 | H14: A | K14: RUIZ ROJAS PAUBLO ENRIQUE | L14: 593.21 | M14: AA | P14: PALACIOS URIBE PAMELA CAROLINA | Q14: 978.81 | R14: AA
A15: SALAZAR FUERTES JESUS ABEL | B15: 338.98 | C15: A | F15: ROJAS AQUINO EVELING KARINA | G15: 1762.69 | H15: AAA | K15: CASTRO TAMANAJA VANIA VIVIAN | L15: 186.44 | M15: A | P15: LLERENA LOYOLA ELSA YESENIA | Q15: 949.14 | R15: AA
A16: ESPINOZA LAVALLE CESAR FRANKZ | B16: 322.03 | C16: A | F16: ACOSTA VIERA ALVARO | G16: 745.75 | H16: AA | K16: FERNANDEZ GUTIERREZ OLGA PATRICIA | L16: 101.69 | M16: A | P16: CHACÓN ENRIQUE | Q16: 796.6 | R16: AA
A17: MONTERO PACORA YHASSER ZOSIMO | B17: 135.59 | C17: A | F17: FIERRO LEANDRO | G17: 11254.21 | H17: AAA | K17: CRISPIN MORALES NANCY JENNY | L17: 1322.04 | M17: AAA | P17: FERNANDEZ OLGA PATRICIA | Q17: 779.65 | R17: AA
F18: SAPAICO VICUÑA AUGUSTO RODRIGO | G18: 1322.01 | H18: AAA | K18: ROJAS AQUINO EVELING KARINA | L18: 457.62 | M18: A | P18: BARRETO VIRTO JOSE EMMANUEL | Q18: 762.71 | R18: AA
F19: HUAMAN RIOS LUIS ENRIQUE | G19: 135.59 | H19: A | K19: ACOSTA VIERA ALVARO | L19: 440.67 | M19: A | P19: ROJAS AQUINO EVELING KARINA | Q19: 694.91 | R19: AA
F20: MANCHEGO LOMBARDI MICHAEL | G20: 1135.57 | H20: AAA | K20: FIERRO LEANDRO | L20: 7805.08 | M20: AAA | P20: MENDOZA DIAZ NORA BEATRIZ | Q20: 550.85 | R20: AA
F21: REYES DIAZ JORGE RICARDO | G21: 152.54 | H21: A | K21: SAPAICO VICUÑA AUGUSTO RODRIGO | L21: 966.09 | M21: AA | P21: GUTARRA PAUCAR JULIA | Q21: 508.47 | R21: AA
F22: PALACIOS URIBE PAMELA CAROLINA | G22: 2949.14 | H22: AAA | K22: HUAMAN RIOS LUIS ENRIQUE | L22: 474.57 | M22: A | P22: GAMERO FERNANDEZ EBERTH | Q22: 508.47 | R22: AA
F23: DURAN ESPINOZA CESAR ARTURO | G23: 135.59 | H23: A | K23: MANCHEGO LOMBARDI MICHAEL | L23: 783.9 | M23: AA | P23: AGRAMONTE ZEA EDILBERTO | Q23: 474.57 | R23: A
F24: PALACIOS URIBE PAMELA CAROLINA | G24: 271.18 | H24: A | K24: ALEMAÑY ERNESTO | L24: 186.44 | M24: A | P24: HUAMAN RIOS LUIS ENRIQUE | Q24: 423.72 | R24: A
F25: JAVE ESCALANTE LIZETH | G25: 2499.96 | H25: AAA | K25: ESPEJO ALVA JULIO EDWIN | L25: 135.59 | M25: A | P25: JAVE ESCALANTE LIZETH | Q25: 372.88 | R25: A
F26: LLERENA LOYOLA ELSA YESENIA | G26: 949.14 | H26: AA | K26: REYES DIAZ JORGE RICARDO | L26: 135.59 | M26: A | P26: REYES DIAZ JORGE RICARDO | Q26: 372.88 | R26: A
F27: BARRETO VIRTO JOSE EMMANUEL | G27: 474.57 | H27: A | K27: FONTENLA SERNA DAVID IVAN | L27: 737.29 | M27: AA | P27: DURAN ESPINOZA CESAR ARTURO | Q27: 338.98 | R27: A
F28: ISABEL PALACIOS RAISA LORENA | G28: 372.88 | H28: A | K28: PALACIOS URIBE PAMELA CAROLINA | L28: 275.42 | M28: A | P28: HUANAMPA CARLOS | Q28: 338.98 | R28: A
F29: PACHAS CHURA LIDIA VANESSA | G29: 847.46 | H29: AA | K29: DURAN ESPINOZA CESAR ARTURO | L29: 186.44 | M29: A | P29: SANCHEZ SERGIO | Q29: 338.98 | R29: A
... F41: ROMAN FRANCISCO | G41: 1144.06 | H41: AAA | K41: POMAZONGO GOYAS MANUEL ALEJANDRO | L41: 152.54 | M41: A | P41: TERAN SANCHEZ GUILLERMO ALFONSO | Q41: 101.69 | R41: Sin Categoría
F42: ESPINOZA LAVALLE CESAR FRANKZ | G42: 559.32 | H42: AA | K42: ISABEL PALACIOS RAISA LORENA | L42: 203.39 | M42: A
F43: LEON SUAREZ LUIS NICOLAS | G43: 2271.18 | H43: AAA | K43: TARAZONA CHAVEZ ROSAMARIA | L43: 135.59 | M43: A
F44: MONTERO PACORA YHASSER ZOSIMO | G44: 135.59 | H44: A | K44: RAMOS COOPER SHIRLEY IVONNE | L44: 288.13 | M44: A
F45: TELMA MESA EDITH | G45: 152.54 | H45: A | K45: RODRIGUEZ RIVERO DARLEN | L45: 135.59 | M45: A
F46: ARAMBURU CASTRO HUGO ANIBAL | G46: 169.49 | H46: A | K46: PACHAS CHURA LIDIA VANESSA | L46: 288.13 | M46: A
F47: CERNA TAFUR ELAR LALO | G47: 152.54 | H47: A | K47: TANAKA LUIS | L47: 457.62 | M47: A
F48: MUNAYCO GUILLEN FERNANDO | G48: 135.59 | H48: A | K48: HUAMAN GONZALEZ JORGE ANTONIO | L48: 288.13 | M48: A
K49: BACA CHAVEZ MERCEDES | L49: 135.59 | M49: A
K50: ENCISO QUILLA KARIN | L50: 275.42 | M50: A
K51: MARIN CHAVEZ JUAN JOSE | L51: 186.44 | M51: A
K52: PEREZ MARTINOT MANUEL RAUL | L52: 372.88 | M52: A
K53: RAMIREZ ORBE JOSÉ LUIS | L53: 135.59 | M53: A
K54: PAITAN QUISPE EMILYN | L54: 271.18 | M54: A
K55: RAMOS ALIAGA DAVID | L55: 135.59 | M55: A
K56: TUME JARA LUCIA MARIA | L56: 186.44 | M56: A
K57: SONCCO HUISA BACILIO | L57: 135.59 | M57: A
K58: SALGADO CERRATE CARLOS | L58: 271.18 | M58: A
K59: CAMPANA BELLOTA LUIS | L59: 135.59 | M59: A
K60: BARZOLA CORDERO VIOLETA | L60: 186.44 | M60: A
... K65: BERROCAL VIVIANA | L65: 101.69 | M65: A

Sheet Categoría_Institución
A1: SETIEMBRE | F1: AGOSTO | K1: JULIO
A2: DETALLE | B2: S/. | C2: # | D2: % | F2: DETALLE | G2: S/. | H2: # | I2: % | K2: DETALLE | L2: S/. | M2: # | N2: %
A3: AAA | B3: =+SUMIF(Tabla414[CATEGORÍA],"AAA",Tabla414[FACTURACIÓN]) -> 13220.34 | C3: =+COUNTIF(Tabla414[CATEGORÍA],"AAA") -> 2 | D3: =C3/$C$7 -> 0.16666667 | F3: AAA | G3: =+SUMIF(Tabla41416[CATEGORÍA],"AAA",Tabla41416[FACTURACIÓN]) -> 24821.94 | H3: =+COUNTIF(Tabla41416[CATEGORÍA],"AAA") -> 8 | I3: =H3/$H$7 -> 0.27586207 | K3: AAA | L3: =+SUMIF(Tabla41418[CATEGORÍA],"AAA",Tabla41418[FACTURACIÓN]) -> 21707.58 | M3: =+COUNTIF(Tabla41418[CATEGORÍA],"AAA") -> 6 | N3: =M3/$M$7 -> 0.35294118
A4: AA | B4: =+SUMIF(Tabla414[CATEGORÍA],"AA",Tabla414[FACTURACIÓN]) -> 1440.67 | C4: =+COUNTIF(Tabla414[CATEGORÍA],"AA") -> 2 | D4: =C4/$C$7 -> 0.16666667 | F4: AA | G4: =+SUMIF(Tabla41416[CATEGORÍA],"AA",Tabla41416[FACTURACIÓN]) -> 2716.08 | H4: =+COUNTIF(Tabla41416[CATEGORÍA],"AA") -> 4 | I4: =H4/$H$7 -> 0.13793103 | K4: AA | L4: =+SUMIF(Tabla41418[CATEGORÍA],"AA",Tabla41418[FACTURACIÓN]) -> 3754.21 | M4: =+COUNTIF(Tabla41418[CATEGORÍA],"AA") -> 5 | N4: =M4/$M$7 -> 0.29411765
A5: A | B5: =+SUMIF(Tabla414[CATEGORÍA],"A",Tabla414[FACTURACIÓN]) -> 813.55 | C5: =+COUNTIF(Tabla414[CATEGORÍA],"A") -> 2 | D5: =C5/$C$7 -> 0.16666667 | F5: A | G5: =+SUMIF(Tabla41416[CATEGORÍA],"A",Tabla41416[FACTURACIÓN]) -> 2444.88 | H5: =+COUNTIF(Tabla41416[CATEGORÍA],"A") -> 7 | I5: =H5/$H$7 -> 0.24137931 | K5: A | L5: =+SUMIF(Tabla41418[CATEGORÍA],"A",Tabla41418[FACTURACIÓN]) -> 1898.28 | M5: =+COUNTIF(Tabla41418[CATEGORÍA],"A") -> 5 | N5: =M5/$M$7 -> 0.29411765
A6: Sin Categoría | B6: =+SUMIF(Tabla414[CATEGORÍA],"Sin Categoría",Tabla414[FACTURACIÓN]) -> 936.43 | C6: =+COUNTIF(Tabla414[CATEGORÍA],"Sin Categoría") -> 6 | D6: =C6/$C$7 -> 0.5 | F6: Sin Categoría | G6: =+SUMIF(Tabla41416[CATEGORÍA],"Sin Categoría",Tabla41416[FACTURACIÓN]) -> 1525.4 | H6: =+COUNTIF(Tabla41416[CATEGORÍA],"Sin Categoría") -> 10 | I6: =H6/$H$7 -> 0.34482759 | K6: Sin Categoría | L6: =+SUMIF(Tabla41418[CATEGORÍA],"Sin Categoría",Tabla41418[FACTURACIÓN]) -> 152.54 | M6: =+COUNTIF(Tabla41418[CATEGORÍA],"Sin Categoría") -> 1 | N6: =M6/$M$7 -> 0.058823529
A7: Total | B7: =+SUM(Tabla414[FACTURACIÓN]) -> 16410.99 | C7: =+COUNT(Tabla414[FACTURACIÓN]) -> 12 | D7: =C7/$C$7 -> 1 | F7: Total | G7: =+SUM(Tabla41416[FACTURACIÓN]) -> 31508.3 | H7: =+COUNT(Tabla41416[FACTURACIÓN]) -> 29 | I7: =H7/$H$7 -> 1 | K7: Total | L7: =+SUM(Tabla41418[FACTURACIÓN]) -> 27512.61 | M7: =+COUNT(Tabla41418[FACTURACIÓN]) -> 17 | N7: =M7/$M$7 -> 1
A8: MEDICO | B8: FACTURACIÓN | C8: CATEGORÍA | F8: MEDICO | G8: FACTURACIÓN | H8: CATEGORÍA | K8: MEDICO | L8: FACTURACIÓN | M8: CATEGORÍA
A9: GAMARRA SALUD | B9: 6728.8 | C9: AAA | F9: POLICLÍNICO DIVINO NIÑO JESÚS | G9: 7805.08 | H9: AAA | K9: POLICLÍNICO DIVINO NIÑO JESÚS | L9: 10927.98 | M9: AAA
A10: POLICLÍNICO DIVINO NIÑO JESÚS | B10: 6491.54 | C10: AAA | F10: GAMARRA SALUD | G10: 5872.87 | H10: AAA | K10: GAMARRA SALUD | L10: 5067.78 | M10: AAA
A11: CONSULTORIO PARTICULAR | B11: 728.81 | C11: AA | F11: HOSPITAL LOAYZA | G11: 2610.14 | H11: AAA | K11: HOSPITAL LOAYZA | L11: 1745.74 | M11: AAA
A12: HOSPITAL LOAYZA | B12: 711.86 | C12: AA | F12: CLÍNICA SAN CAMILO | G12: 2283.88 | H12: AAA | K12: HOSPITAL ALMENARA | L12: 1461.87 | M12: AAA
A13: HOSPITAL DE LA SOLIDARIDAD SJL | B13: 474.57 | C13: A | F13: CONSULTORIO PARTICULAR | G13: 2072.01 | H13: AAA | K13: CONSULTORIO PARTICULAR | L13: 1368.63 | M13: AAA
A14: HOSPITAL DE POLICIA | B14: 338.98 | C14: A | F14: HOSPITAL ALMENARA | G14: 1644.07 | H14: AAA | K14: CONSULTORIO CUBANO COMAS | L14: 1135.58 | M14: AAA
A15: ESSALUD ATE | B15: 186.44 | C15: Sin Categoría | F15: CLINICA MAISON DE SANTE | G15: 1508.47 | H15: AAA | K15: CLINICA MAISON DE SANTE | L15: 949.14 | M15: AA
A16: HOSPITAL REBAGLEATI | B16: 186.44 | C16: Sin Categoría | F16: HOSPITAL NAVAL | G16: 1025.42 | H16: AAA | K16: HOSPITAL HIPOLITO UNANUE | L16: 796.6 | M16: AA
A17: HOSPITAL CARRION | B17: 152.54 | C17: Sin Categoría | F17: HOSPITAL DE LA SOLIDARIDAD SJL | G17: 898.3 | H17: AA | K17: HOSPITAL DE POLICIA | L17: 762.71 | M17: AA
A18: HOSPITAL ALMENARA | B18: 139.83 | C18: Sin Categoría | F18: HOSPITAL SABOGAL | G18: 661.01 | H18: AA | K18: POLICLÍNICO ESPÍRITU SANTO | L18: 694.91 | M18: AA
A19: HOSPITAL MONGRUT | B19: 135.59 | C19: Sin Categoría | F19: CONSULTORIO CUBANO COMAS | G19: 593.21 | H19: AA | K19: ESSALUD ATE | L19: 550.85 | M19: AA
A20: CLÍNICA SAN CAMILO | B20: 135.59 | C20: Sin Categoría | F20: HOSPITAL SAN JUAN DE LURIGANCHO | G20: 563.56 | H20: AA | K20: HOSPITAL DE LA SOLIDARIDAD SJL | L20: 474.57 | M20: A
F21: HOSPITAL SERGIO BERNALES | G21: 474.57 | H21: A | K21: HOSPITAL SERGIO BERNALES | L21: 423.72 | M21: A
F22: POLICLÍNICO ESPÍRITU SANTO | G22: 457.62 | H22: A | K22: HOSPITAL CAYETANO HEREDIA | L22: 372.88 | M22: A
F23: CONSULTORIO | G23: 372.88 | H23: A | K23: CONSULTORIO LA MOLINA | L23: 338.98 | M23: A
F24: HOSPITAL INO | G24: 305.08 | H24: A | K24: OPELUCE LINCE | L24: 288.13 | M24: A
F25: POLICLINICO SAN JUAN DE MIRAFLORES | G25: 288.13 | H25: A | K25: HOSPITAL MONGRUT | L25: 152.54 | M25: Sin Categoría
F26: SISOL DE LOS OLIVOS | G26: 275.42 | H26: A
F27: HOSPITAL CAYETANO HEREDIA | G27: 271.18 | H27: A
F28: CLINICA LA LUZ | G28: 186.44 | H28: Sin Categoría
F29: CONSULTORIO LA MOLINA | G29: 186.44 | H29: Sin Categoría
F30: HOSPITAL DE LA MARINA | G30: 186.44 | H30: Sin Categoría
F31: HOSPITAL 2 DE MAYO | G31: 186.44 | H31: Sin Categoría
F32: HOSPITAL HIPOLITO UNANUE | G32: 135.59 | H32: Sin Categoría
F33: HOSPITAL DE LA POLICIA | G33: 135.59 | H33: Sin Categoría
F34: CLÍNICA SAN FELIPE LA MOLINA | G34: 135.59 | H34: Sin Categoría
F35: ECOCENTER | G35: 135.59 | H35: Sin Categoría
F36: HOSPITAL MILITAR | G36: 135.59 | H36: Sin Categoría
F37: HOSPITAL MARIA AUXILIADORA | G37: 101.69 | H37: Sin Categoría

Sheet Detalle
A1: MES | B1: Setiembre
A3: Etiquetas de fila | B3: S/. Imp. | C3: # Cant.
A4: FACOEMULSIFICACION PRIMIUM | B4: 15889.82 | C4: 15
A5: ECOGRAFIA OCULAR GENERAL SCAN A,B | B5: 4203.29 | C5: 33
A6: OCT DE NERVIO OPTICO Y CELULAS GANGLION | B6: 3711.85 | C6: 20
A7: CAMPIMETRIA (CAMPO VISUAL) | B7: 3254.16 | C7: 24
A8: TOPOGRAFIA CORNEAL | B8: 2898.26 | C8: 21
A9: OCT DE MACULA | B9: 2033.89 | C9: 11
A10: BIOMETRIA IOL MASTER 700 | B10: 2025.39 | C10: 14
A11: MICROSCOPIA ESPECULAR | B11: 1957.58 | C11: 15
A12: MININUC | B12: 1805.09 | C12: 2
A13: CIRUGIA REFRACTIVA TRANS PRK | B13: 1440.67 | C13: 2
A14: ANGIOGRAFIA CON FLUORESCEINA | B14: 1355.92 | C14: 4
A15: FACOEMULSIFICACION COMPLICADA | B15: 1169.49 | C15: 1
... A33: Total general | B33: 46215.76 | C33: 224

Sheet GUIA_DASHBOARD
A1: PRECISA | GUÍA PARA ACTUALIZACIÓN MENSUAL
A2: OBJETIVO | B2: Conservar las bases y cinco hojas principales para consultar en el dashboard.
A3: HOJA | B3: QUÉ HACER CADA MES
A4: Base_Precisa | B4: Pegar nuevas filas al final, sin borrar meses anteriores. Completar la columna MES.
A5: Cálculo_Categorías | B5: Vista de cálculos; no pegar encima de las fórmulas. Revisar mes seleccionado.
A6: Categoría_Médicos | B6: Vista de indicadores por mes; revisar el nuevo corte y sus referencias.
A7: Categoría_Institución | B7: Vista de indicadores por mes; revisar el nuevo corte y sus referencias.
A8: Detalle | B8: Vista por servicio; actualizar o regenerar el detalle del mes.
A9: HOJAS DE APOYO
A10: Médicos | B10: Registro operativo: confirmar si alimenta Base_Precisa para no duplicar registros.
A11: Cuentas | B11: Actualizar solo si cambian datos bancarios. Mantener permisos restringidos.
A12: Bonos2 | B12: Actualizar solo cuando cambien tarifas/bonos.
A13: PROCEDIMIENTO
A14: 1 | B14: Realiza una copia de seguridad del archivo antes del cierre mensual.
A15: 2 | B15: Agrega los nuevos registros en la base correspondiente sin modificar encabezados.
A16: 3 | B16: Verifica fechas, MES, importes, nombres e identificadores para evitar duplicados.
A17: 4 | B17: Revisa fórmulas y totales de las vistas de cálculo; no sobreescribas fórmulas.
A18: 5 | B18: Usa las hojas de reporte como origen para visualizar resultados en el dashboard.
A19: IMPORTANTE | B19: Subir este Excel a Drive no conecta automáticamente el dashboard HTML. Requiere una conexión/importación de datos independiente.
